Workbook
Name Расходы_список: Настройки!$J$6:INDEX(Настройки!$J:$J,MAX(6,SUMPRODUCT(MAX((Настройки!$J$6:$J$35<>"")*ROW(Настройки!$J$6:$J$35)))))
Name Доходы_список: Настройки!$L$6:INDEX(Настройки!$L:$L,MAX(6,SUMPRODUCT(MAX((Настройки!$L$6:$L$17<>"")*ROW(Настройки!$L$6:$L$17)))))
Name Счета_список: Настройки!$N$6:INDEX(Настройки!$N:$N,MAX(6,SUMPRODUCT(MAX((Настройки!$N$6:$N$17<>"")*ROW(Настройки!$N$6:$N$17)))))
Name Даты_месяца: Операции!$S$10:INDEX(Операции!$S:$S,9+Операции!$S$9)

Sheet Инструкция
B2: Трекер и планер расходов
B3: План и факт в одном файле · помесячная статистика за учётный год · всё считается формулами
B5: Куда что вносить
B6: Операции | C6: Каждый день: что потратила, что пришло, откуда и куда. Тип «Перевод» — снятие наличных, погашение кредитки, перевод между картами: он меняет только остатки счетов.
B7: Журнал | C7: Запланированные разовые траты: дата, категория, что, сумма, статус «Запланировано». Заплатила — «Оплачено», счёт (и сумма факт, если отличалась). В «Операции» её не вносишь.
B8: Постоянные | C8: Аренда, связь, подписки, зарплата — один раз строкой. Каждый месяц: ✓ — оплачено по плану, число — оплачено столько, пусто — ещё нет. «Действует с / по» — для подписок, которые начинаются или заканчиваются.
B9: Покупки | C9: Крупные покупки с датой. Купила — ✓ в «Куплено», цена факт и счёт.
B10: Долги | C10: Кредиты и рассрочки с прогрессом погашения.
B11: Правило | C11: Каждая трата живёт в одном месте. Если в «Операциях» или «Журнале» появится то, что уже есть в другом месте, колонка «Возможный дубль» подсветится жёлтым.
B13: Что смотреть
B14: Счета | C14: Сколько сейчас на каждой карте, в наличных и сколько долга по кредитке. Остатки на начало вводишь один раз; внизу — проверка, нет ли оплат без счёта.
B15: Месяц | C15: Выбери любой месяц учётного года: по категориям лимит, план, факт, остаток лимита; куда ушли деньги и траты по дням.
B16: Прогноз | C16: Три месяца вперёд по неделям: хватит ли денег и где остаток опускается ниже подушки.
B17: Статистика | C17: 12 месяцев подряд: доход и расход план/факт, баланс, накоплено, самый дорогой месяц; таблица «категория × месяц» с подсветкой и главные статьи за год.
B19: Настройки
B20: Прогноз с | C20: Месяц начала прогноза — сдвигай как хочешь.
B21: Учёт с | C21: Начало учётного года (сейчас октябрь 2026). Отметки ✓ на «Постоянных» привязаны к нему — меняй только в новом файле через год.
B22: Списки | C22: Категории, счета, статусы. Новая строка в конце списка сразу появляется в меню.
B23: Деньги на старте | C23: Больше не вводятся: считаются по остаткам счетов.
B25: Цвета
B26: Жёлтая заливка, синий текст | C26: Ячейки для ввода. Всё остальное — формулы.
B27: Зелёная строка журнала | C27: Оплачено. Красная — просрочено. Жёлтая — срок в ближайшие 7 дней.
B28: Оранжевая клетка месяца | C28: В «Постоянных» вписана сумма, отличная от плана.
B29: Серая клетка месяца | C29: Платёж в этом месяце не действует (вне «с / по»).

Sheet Настройки
B2: Настройки
B3: Период прогноза, учётный год и деньги на старте
J4: Списки для меню — правь под себя; новая строка сразу появляется в меню
B5: Период и деньги | J5: Категории расходов | L5: Категории доходов | N5: Счета | P5: Статус | R5: Приоритет | T5: Тип | V5: Месяцы | X5: Месяцы учёта
B6: Прогноз: год начала | C6: 2026 | E6: Горизонт прогноза | F6: =DATE($C$6,$D$7,1) | G6: =DATE($C$6,$D$7+3,1)-1 | J6: Жильё | L6: Зарплата | N6: Карта | P6: Запланировано | R6: Обязательно | T6: Расход | V6: Январь | X6: =INDEX($V$6:$V$17,MONTH(DATE($C$8,$D$9+0,1)))&" "&YEAR(DATE($C$8,$D$9+0,1))
B7: Прогноз: месяц начала | C7: Октябрь | D7: =IFERROR(MATCH($C$7,$V$6:$V$17,0),1) | J7: Продукты | L7: Премия | N7: Наличные | P7: Оплачено | R7: Желательно | T7: Доход | V7: Февраль | X7: =INDEX($V$6:$V$17,MONTH(DATE($C$8,$D$9+1,1)))&" "&YEAR(DATE($C$8,$D$9+1,1))
B8: Учёт: год начала | C8: 2026 | E8: Учётный год | F8: =DATE($C$8,$D$9,1) | G8: =DATE($C$8,$D$9+12,1)-1 | J8: Транспорт | N8: Кредитка | P8: Перенесено | R8: Можно отложить | V8: Март | X8: =INDEX($V$6:$V$17,MONTH(DATE($C$8,$D$9+2,1)))&" "&YEAR(DATE($C$8,$D$9+2,1))
B9: Учёт: месяц начала | C9: Октябрь | D9: =IFERROR(MATCH($C$9,$V$6:$V$17,0),1) | J9: Подписки | P9: Отменено | V9: Апрель | X9: =INDEX($V$6:$V$17,MONTH(DATE($C$8,$D$9+3,1)))&" "&YEAR(DATE($C$8,$D$9+3,1))
B10: Деньги на старте прогноза (по счетам) | C10: =SUM(Счета!$D$10:$D$21)+SUMIFS(Операции!$Q$10:$Q$1009,Операции!$D$10:$D$1009,"Доход",Операции!$C$10:$C$1009,">="&Счета!$C$4,Операции!$C$10:$C$1009,"<"&DATE(Настройки!$C$6,Настройки!$D$7,1))-SUMIFS(Операции!$Q$10:$Q$1009,Операции!$D$10:$D$1009,"Расход",Операции!$C$10:$C$1009,">="&Счета!$C$4,Операции!$C$10:$C$1009,"<"&DATE(Настройки!$C$6,Настройки!$D$7,1))+SUMIFS(Журнал!$P$10:$P$1509,Журнал!$D$10:$D$1509,"Доход",Журнал!$R$10:$R$1509,">="&DATE(YEAR(Счета!$C$4),MONTH(Счета!$C$4),1),Журнал!$R$10:$R$1509,"<"&DATE(Настройки!$C$6,Настройки!$D$7,1))-SUMIFS(Журнал!$P$10:$P$1509,Журнал!$D$10:$D$1509,"<>Доход",Журнал!$R$10:$R$1509,">="&DATE(YEAR(Счета!$C$4),MONTH(Счета!$C$4),1),Журнал!$R$10:$R$1509,"<"&DATE(Настройки!$C$6,Настройки!$D$7,1))+SUMIFS(Постоянные!$AC$8:$AC$367,Постоянные!$Z$8:$Z$367,"Доход",Постоянные!$Y$8:$Y$367,">="&Счета!$C$4,Постоянные!$Y$8:$Y$367,"<"&DATE(Настройки!$C$6,Настройки!$D$7,1))-SUMIFS(Постоянные!$AC$8:$AC$367,Постоянные!$Z$8:$Z$367,"Расход",Постоянные!$Y$8:$Y$367,">="&Счета!$C$4,Постоянные!$Y$8:$Y$367,"<"&DATE(Настройки!$C$6,Настройки!$D$7,1))-SUMIFS(Покупки!$S$7:$S$18,Покупки!$G$7:$G$18,">="&Счета!$C$4,Покупки!$G$7:$G$18,"<"&DATE(Настройки!$C$6,Настройки!$D$7,1)) | J10: Техника | V10: Май | X10: =INDEX($V$6:$V$17,MONTH(DATE($C$8,$D$9+4,1)))&" "&YEAR(DATE($C$8,$D$9+4,1))
B11: Неприкосновенный запас (подушка) | C11: 100 | V11: Июнь | X11: =INDEX($V$6:$V$17,MONTH(DATE($C$8,$D$9+5,1)))&" "&YEAR(DATE($C$8,$D$9+5,1))
V12: Июль | X12: =INDEX($V$6:$V$17,MONTH(DATE($C$8,$D$9+6,1)))&" "&YEAR(DATE($C$8,$D$9+6,1))
B13: Прогноз — три месяца вперёд, сдвигай его как угодно. Учётный год — 12 месяцев статистики; отметки ✓ на «Постоянных» привязаны к нему, поэтому его начало меняют только при переходе на новый файл. | V13: Август | X13: =INDEX($V$6:$V$17,MONTH(DATE($C$8,$D$9+7,1)))&" "&YEAR(DATE($C$8,$D$9+7,1))
V14: Сентябрь | X14: =INDEX($V$6:$V$17,MONTH(DATE($C$8,$D$9+8,1)))&" "&YEAR(DATE($C$8,$D$9+8,1))
V15: Октябрь | X15: =INDEX($V$6:$V$17,MONTH(DATE($C$8,$D$9+9,1)))&" "&YEAR(DATE($C$8,$D$9+9,1))
V16: Ноябрь | X16: =INDEX($V$6:$V$17,MONTH(DATE($C$8,$D$9+10,1)))&" "&YEAR(DATE($C$8,$D$9+10,1))
V17: Декабрь | X17: =INDEX($V$6:$V$17,MONTH(DATE($C$8,$D$9+11,1)))&" "&YEAR(DATE($C$8,$D$9+11,1))

Sheet Операции
B2: Операции
B3: Каждый день: трата, поступление или перевод между счетами (снятие наличных, погашение кредитки)
B5: Сводка: | C5: Потрачено сегодня | E5: Потрачено за выбранный месяц | F5: Поступило за выбранный месяц | G5: Строк без счёта | I5: Возможных дублей
C6: =SUMIFS($Q$10:$Q$1009,$D$10:$D$1009,"Расход",$C$10:$C$1009,TODAY()) | E6: =SUMIFS($Q$10:$Q$1009,$D$10:$D$1009,"Расход",$P$10:$P$1009,$S$8) | F6: =SUMIFS($Q$10:$Q$1009,$D$10:$D$1009,"Доход",$P$10:$P$1009,$S$8) | G6: =COUNTIFS($G$10:$G$1009,"<>",$H$10:$H$1009,"") | I6: =COUNTIF($K$10:$K$1009,"?*")
C7: Месяц | D7: Октябрь 2026 | F7: ← выбери месяц: в колонке «Дата» появятся его дни (другую дату можно вписать вручную)
S8: =IFERROR(DATE(Настройки!$C$8,Настройки!$D$9+MATCH($D$7,Настройки!$X$6:$X$17,0)-1,1),DATE(YEAR(TODAY()),MONTH(TODAY()),1))
B9: № | C9: Дата | D9: Тип | E9: Категория | F9: Что | G9: Сумма | H9: Счёт | I9: На счёт (для перевода) | J9: Месяц | K9: Возможный дубль | S9: =DAY(DATE(YEAR($S$8),MONTH($S$8)+1,1)-1)
B10: =IF(AND($C10="",$F10=""),"",ROW()-9) | C10: 46307 | D10: Расход | E10: Продукты | F10: Магазин | G10: -30 | H10: Кредитка | J10: =IF($C10="","",INDEX(Настройки!$V$6:$V$17,MONTH($C10))&" "&YEAR($C10)) | K10: =IF(OR($F10="",$D10="Перевод"),"",IF(AND(N($G10)<>0,COUNTIFS(Журнал!$C$10:$C$1509,$C10,Журнал!$P$10:$P$1509,$G10)>0),"есть в Журнале",IF(COUNTIF(Постоянные!$C$8:$C$37,$F10)>0,"есть в Постоянных",IF(COUNTIF(Покупки!$C$7:$C$18,$F10)>0,"есть в Покупках","")))) | P10: =IF($C10="","",DATE(YEAR($C10),MONTH($C10),1)) | Q10: =IF(ISNUMBER($G10),ABS($G10),0) | R10: =IF(AND($D10="Расход",COUNTIFS(Счета!$B$10:$B$21,$H10,Счета!$C$10:$C$21,"Кредитная")>0),1,0) | S10: =IF(1<=$S$9,DATE(YEAR($S$8),MONTH($S$8),1),"")
B11: =IF(AND($C11="",$F11=""),"",ROW()-9) | C11: 46308 | D11: Перевод | F11: Снятие | G11: 100 | H11: Карта | I11: Наличные | J11: =IF($C11="","",INDEX(Настройки!$V$6:$V$17,MONTH($C11))&" "&YEAR($C11)) | K11: =IF(OR($F11="",$D11="Перевод"),"",IF(AND(N($G11)<>0,COUNTIFS(Журнал!$C$10:$C$1509,$C11,Журнал!$P$10:$P$1509,$G11)>0),"есть в Журнале",IF(COUNTIF(Постоянные!$C$8:$C$37,$F11)>0,"есть в Постоянных",IF(COUNTIF(Покупки!$C$7:$C$18,$F11)>0,"есть в Покупках","")))) | P11: =IF($C11="","",DATE(YEAR($C11),MONTH($C11),1)) | Q11: =IF(ISNUMBER($G11),ABS($G11),0) | R11: =IF(AND($D11="Расход",COUNTIFS(Счета!$B$10:$B$21,$H11,Счета!$C$10:$C$21,"Кредитная")>0),1,0) | S11: =IF(2<=$S$9,DATE(YEAR($S$8),MONTH($S$8),2),"")
B12: =IF(AND($C12="",$F12=""),"",ROW()-9) | C12: 46309 | D12: Расход | E12: Транспорт | F12: Билет | G12: 20 | H12: Наличные | J12: =IF($C12="","",INDEX(Настройки!$V$6:$V$17,MONTH($C12))&" "&YEAR($C12)) | K12: =IF(OR($F12="",$D12="Перевод"),"",IF(AND(N($G12)<>0,COUNTIFS(Журнал!$C$10:$C$1509,$C12,Журнал!$P$10:$P$1509,$G12)>0),"есть в Журнале",IF(COUNTIF(Постоянные!$C$8:$C$37,$F12)>0,"есть в Постоянных",IF(COUNTIF(Покупки!$C$7:$C$18,$F12)>0,"есть в Покупках","")))) | P12: =IF($C12="","",DATE(YEAR($C12),MONTH($C12),1)) | Q12: =IF(ISNUMBER($G12),ABS($G12),0) | R12: =IF(AND($D12="Расход",COUNTIFS(Счета!$B$10:$B$21,$H12,Счета!$C$10:$C$21,"Кредитная")>0),1,0) | S12: =IF(3<=$S$9,DATE(YEAR($S$8),MONTH($S$8),3),"")
B13: =IF(AND($C13="",$F13=""),"",ROW()-9) | C13: 46315 | D13: Перевод | F13: Погашение кредитки | G13: 30 | H13: Карта | I13: Кредитка | J13: =IF($C13="","",INDEX(Настройки!$V$6:$V$17,MONTH($C13))&" "&YEAR($C13)) | K13: =IF(OR($F13="",$D13="Перевод"),"",IF(AND(N($G13)<>0,COUNTIFS(Журнал!$C$10:$C$1509,$C13,Журнал!$P$10:$P$1509,$G13)>0),"есть в Журнале",IF(COUNTIF(Постоянные!$C$8:$C$37,$F13)>0,"есть в Постоянных",IF(COUNTIF(Покупки!$C$7:$C$18,$F13)>0,"есть в Покупках","")))) | P13: =IF($C13="","",DATE(YEAR($C13),MONTH($C13),1)) | Q13: =IF(ISNUMBER($G13),ABS($G13),0) | R13: =IF(AND($D13="Расход",COUNTIFS(Счета!$B$10:$B$21,$H13,Счета!$C$10:$C$21,"Кредитная")>0),1,0) | S13: =IF(4<=$S$9,DATE(YEAR($S$8),MONTH($S$8),4),"")
B14: =IF(AND($C14="",$F14=""),"",ROW()-9) | C14: 46316 | D14: Доход | E14: Премия | F14: Кэшбэк | G14: 5 | H14: Карта | J14: =IF($C14="","",INDEX(Настройки!$V$6:$V$17,MONTH($C14))&" "&YEAR($C14)) | K14: =IF(OR($F14="",$D14="Перевод"),"",IF(AND(N($G14)<>0,COUNTIFS(Журнал!$C$10:$C$1509,$C14,Журнал!$P$10:$P$1509,$G14)>0),"есть в Журнале",IF(COUNTIF(Постоянные!$C$8:$C$37,$F14)>0,"есть в Постоянных",IF(COUNTIF(Покупки!$C$7:$C$18,$F14)>0,"есть в Покупках","")))) | P14: =IF($C14="","",DATE(YEAR($C14),MONTH($C14),1)) | Q14: =IF(ISNUMBER($G14),ABS($G14),0) | R14: =IF(AND($D14="Расход",COUNTIFS(Счета!$B$10:$B$21,$H14,Счета!$C$10:$C$21,"Кредитная")>0),1,0) | S14: =IF(5<=$S$9,DATE(YEAR($S$8),MONTH($S$8),5),"")
B15: =IF(AND($C15="",$F15=""),"",ROW()-9) | C15: 46301 | D15: Расход | E15: Продукты | F15: Кафе | G15: 100 | H15: Карта | J15: =IF($C15="","",INDEX(Настройки!$V$6:$V$17,MONTH($C15))&" "&YEAR($C15)) | K15: =IF(OR($F15="",$D15="Перевод"),"",IF(AND(N($G15)<>0,COUNTIFS(Журнал!$C$10:$C$1509,$C15,Журнал!$P$10:$P$1509,$G15)>0),"есть в Журнале",IF(COUNTIF(Постоянные!$C$8:$C$37,$F15)>0,"есть в Постоянных",IF(COUNTIF(Покупки!$C$7:$C$18,$F15)>0,"есть в Покупках","")))) | P15: =IF($C15="","",DATE(YEAR($C15),MONTH($C15),1)) | Q15: =IF(ISNUMBER($G15),ABS($G15),0) | R15: =IF(AND($D15="Расход",COUNTIFS(Счета!$B$10:$B$21,$H15,Счета!$C$10:$C$21,"Кредитная")>0),1,0) | S15: =IF(6<=$S$9,DATE(YEAR($S$8),MONTH($S$8),6),"")
B16: =IF(AND($C16="",$F16=""),"",ROW()-9) | J16: =IF($C16="","",INDEX(Настройки!$V$6:$V$17,MONTH($C16))&" "&YEAR($C16)) | K16: =IF(OR($F16="",$D16="Перевод"),"",IF(AND(N($G16)<>0,COUNTIFS(Журнал!$C$10:$C$1509,$C16,Журнал!$P$10:$P$1509,$G16)>0),"есть в Журнале",IF(COUNTIF(Постоянные!$C$8:$C$37,$F16)>0,"есть в Постоянных",IF(COUNTIF(Покупки!$C$7:$C$18,$F16)>0,"есть в Покупках","")))) | P16: =IF($C16="","",DATE(YEAR($C16),MONTH($C16),1)) | Q16: =IF(ISNUMBER($G16),ABS($G16),0) | R16: =IF(AND($D16="Расход",COUNTIFS(Счета!$B$10:$B$21,$H16,Счета!$C$10:$C$21,"Кредитная")>0),1,0) | S16: =IF(7<=$S$9,DATE(YEAR($S$8),MONTH($S$8),7),"")
B17: =IF(AND($C17="",$F17=""),"",ROW()-9) | J17: =IF($C17="","",INDEX(Настройки!$V$6:$V$17,MONTH($C17))&" "&YEAR($C17)) | K17: =IF(OR($F17="",$D17="Перевод"),"",IF(AND(N($G17)<>0,COUNTIFS(Журнал!$C$10:$C$1509,$C17,Журнал!$P$10:$P$1509,$G17)>0),"есть в Журнале",IF(COUNTIF(Постоянные!$C$8:$C$37,$F17)>0,"есть в Постоянных",IF(COUNTIF(Покупки!$C$7:$C$18,$F17)>0,"есть в Покупках","")))) | P17: =IF($C17="","",DATE(YEAR($C17),MONTH($C17),1)) | Q17: =IF(ISNUMBER($G17),ABS($G17),0) | R17: =IF(AND($D17="Расход",COUNTIFS(Счета!$B$10:$B$21,$H17,Счета!$C$10:$C$21,"Кредитная")>0),1,0) | S17: =IF(8<=$S$9,DATE(YEAR($S$8),MONTH($S$8),8),"")
B18: =IF(AND($C18="",$F18=""),"",ROW()-9) | J18: =IF($C18="","",INDEX(Настройки!$V$6:$V$17,MONTH($C18))&" "&YEAR($C18)) | K18: =IF(OR($F18="",$D18="Перевод"),"",IF(AND(N($G18)<>0,COUNTIFS(Журнал!$C$10:$C$1509,$C18,Журнал!$P$10:$P$1509,$G18)>0),"есть в Журнале",IF(COUNTIF(Постоянные!$C$8:$C$37,$F18)>0,"есть в Постоянных",IF(COUNTIF(Покупки!$C$7:$C$18,$F18)>0,"есть в Покупках","")))) | P18: =IF($C18="","",DATE(YEAR($C18),MONTH($C18),1)) | Q18: =IF(ISNUMBER($G18),ABS($G18),0) | R18: =IF(AND($D18="Расход",COUNTIFS(Счета!$B$10:$B$21,$H18,Счета!$C$10:$C$21,"Кредитная")>0),1,0) | S18: =IF(9<=$S$9,DATE(YEAR($S$8),MONTH($S$8),9),"")
B19: =IF(AND($C19="",$F19=""),"",ROW()-9) | J19: =IF($C19="","",INDEX(Настройки!$V$6:$V$17,MONTH($C19))&" "&YEAR($C19)) | K19: =IF(OR($F19="",$D19="Перевод"),"",IF(AND(N($G19)<>0,COUNTIFS(Журнал!$C$10:$C$1509,$C19,Журнал!$P$10:$P$1509,$G19)>0),"есть в Журнале",IF(COUNTIF(Постоянные!$C$8:$C$37,$F19)>0,"есть в Постоянных",IF(COUNTIF(Покупки!$C$7:$C$18,$F19)>0,"есть в Покупках","")))) | P19: =IF($C19="","",DATE(YEAR($C19),MONTH($C19),1)) | Q19: =IF(ISNUMBER($G19),ABS($G19),0) | R19: =IF(AND($D19="Расход",COUNTIFS(Счета!$B$10:$B$21,$H19,Счета!$C$10:$C$21,"Кредитная")>0),1,0) | S19: =IF(10<=$S$9,DATE(YEAR($S$8),MONTH($S$8),10),"")
B20: =IF(AND($C20="",$F20=""),"",ROW()-9) | J20: =IF($C20="","",INDEX(Настройки!$V$6:$V$17,MONTH($C20))&" "&YEAR($C20)) | K20: =IF(OR($F20="",$D20="Перевод"),"",IF(AND(N($G20)<>0,COUNTIFS(Журнал!$C$10:$C$1509,$C20,Журнал!$P$10:$P$1509,$G20)>0),"есть в Журнале",IF(COUNTIF(Постоянные!$C$8:$C$37,$F20)>0,"есть в Постоянных",IF(COUNTIF(Покупки!$C$7:$C$18,$F20)>0,"есть в Покупках","")))) | P20: =IF($C20="","",DATE(YEAR($C20),MONTH($C20),1)) | Q20: =IF(ISNUMBER($G20),ABS($G20),0) | R20: =IF(AND($D20="Расход",COUNTIFS(Счета!$B$10:$B$21,$H20,Счета!$C$10:$C$21,"Кредитная")>0),1,0) | S20: =IF(11<=$S$9,DATE(YEAR($S$8),MONTH($S$8),11),"")
B21: =IF(AND($C21="",$F21=""),"",ROW()-9) | J21: =IF($C21="","",INDEX(Настройки!$V$6:$V$17,MONTH($C21))&" "&YEAR($C21)) | K21: =IF(OR($F21="",$D21="Перевод"),"",IF(AND(N($G21)<>0,COUNTIFS(Журнал!$C$10:$C$1509,$C21,Журнал!$P$10:$P$1509,$G21)>0),"есть в Журнале",IF(COUNTIF(Постоянные!$C$8:$C$37,$F21)>0,"есть в Постоянных",IF(COUNTIF(Покупки!$C$7:$C$18,$F21)>0,"есть в Покупках","")))) | P21: =IF($C21="","",DATE(YEAR($C21),MONTH($C21),1)) | Q21: =IF(ISNUMBER($G21),ABS($G21),0) | R21: =IF(AND($D21="Расход",COUNTIFS(Счета!$B$10:$B$21,$H21,Счета!$C$10:$C$21,"Кредитная")>0),1,0) | S21: =IF(12<=$S$9,DATE(YEAR($S$8),MONTH($S$8),12),"")
B22: =IF(AND($C22="",$F22=""),"",ROW()-9) | J22: =IF($C22="","",INDEX(Настройки!$V$6:$V$17,MONTH($C22))&" "&YEAR($C22)) | K22: =IF(OR($F22="",$D22="Перевод"),"",IF(AND(N($G22)<>0,COUNTIFS(Журнал!$C$10:$C$1509,$C22,Журнал!$P$10:$P$1509,$G22)>0),"есть в Журнале",IF(COUNTIF(Постоянные!$C$8:$C$37,$F22)>0,"есть в Постоянных",IF(COUNTIF(Покупки!$C$7:$C$18,$F22)>0,"есть в Покупках","")))) | P22: =IF($C22="","",DATE(YEAR($C22),MONTH($C22),1)) | Q22: =IF(ISNUMBER($G22),ABS($G22),0) | R22: =IF(AND($D22="Расход",COUNTIFS(Счета!$B$10:$B$21,$H22,Счета!$C$10:$C$21,"Кредитная")>0),1,0) | S22: =IF(13<=$S$9,DATE(YEAR($S$8),MONTH($S$8),13),"")
B23: =IF(AND($C23="",$F23=""),"",ROW()-9) | J23: =IF($C23="","",INDEX(Настройки!$V$6:$V$17,MONTH($C23))&" "&YEAR($C23)) | K23: =IF(OR($F23="",$D23="Перевод"),"",IF(AND(N($G23)<>0,COUNTIFS(Журнал!$C$10:$C$1509,$C23,Журнал!$P$10:$P$1509,$G23)>0),"есть в Журнале",IF(COUNTIF(Постоянные!$C$8:$C$37,$F23)>0,"есть в Постоянных",IF(COUNTIF(Покупки!$C$7:$C$18,$F23)>0,"есть в Покупках","")))) | P23: =IF($C23="","",DATE(YEAR($C23),MONTH($C23),1)) | Q23: =IF(ISNUMBER($G23),ABS($G23),0) | R23: =IF(AND($D23="Расход",COUNTIFS(Счета!$B$10:$B$21,$H23,Счета!$C$10:$C$21,"Кредитная")>0),1,0) | S23: =IF(14<=$S$9,DATE(YEAR($S$8),MONTH($S$8),14),"")
B24: =IF(AND($C24="",$F24=""),"",ROW()-9) | J24: =IF($C24="","",INDEX(Настройки!$V$6:$V$17,MONTH($C24))&" "&YEAR($C24)) | K24: =IF(OR($F24="",$D24="Перевод"),"",IF(AND(N($G24)<>0,COUNTIFS(Журнал!$C$10:$C$1509,$C24,Журнал!$P$10:$P$1509,$G24)>0),"есть в Журнале",IF(COUNTIF(Постоянные!$C$8:$C$37,$F24)>0,"есть в Постоянных",IF(COUNTIF(Покупки!$C$7:$C$18,$F24)>0,"есть в Покупках","")))) | P24: =IF($C24="","",DATE(YEAR($C24),MONTH($C24),1)) | Q24: =IF(ISNUMBER($G24),ABS($G24),0) | R24: =IF(AND($D24="Расход",COUNTIFS(Счета!$B$10:$B$21,$H24,Счета!$C$10:$C$21,"Кредитная")>0),1,0) | S24: =IF(15<=$S$9,DATE(YEAR($S$8),MONTH($S$8),15),"")
B25: =IF(AND($C25="",$F25=""),"",ROW()-9) | J25: =IF($C25="","",INDEX(Настройки!$V$6:$V$17,MONTH($C25))&" "&YEAR($C25)) | K25: =IF(OR($F25="",$D25="Перевод"),"",IF(AND(N($G25)<>0,COUNTIFS(Журнал!$C$10:$C$1509,$C25,Журнал!$P$10:$P$1509,$G25)>0),"есть в Журнале",IF(COUNTIF(Постоянные!$C$8:$C$37,$F25)>0,"есть в Постоянных",IF(COUNTIF(Покупки!$C$7:$C$18,$F25)>0,"есть в Покупках","")))) | P25: =IF($C25="","",DATE(YEAR($C25),MONTH($C25),1)) | Q25: =IF(ISNUMBER($G25),ABS($G25),0) | R25: =IF(AND($D25="Расход",COUNTIFS(Счета!$B$10:$B$21,$H25,Счета!$C$10:$C$21,"Кредитная")>0),1,0) | S25: =IF(16<=$S$9,DATE(YEAR($S$8),MONTH($S$8),16),"")
B26: =IF(AND($C26="",$F26=""),"",ROW()-9) | J26: =IF($C26="","",INDEX(Настройки!$V$6:$V$17,MONTH($C26))&" "&YEAR($C26)) | K26: =IF(OR($F26="",$D26="Перевод"),"",IF(AND(N($G26)<>0,COUNTIFS(Журнал!$C$10:$C$1509,$C26,Журнал!$P$10:$P$1509,$G26)>0),"есть в Журнале",IF(COUNTIF(Постоянные!$C$8:$C$37,$F26)>0,"есть в Постоянных",IF(COUNTIF(Покупки!$C$7:$C$18,$F26)>0,"есть в Покупках","")))) | P26: =IF($C26="","",DATE(YEAR($C26),MONTH($C26),1)) | Q26: =IF(ISNUMBER($G26),ABS($G26),0) | R26: =IF(AND($D26="Расход",COUNTIFS(Счета!$B$10:$B$21,$H26,Счета!$C$10:$C$21,"Кредитная")>0),1,0) | S26: =IF(17<=$S$9,DATE(YEAR($S$8),MONTH($S$8),17),"")
B27: =IF(AND($C27="",$F27=""),"",ROW()-9) | J27: =IF($C27="","",INDEX(Настройки!$V$6:$V$17,MONTH($C27))&" "&YEAR($C27)) | K27: =IF(OR($F27="",$D27="Перевод"),"",IF(AND(N($G27)<>0,COUNTIFS(Журнал!$C$10:$C$1509,$C27,Журнал!$P$10:$P$1509,$G27)>0),"есть в Журнале",IF(COUNTIF(Постоянные!$C$8:$C$37,$F27)>0,"есть в Постоянных",IF(COUNTIF(Покупки!$C$7:$C$18,$F27)>0,"есть в Покупках","")))) | P27: =IF($C27="","",DATE(YEAR($C27),MONTH($C27),1)) | Q27: =IF(ISNUMBER($G27),ABS($G27),0) | R27: =IF(AND($D27="Расход",COUNTIFS(Счета!$B$10:$B$21,$H27,Счета!$C$10:$C$21,"Кредитная")>0),1,0) | S27: =IF(18<=$S$9,DATE(YEAR($S$8),MONTH($S$8),18),"")
B28: =IF(AND($C28="",$F28=""),"",ROW()-9) | J28: =IF($C28="","",INDEX(Настройки!$V$6:$V$17,MONTH($C28))&" "&YEAR($C28)) | K28: =IF(OR($F28="",$D28="Перевод"),"",IF(AND(N($G28)<>0,COUNTIFS(Журнал!$C$10:$C$1509,$C28,Журнал!$P$10:$P$1509,$G28)>0),"есть в Журнале",IF(COUNTIF(Постоянные!$C$8:$C$37,$F28)>0,"есть в Постоянных",IF(COUNTIF(Покупки!$C$7:$C$18,$F28)>0,"есть в Покупках","")))) | P28: =IF($C28="","",DATE(YEAR($C28),MONTH($C28),1)) | Q28: =IF(ISNUMBER($G28),ABS($G28),0) | R28: =IF(AND($D28="Расход",COUNTIFS(Счета!$B$10:$B$21,$H28,Счета!$C$10:$C$21,"Кредитная")>0),1,0) | S28: =IF(19<=$S$9,DATE(YEAR($S$8),MONTH($S$8),19),"")
B29: =IF(AND($C29="",$F29=""),"",ROW()-9) | J29: =IF($C29="","",INDEX(Настройки!$V$6:$V$17,MONTH($C29))&" "&YEAR($C29)) | K29: =IF(OR($F29="",$D29="Перевод"),"",IF(AND(N($G29)<>0,COUNTIFS(Журнал!$C$10:$C$1509,$C29,Журнал!$P$10:$P$1509,$G29)>0),"есть в Журнале",IF(COUNTIF(Постоянные!$C$8:$C$37,$F29)>0,"есть в Постоянных",IF(COUNTIF(Покупки!$C$7:$C$18,$F29)>0,"есть в Покупках","")))) | P29: =IF($C29="","",DATE(YEAR($C29),MONTH($C29),1)) | Q29: =IF(ISNUMBER($G29),ABS($G29),0) | R29: =IF(AND($D29="Расход",COUNTIFS(Счета!$B$10:$B$21,$H29,Счета!$C$10:$C$21,"Кредитная")>0),1,0) | S29: =IF(20<=$S$9,DATE(YEAR($S$8),MONTH($S$8),20),"")
B30: =IF(AND($C30="",$F30=""),"",ROW()-9) | J30: =IF($C30="","",INDEX(Настройки!$V$6:$V$17,MONTH($C30))&" "&YEAR($C30)) | K30: =IF(OR($F30="",$D30="Перевод"),"",IF(AND(N($G30)<>0,COUNTIFS(Журнал!$C$10:$C$1509,$C30,Журнал!$P$10:$P$1509,$G30)>0),"есть в Журнале",IF(COUNTIF(Постоянные!$C$8:$C$37,$F30)>0,"есть в Постоянных",IF(COUNTIF(Покупки!$C$7:$C$18,$F30)>0,"есть в Покупках","")))) | P30: =IF($C30="","",DATE(YEAR($C30),MONTH($C30),1)) | Q30: =IF(ISNUMBER($G30),ABS($G30),0) | R30: =IF(AND($D30="Расход",COUNTIFS(Счета!$B$10:$B$21,$H30,Счета!$C$10:$C$21,"Кредитная")>0),1,0) | S30: =IF(21<=$S$9,DATE(YEAR($S$8),MONTH($S$8),21),"")
B31: =IF(AND($C31="",$F31=""),"",ROW()-9) | J31: =IF($C31="","",INDEX(Настройки!$V$6:$V$17,MONTH($C31))&" "&YEAR($C31)) | K31: =IF(OR($F31="",$D31="Перевод"),"",IF(AND(N($G31)<>0,COUNTIFS(Журнал!$C$10:$C$1509,$C31,Журнал!$P$10:$P$1509,$G31)>0),"есть в Журнале",IF(COUNTIF(Постоянные!$C$8:$C$37,$F31)>0,"есть в Постоянных",IF(COUNTIF(Покупки!$C$7:$C$18,$F31)>0,"есть в Покупках","")))) | P31: =IF($C31="","",DATE(YEAR($C31),MONTH($C31),1)) | Q31: =IF(ISNUMBER($G31),ABS($G31),0) | R31: =IF(AND($D31="Расход",COUNTIFS(Счета!$B$10:$B$21,$H31,Счета!$C$10:$C$21,"Кредитная")>0),1,0) | S31: =IF(22<=$S$9,DATE(YEAR($S$8),MONTH($S$8),22),"")
B32: =IF(AND($C32="",$F32=""),"",ROW()-9) | J32: =IF($C32="","",INDEX(Настройки!$V$6:$V$17,MONTH($C32))&" "&YEAR($C32)) | K32: =IF(OR($F32="",$D32="Перевод"),"",IF(AND(N($G32)<>0,COUNTIFS(Журнал!$C$10:$C$1509,$C32,Журнал!$P$10:$P$1509,$G32)>0),"есть в Журнале",IF(COUNTIF(Постоянные!$C$8:$C$37,$F32)>0,"есть в Постоянных",IF(COUNTIF(Покупки!$C$7:$C$18,$F32)>0,"есть в Покупках","")))) | P32: =IF($C32="","",DATE(YEAR($C32),MONTH($C32),1)) | Q32: =IF(ISNUMBER($G32),ABS($G32),0) | R32: =IF(AND($D32="Расход",COUNTIFS(Счета!$B$10:$B$21,$H32,Счета!$C$10:$C$21,"Кредитная")>0),1,0) | S32: =IF(23<=$S$9,DATE(YEAR($S$8),MONTH($S$8),23),"")
B33: =IF(AND($C33="",$F33=""),"",ROW()-9) | J33: =IF($C33="","",INDEX(Настройки!$V$6:$V$17,MONTH($C33))&" "&YEAR($C33)) | K33: =IF(OR($F33="",$D33="Перевод"),"",IF(AND(N($G33)<>0,COUNTIFS(Журнал!$C$10:$C$1509,$C33,Журнал!$P$10:$P$1509,$G33)>0),"есть в Журнале",IF(COUNTIF(Постоянные!$C$8:$C$37,$F33)>0,"есть в Постоянных",IF(COUNTIF(Покупки!$C$7:$C$18,$F33)>0,"есть в Покупках","")))) | P33: =IF($C33="","",DATE(YEAR($C33),MONTH($C33),1)) | Q33: =IF(ISNUMBER($G33),ABS($G33),0) | R33: =IF(AND($D33="Расход",COUNTIFS(Счета!$B$10:$B$21,$H33,Счета!$C$10:$C$21,"Кредитная")>0),1,0) | S33: =IF(24<=$S$9,DATE(YEAR($S$8),MONTH($S$8),24),"")
B34: =IF(AND($C34="",$F34=""),"",ROW()-9) | J34: =IF($C34="","",INDEX(Настройки!$V$6:$V$17,MONTH($C34))&" "&YEAR($C34)) | K34: =IF(OR($F34="",$D34="Перевод"),"",IF(AND(N($G34)<>0,COUNTIFS(Журнал!$C$10:$C$1509,$C34,Журнал!$P$10:$P$1509,$G34)>0),"есть в Журнале",IF(COUNTIF(Постоянные!$C$8:$C$37,$F34)>0,"есть в Постоянных",IF(COUNTIF(Покупки!$C$7:$C$18,$F34)>0,"есть в Покупках","")))) | P34: =IF($C34="","",DATE(YEAR($C34),MONTH($C34),1)) | Q34: =IF(ISNUMBER($G34),ABS($G34),0) | R34: =IF(AND($D34="Расход",COUNTIFS(Счета!$B$10:$B$21,$H34,Счета!$C$10:$C$21,"Кредитная")>0),1,0) | S34: =IF(25<=$S$9,DATE(YEAR($S$8),MONTH($S$8),25),"")
B35: =IF(AND($C35="",$F35=""),"",ROW()-9) | J35: =IF($C35="","",INDEX(Настройки!$V$6:$V$17,MONTH($C35))&" "&YEAR($C35)) | K35: =IF(OR($F35="",$D35="Перевод"),"",IF(AND(N($G35)<>0,COUNTIFS(Журнал!$C$10:$C$1509,$C35,Журнал!$P$10:$P$1509,$G35)>0),"есть в Журнале",IF(COUNTIF(Постоянные!$C$8:$C$37,$F35)>0,"есть в Постоянных",IF(COUNTIF(Покупки!$C$7:$C$18,$F35)>0,"есть в Покупках","")))) | P35: =IF($C35="","",DATE(YEAR($C35),MONTH($C35),1)) | Q35: =IF(ISNUMBER($G35),ABS($G35),0) | R35: =IF(AND($D35="Расход",COUNTIFS(Счета!$B$10:$B$21,$H35,Счета!$C$10:$C$21,"Кредитная")>0),1,0) | S35: =IF(26<=$S$9,DATE(YEAR($S$8),MONTH($S$8),26),"")
B36: =IF(AND($C36="",$F36=""),"",ROW()-9) | J36: =IF($C36="","",INDEX(Настройки!$V$6:$V$17,MONTH($C36))&" "&YEAR($C36)) | K36: =IF(OR($F36="",$D36="Перевод"),"",IF(AND(N($G36)<>0,COUNTIFS(Журнал!$C$10:$C$1509,$C36,Журнал!$P$10:$P$1509,$G36)>0),"есть в Журнале",IF(COUNTIF(Постоянные!$C$8:$C$37,$F36)>0,"есть в Постоянных",IF(COUNTIF(Покупки!$C$7:$C$18,$F36)>0,"есть в Покупках","")))) | P36: =IF($C36="","",DATE(YEAR($C36),MONTH($C36),1)) | Q36: =IF(ISNUMBER($G36),ABS($G36),0) | R36: =IF(AND($D36="Расход",COUNTIFS(Счета!$B$10:$B$21,$H36,Счета!$C$10:$C$21,"Кредитная")>0),1,0) | S36: =IF(27<=$S$9,DATE(YEAR($S$8),MONTH($S$8),27),"")
B37: =IF(AND($C37="",$F37=""),"",ROW()-9) | J37: =IF($C37="","",INDEX(Настройки!$V$6:$V$17,MONTH($C37))&" "&YEAR($C37)) | K37: =IF(OR($F37="",$D37="Перевод"),"",IF(AND(N($G37)<>0,COUNTIFS(Журнал!$C$10:$C$1509,$C37,Журнал!$P$10:$P$1509,$G37)>0),"есть в Журнале",IF(COUNTIF(Постоянные!$C$8:$C$37,$F37)>0,"есть в Постоянных",IF(COUNTIF(Покупки!$C$7:$C$18,$F37)>0,"есть в Покупках","")))) | P37: =IF($C37="","",DATE(YEAR($C37),MONTH($C37),1)) | Q37: =IF(ISNUMBER($G37),ABS($G37),0) | R37: =IF(AND($D37="Расход",COUNTIFS(Счета!$B$10:$B$21,$H37,Счета!$C$10:$C$21,"Кредитная")>0),1,0) | S37: =IF(28<=$S$9,DATE(YEAR($S$8),MONTH($S$8),28),"")
B38: =IF(AND($C38="",$F38=""),"",ROW()-9) | J38: =IF($C38="","",INDEX(Настройки!$V$6:$V$17,MONTH($C38))&" "&YEAR($C38)) | K38: =IF(OR($F38="",$D38="Перевод"),"",IF(AND(N($G38)<>0,COUNTIFS(Журнал!$C$10:$C$1509,$C38,Журнал!$P$10:$P$1509,$G38)>0),"есть в Журнале",IF(COUNTIF(Постоянные!$C$8:$C$37,$F38)>0,"есть в Постоянных",IF(COUNTIF(Покупки!$C$7:$C$18,$F38)>0,"есть в Покупках","")))) | P38: =IF($C38="","",DATE(YEAR($C38),MONTH($C38),1)) | Q38: =IF(ISNUMBER($G38),ABS($G38),0) | R38: =IF(AND($D38="Расход",COUNTIFS(Счета!$B$10:$B$21,$H38,Счета!$C$10:$C$21,"Кредитная")>0),1,0) | S38: =IF(29<=$S$9,DATE(YEAR($S$8),MONTH($S$8),29),"")
B39: =IF(AND($C39="",$F39=""),"",ROW()-9) | J39: =IF($C39="","",INDEX(Настройки!$V$6:$V$17,MONTH($C39))&" "&YEAR($C39)) | K39: =IF(OR($F39="",$D39="Перевод"),"",IF(AND(N($G39)<>0,COUNTIFS(Журнал!$C$10:$C$1509,$C39,Журнал!$P$10:$P$1509,$G39)>0),"есть в Журнале",IF(COUNTIF(Постоянные!$C$8:$C$37,$F39)>0,"есть в Постоянных",IF(COUNTIF(Покупки!$C$7:$C$18,$F39)>0,"есть в Покупках","")))) | P39: =IF($C39="","",DATE(YEAR($C39),MONTH($C39),1)) | Q39: =IF(ISNUMBER($G39),ABS($G39),0) | R39: =IF(AND($D39="Расход",COUNTIFS(Счета!$B$10:$B$21,$H39,Счета!$C$10:$C$21,"Кредитная")>0),1,0) | S39: =IF(30<=$S$9,DATE(YEAR($S$8),MONTH($S$8),30),"")
B40: =IF(AND($C40="",$F40=""),"",ROW()-9) | J40: =IF($C40="","",INDEX(Настройки!$V$6:$V$17,MONTH($C40))&" "&YEAR($C40)) | K40: =IF(OR($F40="",$D40="Перевод"),"",IF(AND(N($G40)<>0,COUNTIFS(Журнал!$C$10:$C$1509,$C40,Журнал!$P$10:$P$1509,$G40)>0),"есть в Журнале",IF(COUNTIF(Постоянные!$C$8:$C$37,$F40)>0,"есть в Постоянных",IF(COUNTIF(Покупки!$C$7:$C$18,$F40)>0,"есть в Покупках","")))) | P40: =IF($C40="","",DATE(YEAR($C40),MONTH($C40),1)) | Q40: =IF(ISNUMBER($G40),ABS($G40),0) | R40: =IF(AND($D40="Расход",COUNTIFS(Счета!$B$10:$B$21,$H40,Счета!$C$10:$C$21,"Кредитная")>0),1,0) | S40: =IF(31<=$S$9,DATE(YEAR($S$8),MONTH($S$8),31),"")
B41: =IF(AND($C41="",$F41=""),"",ROW()-9) | J41: =IF($C41="","",INDEX(Настройки!$V$6:$V$17,MONTH($C41))&" "&YEAR($C41)) | K41: =IF(OR($F41="",$D41="Перевод"),"",IF(AND(N($G41)<>0,COUNTIFS(Журнал!$C$10:$C$1509,$C41,Журнал!$P$10:$P$1509,$G41)>0),"есть в Журнале",IF(COUNTIF(Постоянные!$C$8:$C$37,$F41)>0,"есть в Постоянных",IF(COUNTIF(Покупки!$C$7:$C$18,$F41)>0,"есть в Покупках","")))) | P41: =IF($C41="","",DATE(YEAR($C41),MONTH($C41),1)) | Q41: =IF(ISNUMBER($G41),ABS($G41),0) | R41: =IF(AND($D41="Расход",COUNTIFS(Счета!$B$10:$B$21,$H41,Счета!$C$10:$C$21,"Кредитная")>0),1,0)
B42: =IF(AND($C42="",$F42=""),"",ROW()-9) | J42: =IF($C42="","",INDEX(Настройки!$V$6:$V$17,MONTH($C42))&" "&YEAR($C42)) | K42: =IF(OR($F42="",$D42="Перевод"),"",IF(AND(N($G42)<>0,COUNTIFS(Журнал!$C$10:$C$1509,$C42,Журнал!$P$10:$P$1509,$G42)>0),"есть в Журнале",IF(COUNTIF(Постоянные!$C$8:$C$37,$F42)>0,"есть в Постоянных",IF(COUNTIF(Покупки!$C$7:$C$18,$F42)>0,"есть в Покупках","")))) | P42: =IF($C42="","",DATE(YEAR($C42),MONTH($C42),1)) | Q42: =IF(ISNUMBER($G42),ABS($G42),0) | R42: =IF(AND($D42="Расход",COUNTIFS(Счета!$B$10:$B$21,$H42,Счета!$C$10:$C$21,"Кредитная")>0),1,0)
B43: =IF(AND($C43="",$F43=""),"",ROW()-9) | J43: =IF($C43="","",INDEX(Настройки!$V$6:$V$17,MONTH($C43))&" "&YEAR($C43)) | K43: =IF(OR($F43="",$D43="Перевод"),"",IF(AND(N($G43)<>0,COUNTIFS(Журнал!$C$10:$C$1509,$C43,Журнал!$P$10:$P$1509,$G43)>0),"есть в Журнале",IF(COUNTIF(Постоянные!$C$8:$C$37,$F43)>0,"есть в Постоянных",IF(COUNTIF(Покупки!$C$7:$C$18,$F43)>0,"есть в Покупках","")))) | P43: =IF($C43="","",DATE(YEAR($C43),MONTH($C43),1)) | Q43: =IF(ISNUMBER($G43),ABS($G43),0) | R43: =IF(AND($D43="Расход",COUNTIFS(Счета!$B$10:$B$21,$H43,Счета!$C$10:$C$21,"Кредитная")>0),1,0)
B44: =IF(AND($C44="",$F44=""),"",ROW()-9) | J44: =IF($C44="","",INDEX(Настройки!$V$6:$V$17,MONTH($C44))&" "&YEAR($C44)) | K44: =IF(OR($F44="",$D44="Перевод"),"",IF(AND(N($G44)<>0,COUNTIFS(Журнал!$C$10:$C$1509,$C44,Журнал!$P$10:$P$1509,$G44)>0),"есть в Журнале",IF(COUNTIF(Постоянные!$C$8:$C$37,$F44)>0,"есть в Постоянных",IF(COUNTIF(Покупки!$C$7:$C$18,$F44)>0,"есть в Покупках","")))) | P44: =IF($C44="","",DATE(YEAR($C44),MONTH($C44),1)) | Q44: =IF(ISNUMBER($G44),ABS($G44),0) | R44: =IF(AND($D44="Расход",COUNTIFS(Счета!$B$10:$B$21,$H44,Счета!$C$10:$C$21,"Кредитная")>0),1,0)
B45: =IF(AND($C45="",$F45=""),"",ROW()-9) | J45: =IF($C45="","",INDEX(Настройки!$V$6:$V$17,MONTH($C45))&" "&YEAR($C45)) | K45: =IF(OR($F45="",$D45="Перевод"),"",IF(AND(N($G45)<>0,COUNTIFS(Журнал!$C$10:$C$1509,$C45,Журнал!$P$10:$P$1509,$G45)>0),"есть в Журнале",IF(COUNTIF(Постоянные!$C$8:$C$37,$F45)>0,"есть в Постоянных",IF(COUNTIF(Покупки!$C$7:$C$18,$F45)>0,"есть в Покупках","")))) | P45: =IF($C45="","",DATE(YEAR($C45),MONTH($C45),1)) | Q45: =IF(ISNUMBER($G45),ABS($G45),0) | R45: =IF(AND($D45="Расход",COUNTIFS(Счета!$B$10:$B$21,$H45,Счета!$C$10:$C$21,"Кредитная")>0),1,0)
B46: =IF(AND($C46="",$F46=""),"",ROW()-9) | J46: =IF($C46="","",INDEX(Настройки!$V$6:$V$17,MONTH($C46))&" "&YEAR($C46)) | K46: =IF(OR($F46="",$D46="Перевод"),"",IF(AND(N($G46)<>0,COUNTIFS(Журнал!$C$10:$C$1509,$C46,Журнал!$P$10:$P$1509,$G46)>0),"есть в Журнале",IF(COUNTIF(Постоянные!$C$8:$C$37,$F46)>0,"есть в Постоянных",IF(COUNTIF(Покупки!$C$7:$C$18,$F46)>0,"есть в Покупках","")))) | P46: =IF($C46="","",DATE(YEAR($C46),MONTH($C46),1)) | Q46: =IF(ISNUMBER($G46),ABS($G46),0) | R46: =IF(AND($D46="Расход",COUNTIFS(Счета!$B$10:$B$21,$H46,Счета!$C$10:$C$21,"Кредитная")>0),1,0)
B47: =IF(AND($C47="",$F47=""),"",ROW()-9) | J47: =IF($C47="","",INDEX(Настройки!$V$6:$V$17,MONTH($C47))&" "&YEAR($C47)) | K47: =IF(OR($F47="",$D47="Перевод"),"",IF(AND(N($G47)<>0,COUNTIFS(Журнал!$C$10:$C$1509,$C47,Журнал!$P$10:$P$1509,$G47)>0),"есть в Журнале",IF(COUNTIF(Постоянные!$C$8:$C$37,$F47)>0,"есть в Постоянных",IF(COUNTIF(Покупки!$C$7:$C$18,$F47)>0,"есть в Покупках","")))) | P47: =IF($C47="","",DATE(YEAR($C47),MONTH($C47),1)) | Q47: =IF(ISNUMBER($G47),ABS($G47),0) | R47: =IF(AND($D47="Расход",COUNTIFS(Счета!$B$10:$B$21,$H47,Счета!$C$10:$C$21,"Кредитная")>0),1,0)
B48: =IF(AND($C48="",$F48=""),"",ROW()-9) | J48: =IF($C48="","",INDEX(Настройки!$V$6:$V$17,MONTH($C48))&" "&YEAR($C48)) | K48: =IF(OR($F48="",$D48="Перевод"),"",IF(AND(N($G48)<>0,COUNTIFS(Журнал!$C$10:$C$1509,$C48,Журнал!$P$10:$P$1509,$G48)>0),"есть в Журнале",IF(COUNTIF(Постоянные!$C$8:$C$37,$F48)>0,"есть в Постоянных",IF(COUNTIF(Покупки!$C$7:$C$18,$F48)>0,"есть в Покупках","")))) | P48: =IF($C48="","",DATE(YEAR($C48),MONTH($C48),1)) | Q48: =IF(ISNUMBER($G48),ABS($G48),0) | R48: =IF(AND($D48="Расход",COUNTIFS(Счета!$B$10:$B$21,$H48,Счета!$C$10:$C$21,"Кредитная")>0),1,0)
B49: =IF(AND($C49="",$F49=""),"",ROW()-9) | J49: =IF($C49="","",INDEX(Настройки!$V$6:$V$17,MONTH($C49))&" "&YEAR($C49)) | K49: =IF(OR($F49="",$D49="Перевод"),"",IF(AND(N($G49)<>0,COUNTIFS(Журнал!$C$10:$C$1509,$C49,Журнал!$P$10:$P$1509,$G49)>0),"есть в Журнале",IF(COUNTIF(Постоянные!$C$8:$C$37,$F49)>0,"есть в Постоянных",IF(COUNTIF(Покупки!$C$7:$C$18,$F49)>0,"есть в Покупках","")))) | P49: =IF($C49="","",DATE(YEAR($C49),MONTH($C49),1)) | Q49: =IF(ISNUMBER($G49),ABS($G49),0) | R49: =IF(AND($D49="Расход",COUNTIFS(Счета!$B$10:$B$21,$H49,Счета!$C$10:$C$21,"Кредитная")>0),1,0)
B50: =IF(AND($C50="",$F50=""),"",ROW()-9) | J50: =IF($C50="","",INDEX(Настройки!$V$6:$V$17,MONTH($C50))&" "&YEAR($C50)) | K50: =IF(OR($F50="",$D50="Перевод"),"",IF(AND(N($G50)<>0,COUNTIFS(Журнал!$C$10:$C$1509,$C50,Журнал!$P$10:$P$1509,$G50)>0),"есть в Журнале",IF(COUNTIF(Постоянные!$C$8:$C$37,$F50)>0,"есть в Постоянных",IF(COUNTIF(Покупки!$C$7:$C$18,$F50)>0,"есть в Покупках","")))) | P50: =IF($C50="","",DATE(YEAR($C50),MONTH($C50),1)) | Q50: =IF(ISNUMBER($G50),ABS($G50),0) | R50: =IF(AND($D50="Расход",COUNTIFS(Счета!$B$10:$B$21,$H50,Счета!$C$10:$C$21,"Кредитная")>0),1,0)
B51: =IF(AND($C51="",$F51=""),"",ROW()-9) | J51: =IF($C51="","",INDEX(Настройки!$V$6:$V$17,MONTH($C51))&" "&YEAR($C51)) | K51: =IF(OR($F51="",$D51="Перевод"),"",IF(AND(N($G51)<>0,COUNTIFS(Журнал!$C$10:$C$1509,$C51,Журнал!$P$10:$P$1509,$G51)>0),"есть в Журнале",IF(COUNTIF(Постоянные!$C$8:$C$37,$F51)>0,"есть в Постоянных",IF(COUNTIF(Покупки!$C$7:$C$18,$F51)>0,"есть в Покупках","")))) | P51: =IF($C51="","",DATE(YEAR($C51),MONTH($C51),1)) | Q51: =IF(ISNUMBER($G51),ABS($G51),0) | R51: =IF(AND($D51="Расход",COUNTIFS(Счета!$B$10:$B$21,$H51,Счета!$C$10:$C$21,"Кредитная")>0),1,0)
B52: =IF(AND($C52="",$F52=""),"",ROW()-9) | J52: =IF($C52="","",INDEX(Настройки!$V$6:$V$17,MONTH($C52))&" "&YEAR($C52)) | K52: =IF(OR($F52="",$D52="Перевод"),"",IF(AND(N($G52)<>0,COUNTIFS(Журнал!$C$10:$C$1509,$C52,Журнал!$P$10:$P$1509,$G52)>0),"есть в Журнале",IF(COUNTIF(Постоянные!$C$8:$C$37,$F52)>0,"есть в Постоянных",IF(COUNTIF(Покупки!$C$7:$C$18,$F52)>0,"есть в Покупках","")))) | P52: =IF($C52="","",DATE(YEAR($C52),MONTH($C52),1)) | Q52: =IF(ISNUMBER($G52),ABS($G52),0) | R52: =IF(AND($D52="Расход",COUNTIFS(Счета!$B$10:$B$21,$H52,Счета!$C$10:$C$21,"Кредитная")>0),1,0)
... B1009: =IF(AND($C1009="",$F1009=""),"",ROW()-9) | J1009: =IF($C1009="","",INDEX(Настройки!$V$6:$V$17,MONTH($C1009))&" "&YEAR($C1009)) | K1009: =IF(OR($F1009="",$D1009="Перевод"),"",IF(AND(N($G1009)<>0,COUNTIFS(Журнал!$C$10:$C$1509,$C1009,Журнал!$P$10:$P$1509,$G1009)>0),"есть в Журнале",IF(COUNTIF(Постоянные!$C$8:$C$37,$F1009)>0,"есть в Постоянных",IF(COUNTIF(Покупки!$C$7:$C$18,$F1009)>0,"есть в Покупках","")))) | P1009: =IF($C1009="","",DATE(YEAR($C1009),MONTH($C1009),1)) | Q1009: =IF(ISNUMBER($G1009),ABS($G1009),0) | R1009: =IF(AND($D1009="Расход",COUNTIFS(Счета!$B$10:$B$21,$H1009,Счета!$C$10:$C$21,"Кредитная")>0),1,0)
C1011: Знак суммы не важен: тип решает, трата это или поступление (возврат — «Доход»). Трата по кредитке показывается с минусом. Плановую трату, отмеченную «Оплачено» в «Журнале», сюда не вносите.

Sheet Счета
B2: Счета
B3: Сколько денег на каждой карте, в наличных и сколько долга по кредитке
B4: Остатки на дату | C4: =Настройки!$F$8 | D4: с этой даты в остатки идут все операции, отметки и покупки | Y4: =TODAY()
C5: На картах | E5: Наличные | G5: Долг по кредитке | I5: Всего (за вычетом долга)
C6: =SUMIFS($H$10:$H$21,$C$10:$C$21,"Дебетовая")+SUMIFS($H$10:$H$21,$C$10:$C$21,"Сберегательная") | E6: =SUMIFS($H$10:$H$21,$C$10:$C$21,"Наличные") | G6: =SUM($I$10:$I$21) | I6: =SUM($H$10:$H$21)
B9: Счёт | C9: Тип | D9: На начало | E9: Поступления | F9: Траты | G9: Переводы | H9: Сейчас | I9: Долг
B10: =IF(Настройки!$N$6="","",Настройки!$N$6) | C10: Дебетовая | D10: 1000 | E10: =IF($B10="","",SUMIFS(Операции!$Q$10:$Q$1009,Операции!$D$10:$D$1009,"Доход",Операции!$H$10:$H$1009,$B10,Операции!$C$10:$C$1009,">="&$C$4)+SUMIFS(Журнал!$P$10:$P$1509,Журнал!$D$10:$D$1509,"Доход",Журнал!$J$10:$J$1509,$B10,Журнал!$R$10:$R$1509,">="&DATE(YEAR($C$4),MONTH($C$4),1))+SUMIFS(Постоянные!$AC$8:$AC$367,Постоянные!$Z$8:$Z$367,"Доход",Постоянные!$AE$8:$AE$367,$B10,Постоянные!$Y$8:$Y$367,">="&$C$4)) | F10: =IF($B10="","",SUMIFS(Операции!$Q$10:$Q$1009,Операции!$D$10:$D$1009,"Расход",Операции!$H$10:$H$1009,$B10,Операции!$C$10:$C$1009,">="&$C$4)+SUMIFS(Журнал!$P$10:$P$1509,Журнал!$D$10:$D$1509,"<>Доход",Журнал!$J$10:$J$1509,$B10,Журнал!$R$10:$R$1509,">="&DATE(YEAR($C$4),MONTH($C$4),1))+SUMIFS(Постоянные!$AC$8:$AC$367,Постоянные!$Z$8:$Z$367,"Расход",Постоянные!$AE$8:$AE$367,$B10,Постоянные!$Y$8:$Y$367,">="&$C$4)+SUMIFS(Покупки!$S$7:$S$18,Покупки!$P$7:$P$18,$B10)-SUMIFS(Покупки!$S$7:$S$18,Покупки!$P$7:$P$18,$B10,Покупки!$G$7:$G$18,"<"&$C$4)) | G10: =IF($B10="","",SUMIFS(Операции!$Q$10:$Q$1009,Операции!$D$10:$D$1009,"Перевод",Операции!$I$10:$I$1009,$B10,Операции!$C$10:$C$1009,">="&$C$4)-SUMIFS(Операции!$Q$10:$Q$1009,Операции!$D$10:$D$1009,"Перевод",Операции!$H$10:$H$1009,$B10,Операции!$C$10:$C$1009,">="&$C$4)+IF($B10=$C$32,SUM($Y$39:$Y$50),0)-IF($B10=$C$34,SUM($Y$39:$Y$50),0)) | H10: =IF($B10="","",N($D10)+$E10-$F10+$G10) | I10: =IF(AND($C10="Кредитная",N($H10)<0),$H10,"")
B11: =IF(Настройки!$N$7="","",Настройки!$N$7) | C11: Наличные | D11: 0 | E11: =IF($B11="","",SUMIFS(Операции!$Q$10:$Q$1009,Операции!$D$10:$D$1009,"Доход",Операции!$H$10:$H$1009,$B11,Операции!$C$10:$C$1009,">="&$C$4)+SUMIFS(Журнал!$P$10:$P$1509,Журнал!$D$10:$D$1509,"Доход",Журнал!$J$10:$J$1509,$B11,Журнал!$R$10:$R$1509,">="&DATE(YEAR($C$4),MONTH($C$4),1))+SUMIFS(Постоянные!$AC$8:$AC$367,Постоянные!$Z$8:$Z$367,"Доход",Постоянные!$AE$8:$AE$367,$B11,Постоянные!$Y$8:$Y$367,">="&$C$4)) | F11: =IF($B11="","",SUMIFS(Операции!$Q$10:$Q$1009,Операции!$D$10:$D$1009,"Расход",Операции!$H$10:$H$1009,$B11,Операции!$C$10:$C$1009,">="&$C$4)+SUMIFS(Журнал!$P$10:$P$1509,Журнал!$D$10:$D$1509,"<>Доход",Журнал!$J$10:$J$1509,$B11,Журнал!$R$10:$R$1509,">="&DATE(YEAR($C$4),MONTH($C$4),1))+SUMIFS(Постоянные!$AC$8:$AC$367,Постоянные!$Z$8:$Z$367,"Расход",Постоянные!$AE$8:$AE$367,$B11,Постоянные!$Y$8:$Y$367,">="&$C$4)+SUMIFS(Покупки!$S$7:$S$18,Покупки!$P$7:$P$18,$B11)-SUMIFS(Покупки!$S$7:$S$18,Покупки!$P$7:$P$18,$B11,Покупки!$G$7:$G$18,"<"&$C$4)) | G11: =IF($B11="","",SUMIFS(Операции!$Q$10:$Q$1009,Операции!$D$10:$D$1009,"Перевод",Операции!$I$10:$I$1009,$B11,Операции!$C$10:$C$1009,">="&$C$4)-SUMIFS(Операции!$Q$10:$Q$1009,Операции!$D$10:$D$1009,"Перевод",Операции!$H$10:$H$1009,$B11,Операции!$C$10:$C$1009,">="&$C$4)+IF($B11=$C$32,SUM($Y$39:$Y$50),0)-IF($B11=$C$34,SUM($Y$39:$Y$50),0)) | H11: =IF($B11="","",N($D11)+$E11-$F11+$G11) | I11: =IF(AND($C11="Кредитная",N($H11)<0),$H11,"")
B12: =IF(Настройки!$N$8="","",Настройки!$N$8) | C12: Кредитная | D12: 0 | E12: =IF($B12="","",SUMIFS(Операции!$Q$10:$Q$1009,Операции!$D$10:$D$1009,"Доход",Операции!$H$10:$H$1009,$B12,Операции!$C$10:$C$1009,">="&$C$4)+SUMIFS(Журнал!$P$10:$P$1509,Журнал!$D$10:$D$1509,"Доход",Журнал!$J$10:$J$1509,$B12,Журнал!$R$10:$R$1509,">="&DATE(YEAR($C$4),MONTH($C$4),1))+SUMIFS(Постоянные!$AC$8:$AC$367,Постоянные!$Z$8:$Z$367,"Доход",Постоянные!$AE$8:$AE$367,$B12,Постоянные!$Y$8:$Y$367,">="&$C$4)) | F12: =IF($B12="","",SUMIFS(Операции!$Q$10:$Q$1009,Операции!$D$10:$D$1009,"Расход",Операции!$H$10:$H$1009,$B12,Операции!$C$10:$C$1009,">="&$C$4)+SUMIFS(Журнал!$P$10:$P$1509,Журнал!$D$10:$D$1509,"<>Доход",Журнал!$J$10:$J$1509,$B12,Журнал!$R$10:$R$1509,">="&DATE(YEAR($C$4),MONTH($C$4),1))+SUMIFS(Постоянные!$AC$8:$AC$367,Постоянные!$Z$8:$Z$367,"Расход",Постоянные!$AE$8:$AE$367,$B12,Постоянные!$Y$8:$Y$367,">="&$C$4)+SUMIFS(Покупки!$S$7:$S$18,Покупки!$P$7:$P$18,$B12)-SUMIFS(Покупки!$S$7:$S$18,Покупки!$P$7:$P$18,$B12,Покупки!$G$7:$G$18,"<"&$C$4)) | G12: =IF($B12="","",SUMIFS(Операции!$Q$10:$Q$1009,Операции!$D$10:$D$1009,"Перевод",Операции!$I$10:$I$1009,$B12,Операции!$C$10:$C$1009,">="&$C$4)-SUMIFS(Операции!$Q$10:$Q$1009,Операции!$D$10:$D$1009,"Перевод",Операции!$H$10:$H$1009,$B12,Операции!$C$10:$C$1009,">="&$C$4)+IF($B12=$C$32,SUM($Y$39:$Y$50),0)-IF($B12=$C$34,SUM($Y$39:$Y$50),0)) | H12: =IF($B12="","",N($D12)+$E12-$F12+$G12) | I12: =IF(AND($C12="Кредитная",N($H12)<0),$H12,"")
B13: =IF(Настройки!$N$9="","",Настройки!$N$9) | E13: =IF($B13="","",SUMIFS(Операции!$Q$10:$Q$1009,Операции!$D$10:$D$1009,"Доход",Операции!$H$10:$H$1009,$B13,Операции!$C$10:$C$1009,">="&$C$4)+SUMIFS(Журнал!$P$10:$P$1509,Журнал!$D$10:$D$1509,"Доход",Журнал!$J$10:$J$1509,$B13,Журнал!$R$10:$R$1509,">="&DATE(YEAR($C$4),MONTH($C$4),1))+SUMIFS(Постоянные!$AC$8:$AC$367,Постоянные!$Z$8:$Z$367,"Доход",Постоянные!$AE$8:$AE$367,$B13,Постоянные!$Y$8:$Y$367,">="&$C$4)) | F13: =IF($B13="","",SUMIFS(Операции!$Q$10:$Q$1009,Операции!$D$10:$D$1009,"Расход",Операции!$H$10:$H$1009,$B13,Операции!$C$10:$C$1009,">="&$C$4)+SUMIFS(Журнал!$P$10:$P$1509,Журнал!$D$10:$D$1509,"<>Доход",Журнал!$J$10:$J$1509,$B13,Журнал!$R$10:$R$1509,">="&DATE(YEAR($C$4),MONTH($C$4),1))+SUMIFS(Постоянные!$AC$8:$AC$367,Постоянные!$Z$8:$Z$367,"Расход",Постоянные!$AE$8:$AE$367,$B13,Постоянные!$Y$8:$Y$367,">="&$C$4)+SUMIFS(Покупки!$S$7:$S$18,Покупки!$P$7:$P$18,$B13)-SUMIFS(Покупки!$S$7:$S$18,Покупки!$P$7:$P$18,$B13,Покупки!$G$7:$G$18,"<"&$C$4)) | G13: =IF($B13="","",SUMIFS(Операции!$Q$10:$Q$1009,Операции!$D$10:$D$1009,"Перевод",Операции!$I$10:$I$1009,$B13,Операции!$C$10:$C$1009,">="&$C$4)-SUMIFS(Операции!$Q$10:$Q$1009,Операции!$D$10:$D$1009,"Перевод",Операции!$H$10:$H$1009,$B13,Операции!$C$10:$C$1009,">="&$C$4)+IF($B13=$C$32,SUM($Y$39:$Y$50),0)-IF($B13=$C$34,SUM($Y$39:$Y$50),0)) | H13: =IF($B13="","",N($D13)+$E13-$F13+$G13) | I13: =IF(AND($C13="Кредитная",N($H13)<0),$H13,"")
B14: =IF(Настройки!$N$10="","",Настройки!$N$10) | E14: =IF($B14="","",SUMIFS(Операции!$Q$10:$Q$1009,Операции!$D$10:$D$1009,"Доход",Операции!$H$10:$H$1009,$B14,Операции!$C$10:$C$1009,">="&$C$4)+SUMIFS(Журнал!$P$10:$P$1509,Журнал!$D$10:$D$1509,"Доход",Журнал!$J$10:$J$1509,$B14,Журнал!$R$10:$R$1509,">="&DATE(YEAR($C$4),MONTH($C$4),1))+SUMIFS(Постоянные!$AC$8:$AC$367,Постоянные!$Z$8:$Z$367,"Доход",Постоянные!$AE$8:$AE$367,$B14,Постоянные!$Y$8:$Y$367,">="&$C$4)) | F14: =IF($B14="","",SUMIFS(Операции!$Q$10:$Q$1009,Операции!$D$10:$D$1009,"Расход",Операции!$H$10:$H$1009,$B14,Операции!$C$10:$C$1009,">="&$C$4)+SUMIFS(Журнал!$P$10:$P$1509,Журнал!$D$10:$D$1509,"<>Доход",Журнал!$J$10:$J$1509,$B14,Журнал!$R$10:$R$1509,">="&DATE(YEAR($C$4),MONTH($C$4),1))+SUMIFS(Постоянные!$AC$8:$AC$367,Постоянные!$Z$8:$Z$367,"Расход",Постоянные!$AE$8:$AE$367,$B14,Постоянные!$Y$8:$Y$367,">="&$C$4)+SUMIFS(Покупки!$S$7:$S$18,Покупки!$P$7:$P$18,$B14)-SUMIFS(Покупки!$S$7:$S$18,Покупки!$P$7:$P$18,$B14,Покупки!$G$7:$G$18,"<"&$C$4)) | G14: =IF($B14="","",SUMIFS(Операции!$Q$10:$Q$1009,Операции!$D$10:$D$1009,"Перевод",Операции!$I$10:$I$1009,$B14,Операции!$C$10:$C$1009,">="&$C$4)-SUMIFS(Операции!$Q$10:$Q$1009,Операции!$D$10:$D$1009,"Перевод",Операции!$H$10:$H$1009,$B14,Операции!$C$10:$C$1009,">="&$C$4)+IF($B14=$C$32,SUM($Y$39:$Y$50),0)-IF($B14=$C$34,SUM($Y$39:$Y$50),0)) | H14: =IF($B14="","",N($D14)+$E14-$F14+$G14) | I14: =IF(AND($C14="Кредитная",N($H14)<0),$H14,"")
B15: =IF(Настройки!$N$11="","",Настройки!$N$11) | E15: =IF($B15="","",SUMIFS(Операции!$Q$10:$Q$1009,Операции!$D$10:$D$1009,"Доход",Операции!$H$10:$H$1009,$B15,Операции!$C$10:$C$1009,">="&$C$4)+SUMIFS(Журнал!$P$10:$P$1509,Журнал!$D$10:$D$1509,"Доход",Журнал!$J$10:$J$1509,$B15,Журнал!$R$10:$R$1509,">="&DATE(YEAR($C$4),MONTH($C$4),1))+SUMIFS(Постоянные!$AC$8:$AC$367,Постоянные!$Z$8:$Z$367,"Доход",Постоянные!$AE$8:$AE$367,$B15,Постоянные!$Y$8:$Y$367,">="&$C$4)) | F15: =IF($B15="","",SUMIFS(Операции!$Q$10:$Q$1009,Операции!$D$10:$D$1009,"Расход",Операции!$H$10:$H$1009,$B15,Операции!$C$10:$C$1009,">="&$C$4)+SUMIFS(Журнал!$P$10:$P$1509,Журнал!$D$10:$D$1509,"<>Доход",Журнал!$J$10:$J$1509,$B15,Журнал!$R$10:$R$1509,">="&DATE(YEAR($C$4),MONTH($C$4),1))+SUMIFS(Постоянные!$AC$8:$AC$367,Постоянные!$Z$8:$Z$367,"Расход",Постоянные!$AE$8:$AE$367,$B15,Постоянные!$Y$8:$Y$367,">="&$C$4)+SUMIFS(Покупки!$S$7:$S$18,Покупки!$P$7:$P$18,$B15)-SUMIFS(Покупки!$S$7:$S$18,Покупки!$P$7:$P$18,$B15,Покупки!$G$7:$G$18,"<"&$C$4)) | G15: =IF($B15="","",SUMIFS(Операции!$Q$10:$Q$1009,Операции!$D$10:$D$1009,"Перевод",Операции!$I$10:$I$1009,$B15,Операции!$C$10:$C$1009,">="&$C$4)-SUMIFS(Операции!$Q$10:$Q$1009,Операции!$D$10:$D$1009,"Перевод",Операции!$H$10:$H$1009,$B15,Операции!$C$10:$C$1009,">="&$C$4)+IF($B15=$C$32,SUM($Y$39:$Y$50),0)-IF($B15=$C$34,SUM($Y$39:$Y$50),0)) | H15: =IF($B15="","",N($D15)+$E15-$F15+$G15) | I15: =IF(AND($C15="Кредитная",N($H15)<0),$H15,"")
B16: =IF(Настройки!$N$12="","",Настройки!$N$12) | E16: =IF($B16="","",SUMIFS(Операции!$Q$10:$Q$1009,Операции!$D$10:$D$1009,"Доход",Операции!$H$10:$H$1009,$B16,Операции!$C$10:$C$1009,">="&$C$4)+SUMIFS(Журнал!$P$10:$P$1509,Журнал!$D$10:$D$1509,"Доход",Журнал!$J$10:$J$1509,$B16,Журнал!$R$10:$R$1509,">="&DATE(YEAR($C$4),MONTH($C$4),1))+SUMIFS(Постоянные!$AC$8:$AC$367,Постоянные!$Z$8:$Z$367,"Доход",Постоянные!$AE$8:$AE$367,$B16,Постоянные!$Y$8:$Y$367,">="&$C$4)) | F16: =IF($B16="","",SUMIFS(Операции!$Q$10:$Q$1009,Операции!$D$10:$D$1009,"Расход",Операции!$H$10:$H$1009,$B16,Операции!$C$10:$C$1009,">="&$C$4)+SUMIFS(Журнал!$P$10:$P$1509,Журнал!$D$10:$D$1509,"<>Доход",Журнал!$J$10:$J$1509,$B16,Журнал!$R$10:$R$1509,">="&DATE(YEAR($C$4),MONTH($C$4),1))+SUMIFS(Постоянные!$AC$8:$AC$367,Постоянные!$Z$8:$Z$367,"Расход",Постоянные!$AE$8:$AE$367,$B16,Постоянные!$Y$8:$Y$367,">="&$C$4)+SUMIFS(Покупки!$S$7:$S$18,Покупки!$P$7:$P$18,$B16)-SUMIFS(Покупки!$S$7:$S$18,Покупки!$P$7:$P$18,$B16,Покупки!$G$7:$G$18,"<"&$C$4)) | G16: =IF($B16="","",SUMIFS(Операции!$Q$10:$Q$1009,Операции!$D$10:$D$1009,"Перевод",Операции!$I$10:$I$1009,$B16,Операции!$C$10:$C$1009,">="&$C$4)-SUMIFS(Операции!$Q$10:$Q$1009,Операции!$D$10:$D$1009,"Перевод",Операции!$H$10:$H$1009,$B16,Операции!$C$10:$C$1009,">="&$C$4)+IF($B16=$C$32,SUM($Y$39:$Y$50),0)-IF($B16=$C$34,SUM($Y$39:$Y$50),0)) | H16: =IF($B16="","",N($D16)+$E16-$F16+$G16) | I16: =IF(AND($C16="Кредитная",N($H16)<0),$H16,"")
B17: =IF(Настройки!$N$13="","",Настройки!$N$13) | E17: =IF($B17="","",SUMIFS(Операции!$Q$10:$Q$1009,Операции!$D$10:$D$1009,"Доход",Операции!$H$10:$H$1009,$B17,Операции!$C$10:$C$1009,">="&$C$4)+SUMIFS(Журнал!$P$10:$P$1509,Журнал!$D$10:$D$1509,"Доход",Журнал!$J$10:$J$1509,$B17,Журнал!$R$10:$R$1509,">="&DATE(YEAR($C$4),MONTH($C$4),1))+SUMIFS(Постоянные!$AC$8:$AC$367,Постоянные!$Z$8:$Z$367,"Доход",Постоянные!$AE$8:$AE$367,$B17,Постоянные!$Y$8:$Y$367,">="&$C$4)) | F17: =IF($B17="","",SUMIFS(Операции!$Q$10:$Q$1009,Операции!$D$10:$D$1009,"Расход",Операции!$H$10:$H$1009,$B17,Операции!$C$10:$C$1009,">="&$C$4)+SUMIFS(Журнал!$P$10:$P$1509,Журнал!$D$10:$D$1509,"<>Доход",Журнал!$J$10:$J$1509,$B17,Журнал!$R$10:$R$1509,">="&DATE(YEAR($C$4),MONTH($C$4),1))+SUMIFS(Постоянные!$AC$8:$AC$367,Постоянные!$Z$8:$Z$367,"Расход",Постоянные!$AE$8:$AE$367,$B17,Постоянные!$Y$8:$Y$367,">="&$C$4)+SUMIFS(Покупки!$S$7:$S$18,Покупки!$P$7:$P$18,$B17)-SUMIFS(Покупки!$S$7:$S$18,Покупки!$P$7:$P$18,$B17,Покупки!$G$7:$G$18,"<"&$C$4)) | G17: =IF($B17="","",SUMIFS(Операции!$Q$10:$Q$1009,Операции!$D$10:$D$1009,"Перевод",Операции!$I$10:$I$1009,$B17,Операции!$C$10:$C$1009,">="&$C$4)-SUMIFS(Операции!$Q$10:$Q$1009,Операции!$D$10:$D$1009,"Перевод",Операции!$H$10:$H$1009,$B17,Операции!$C$10:$C$1009,">="&$C$4)+IF($B17=$C$32,SUM($Y$39:$Y$50),0)-IF($B17=$C$34,SUM($Y$39:$Y$50),0)) | H17: =IF($B17="","",N($D17)+$E17-$F17+$G17) | I17: =IF(AND($C17="Кредитная",N($H17)<0),$H17,"")
B18: =IF(Настройки!$N$14="","",Настройки!$N$14) | E18: =IF($B18="","",SUMIFS(Операции!$Q$10:$Q$1009,Операции!$D$10:$D$1009,"Доход",Операции!$H$10:$H$1009,$B18,Операции!$C$10:$C$1009,">="&$C$4)+SUMIFS(Журнал!$P$10:$P$1509,Журнал!$D$10:$D$1509,"Доход",Журнал!$J$10:$J$1509,$B18,Журнал!$R$10:$R$1509,">="&DATE(YEAR($C$4),MONTH($C$4),1))+SUMIFS(Постоянные!$AC$8:$AC$367,Постоянные!$Z$8:$Z$367,"Доход",Постоянные!$AE$8:$AE$367,$B18,Постоянные!$Y$8:$Y$367,">="&$C$4)) | F18: =IF($B18="","",SUMIFS(Операции!$Q$10:$Q$1009,Операции!$D$10:$D$1009,"Расход",Операции!$H$10:$H$1009,$B18,Операции!$C$10:$C$1009,">="&$C$4)+SUMIFS(Журнал!$P$10:$P$1509,Журнал!$D$10:$D$1509,"<>Доход",Журнал!$J$10:$J$1509,$B18,Журнал!$R$10:$R$1509,">="&DATE(YEAR($C$4),MONTH($C$4),1))+SUMIFS(Постоянные!$AC$8:$AC$367,Постоянные!$Z$8:$Z$367,"Расход",Постоянные!$AE$8:$AE$367,$B18,Постоянные!$Y$8:$Y$367,">="&$C$4)+SUMIFS(Покупки!$S$7:$S$18,Покупки!$P$7:$P$18,$B18)-SUMIFS(Покупки!$S$7:$S$18,Покупки!$P$7:$P$18,$B18,Покупки!$G$7:$G$18,"<"&$C$4)) | G18: =IF($B18="","",SUMIFS(Операции!$Q$10:$Q$1009,Операции!$D$10:$D$1009,"Перевод",Операции!$I$10:$I$1009,$B18,Операции!$C$10:$C$1009,">="&$C$4)-SUMIFS(Операции!$Q$10:$Q$1009,Операции!$D$10:$D$1009,"Перевод",Операции!$H$10:$H$1009,$B18,Операции!$C$10:$C$1009,">="&$C$4)+IF($B18=$C$32,SUM($Y$39:$Y$50),0)-IF($B18=$C$34,SUM($Y$39:$Y$50),0)) | H18: =IF($B18="","",N($D18)+$E18-$F18+$G18) | I18: =IF(AND($C18="Кредитная",N($H18)<0),$H18,"")
B19: =IF(Настройки!$N$15="","",Настройки!$N$15) | E19: =IF($B19="","",SUMIFS(Операции!$Q$10:$Q$1009,Операции!$D$10:$D$1009,"Доход",Операции!$H$10:$H$1009,$B19,Операции!$C$10:$C$1009,">="&$C$4)+SUMIFS(Журнал!$P$10:$P$1509,Журнал!$D$10:$D$1509,"Доход",Журнал!$J$10:$J$1509,$B19,Журнал!$R$10:$R$1509,">="&DATE(YEAR($C$4),MONTH($C$4),1))+SUMIFS(Постоянные!$AC$8:$AC$367,Постоянные!$Z$8:$Z$367,"Доход",Постоянные!$AE$8:$AE$367,$B19,Постоянные!$Y$8:$Y$367,">="&$C$4)) | F19: =IF($B19="","",SUMIFS(Операции!$Q$10:$Q$1009,Операции!$D$10:$D$1009,"Расход",Операции!$H$10:$H$1009,$B19,Операции!$C$10:$C$1009,">="&$C$4)+SUMIFS(Журнал!$P$10:$P$1509,Журнал!$D$10:$D$1509,"<>Доход",Журнал!$J$10:$J$1509,$B19,Журнал!$R$10:$R$1509,">="&DATE(YEAR($C$4),MONTH($C$4),1))+SUMIFS(Постоянные!$AC$8:$AC$367,Постоянные!$Z$8:$Z$367,"Расход",Постоянные!$AE$8:$AE$367,$B19,Постоянные!$Y$8:$Y$367,">="&$C$4)+SUMIFS(Покупки!$S$7:$S$18,Покупки!$P$7:$P$18,$B19)-SUMIFS(Покупки!$S$7:$S$18,Покупки!$P$7:$P$18,$B19,Покупки!$G$7:$G$18,"<"&$C$4)) | G19: =IF($B19="","",SUMIFS(Операции!$Q$10:$Q$1009,Операции!$D$10:$D$1009,"Перевод",Операции!$I$10:$I$1009,$B19,Операции!$C$10:$C$1009,">="&$C$4)-SUMIFS(Операции!$Q$10:$Q$1009,Операции!$D$10:$D$1009,"Перевод",Операции!$H$10:$H$1009,$B19,Операции!$C$10:$C$1009,">="&$C$4)+IF($B19=$C$32,SUM($Y$39:$Y$50),0)-IF($B19=$C$34,SUM($Y$39:$Y$50),0)) | H19: =IF($B19="","",N($D19)+$E19-$F19+$G19) | I19: =IF(AND($C19="Кредитная",N($H19)<0),$H19,"")
B20: =IF(Настройки!$N$16="","",Настройки!$N$16) | E20: =IF($B20="","",SUMIFS(Операции!$Q$10:$Q$1009,Операции!$D$10:$D$1009,"Доход",Операции!$H$10:$H$1009,$B20,Операции!$C$10:$C$1009,">="&$C$4)+SUMIFS(Журнал!$P$10:$P$1509,Журнал!$D$10:$D$1509,"Доход",Журнал!$J$10:$J$1509,$B20,Журнал!$R$10:$R$1509,">="&DATE(YEAR($C$4),MONTH($C$4),1))+SUMIFS(Постоянные!$AC$8:$AC$367,Постоянные!$Z$8:$Z$367,"Доход",Постоянные!$AE$8:$AE$367,$B20,Постоянные!$Y$8:$Y$367,">="&$C$4)) | F20: =IF($B20="","",SUMIFS(Операции!$Q$10:$Q$1009,Операции!$D$10:$D$1009,"Расход",Операции!$H$10:$H$1009,$B20,Операции!$C$10:$C$1009,">="&$C$4)+SUMIFS(Журнал!$P$10:$P$1509,Журнал!$D$10:$D$1509,"<>Доход",Журнал!$J$10:$J$1509,$B20,Журнал!$R$10:$R$1509,">="&DATE(YEAR($C$4),MONTH($C$4),1))+SUMIFS(Постоянные!$AC$8:$AC$367,Постоянные!$Z$8:$Z$367,"Расход",Постоянные!$AE$8:$AE$367,$B20,Постоянные!$Y$8:$Y$367,">="&$C$4)+SUMIFS(Покупки!$S$7:$S$18,Покупки!$P$7:$P$18,$B20)-SUMIFS(Покупки!$S$7:$S$18,Покупки!$P$7:$P$18,$B20,Покупки!$G$7:$G$18,"<"&$C$4)) | G20: =IF($B20="","",SUMIFS(Операции!$Q$10:$Q$1009,Операции!$D$10:$D$1009,"Перевод",Операции!$I$10:$I$1009,$B20,Операции!$C$10:$C$1009,">="&$C$4)-SUMIFS(Операции!$Q$10:$Q$1009,Операции!$D$10:$D$1009,"Перевод",Операции!$H$10:$H$1009,$B20,Операции!$C$10:$C$1009,">="&$C$4)+IF($B20=$C$32,SUM($Y$39:$Y$50),0)-IF($B20=$C$34,SUM($Y$39:$Y$50),0)) | H20: =IF($B20="","",N($D20)+$E20-$F20+$G20) | I20: =IF(AND($C20="Кредитная",N($H20)<0),$H20,"")
B21: =IF(Настройки!$N$17="","",Настройки!$N$17) | E21: =IF($B21="","",SUMIFS(Операции!$Q$10:$Q$1009,Операции!$D$10:$D$1009,"Доход",Операции!$H$10:$H$1009,$B21,Операции!$C$10:$C$1009,">="&$C$4)+SUMIFS(Журнал!$P$10:$P$1509,Журнал!$D$10:$D$1509,"Доход",Журнал!$J$10:$J$1509,$B21,Журнал!$R$10:$R$1509,">="&DATE(YEAR($C$4),MONTH($C$4),1))+SUMIFS(Постоянные!$AC$8:$AC$367,Постоянные!$Z$8:$Z$367,"Доход",Постоянные!$AE$8:$AE$367,$B21,Постоянные!$Y$8:$Y$367,">="&$C$4)) | F21: =IF($B21="","",SUMIFS(Операции!$Q$10:$Q$1009,Операции!$D$10:$D$1009,"Расход",Операции!$H$10:$H$1009,$B21,Операции!$C$10:$C$1009,">="&$C$4)+SUMIFS(Журнал!$P$10:$P$1509,Журнал!$D$10:$D$1509,"<>Доход",Журнал!$J$10:$J$1509,$B21,Журнал!$R$10:$R$1509,">="&DATE(YEAR($C$4),MONTH($C$4),1))+SUMIFS(Постоянные!$AC$8:$AC$367,Постоянные!$Z$8:$Z$367,"Расход",Постоянные!$AE$8:$AE$367,$B21,Постоянные!$Y$8:$Y$367,">="&$C$4)+SUMIFS(Покупки!$S$7:$S$18,Покупки!$P$7:$P$18,$B21)-SUMIFS(Покупки!$S$7:$S$18,Покупки!$P$7:$P$18,$B21,Покупки!$G$7:$G$18,"<"&$C$4)) | G21: =IF($B21="","",SUMIFS(Операции!$Q$10:$Q$1009,Операции!$D$10:$D$1009,"Перевод",Операции!$I$10:$I$1009,$B21,Операции!$C$10:$C$1009,">="&$C$4)-SUMIFS(Операции!$Q$10:$Q$1009,Операции!$D$10:$D$1009,"Перевод",Операции!$H$10:$H$1009,$B21,Операции!$C$10:$C$1009,">="&$C$4)+IF($B21=$C$32,SUM($Y$39:$Y$50),0)-IF($B21=$C$34,SUM($Y$39:$Y$50),0)) | H21: =IF($B21="","",N($D21)+$E21-$F21+$G21) | I21: =IF(AND($C21="Кредитная",N($H21)<0),$H21,"")
B22: ИТОГО | D22: =SUM(D10:D21) | E22: =SUM(E10:E21) | F22: =SUM(F10:F21) | G22: =SUM(G10:G21) | H22: =SUM(H10:H21) | I22: =SUM(I10:I21)
B24: Проверка: всё ли попадает в остатки
B25: Оплачено без счёта — строк | D25: =COUNTIFS(Журнал!$P$10:$P$1509,"<>0",Журнал!$J$10:$J$1509,"")+COUNTIFS(Операции!$G$10:$G$1009,"<>",Операции!$H$10:$H$1009,"")+COUNTIFS(Постоянные!$AC$8:$AC$367,"<>0",Постоянные!$AE$8:$AE$367,"")+COUNTIFS(Покупки!$S$7:$S$18,"<>0",Покупки!$P$7:$P$18,"")
B26: …на сумму | D26: =SUMIFS(Журнал!$P$10:$P$1509,Журнал!$J$10:$J$1509,"")+SUMIFS(Операции!$Q$10:$Q$1009,Операции!$H$10:$H$1009,"")+SUMIFS(Постоянные!$AC$8:$AC$367,Постоянные!$AE$8:$AE$367,"")+SUMIFS(Покупки!$S$7:$S$18,Покупки!$P$7:$P$18,"")
B27: Переводов без «на счёт» | D27: =COUNTIFS(Операции!$D$10:$D$1009,"Перевод",Операции!$I$10:$I$1009,"")
B29: Долг по кредитке — со знаком минус (например −350). Снятие наличных и перевод между картами — в «Операциях», тип «Перевод»; погашение кредитки считается само (таблица ниже). Остаток «Сейчас» учитывает всё, что отмечено оплаченным, в том числе отметки на будущие даты.
B31: Кредитная карта: выписки и погашения
B32: Кредитная карта | C32: =IFERROR(INDEX($B$10:$B$21,MATCH("Кредитная",$C$10:$C$21,0)),"")
B33: Гасится автоматически | C33: Да
B34: Со счёта | C34: =Настройки!$N$6
B35: Выписка закрывается (число) | C35: 4
B36: Долг списывается (число) | C36: 10
B37: Ближайшее списание | C37: =IF((COUNTIF($H$39:$H$50,"<"&$Y$4)+1)>12,"—",INDEX($H$39:$H$50,(COUNTIF($H$39:$H$50,"<"&$Y$4)+1))) | D37: =IF((COUNTIF($H$39:$H$50,"<"&$Y$4)+1)>12,0,INDEX($I$39:$I$50,(COUNTIF($H$39:$H$50,"<"&$Y$4)+1))) | E37: =IF($C$33="Да","спишется со счёта «"&$C$34&"»","гасите вручную: «Операции», «Перевод»")
B38: Выписка на | C38: Долг с прошлой выписки | D38: Погашено | E38: Покупки | F38: Возвраты и переводы | G38: Долг по выписке | H38: Спишется | I38: Сумма списания
B39: =DATE(Настройки!$C$8,Настройки!$D$9+0,MAX(1,MIN(28,N($C$35)))) | C39: =IF($C$32="",0,MIN(0,SUMIFS($D$10:$D$21,$B$10:$B$21,$C$32))) | D39: =0 | E39: =IF($C$32="",0,-(SUMIFS(Операции!$Q$10:$Q$1009,Операции!$D$10:$D$1009,"Расход",Операции!$H$10:$H$1009,$C$32,Операции!$C$10:$C$1009,">="&$X39,Операции!$C$10:$C$1009,"<="&$B39)+SUMIFS(Журнал!$P$10:$P$1509,Журнал!$D$10:$D$1509,"<>Доход",Журнал!$J$10:$J$1509,$C$32,Журнал!$C$10:$C$1509,">="&$X39,Журнал!$C$10:$C$1509,"<="&$B39)+SUMIFS(Постоянные!$AC$8:$AC$367,Постоянные!$Z$8:$Z$367,"Расход",Постоянные!$AE$8:$AE$367,$C$32,Постоянные!$Y$8:$Y$367,">="&$X39,Постоянные!$Y$8:$Y$367,"<="&$B39)+SUMIFS(Покупки!$S$7:$S$18,Покупки!$P$7:$P$18,$C$32,Покупки!$G$7:$G$18,">="&$X39,Покупки!$G$7:$G$18,"<="&$B39))) | F39: =IF($C$32="",0,SUMIFS(Операции!$Q$10:$Q$1009,Операции!$D$10:$D$1009,"Доход",Операции!$H$10:$H$1009,$C$32,Операции!$C$10:$C$1009,">="&$X39,Операции!$C$10:$C$1009,"<="&$B39)+SUMIFS(Журнал!$P$10:$P$1509,Журнал!$D$10:$D$1509,"Доход",Журнал!$J$10:$J$1509,$C$32,Журнал!$C$10:$C$1509,">="&$X39,Журнал!$C$10:$C$1509,"<="&$B39)+SUMIFS(Постоянные!$AC$8:$AC$367,Постоянные!$Z$8:$Z$367,"Доход",Постоянные!$AE$8:$AE$367,$C$32,Постоянные!$Y$8:$Y$367,">="&$X39,Постоянные!$Y$8:$Y$367,"<="&$B39)+SUMIFS(Операции!$Q$10:$Q$1009,Операции!$D$10:$D$1009,"Перевод",Операции!$I$10:$I$1009,$C$32,Операции!$C$10:$C$1009,">="&$X39,Операции!$C$10:$C$1009,"<="&$B39)-SUMIFS(Операции!$Q$10:$Q$1009,Операции!$D$10:$D$1009,"Перевод",Операции!$H$10:$H$1009,$C$32,Операции!$C$10:$C$1009,">="&$X39,Операции!$C$10:$C$1009,"<="&$B39)) | G39: =C39+D39+E39+F39 | H39: =DATE(YEAR(B39),MONTH(B39),MAX(1,MIN(28,N($C$36)))) | I39: =IF($C$33="Да",-MIN(0,G39),0) | X39: =$C$4 | Y39: =IF(AND(H39<=$Y$4,H39>=$C$4),I39,0)
B40: =DATE(Настройки!$C$8,Настройки!$D$9+1,MAX(1,MIN(28,N($C$35)))) | C40: =G39 | D40: =I39 | E40: =IF($C$32="",0,-(SUMIFS(Операции!$Q$10:$Q$1009,Операции!$D$10:$D$1009,"Расход",Операции!$H$10:$H$1009,$C$32,Операции!$C$10:$C$1009,">="&$X40,Операции!$C$10:$C$1009,"<="&$B40)+SUMIFS(Журнал!$P$10:$P$1509,Журнал!$D$10:$D$1509,"<>Доход",Журнал!$J$10:$J$1509,$C$32,Журнал!$C$10:$C$1509,">="&$X40,Журнал!$C$10:$C$1509,"<="&$B40)+SUMIFS(Постоянные!$AC$8:$AC$367,Постоянные!$Z$8:$Z$367,"Расход",Постоянные!$AE$8:$AE$367,$C$32,Постоянные!$Y$8:$Y$367,">="&$X40,Постоянные!$Y$8:$Y$367,"<="&$B40)+SUMIFS(Покупки!$S$7:$S$18,Покупки!$P$7:$P$18,$C$32,Покупки!$G$7:$G$18,">="&$X40,Покупки!$G$7:$G$18,"<="&$B40))) | F40: =IF($C$32="",0,SUMIFS(Операции!$Q$10:$Q$1009,Операции!$D$10:$D$1009,"Доход",Операции!$H$10:$H$1009,$C$32,Операции!$C$10:$C$1009,">="&$X40,Операции!$C$10:$C$1009,"<="&$B40)+SUMIFS(Журнал!$P$10:$P$1509,Журнал!$D$10:$D$1509,"Доход",Журнал!$J$10:$J$1509,$C$32,Журнал!$C$10:$C$1509,">="&$X40,Журнал!$C$10:$C$1509,"<="&$B40)+SUMIFS(Постоянные!$AC$8:$AC$367,Постоянные!$Z$8:$Z$367,"Доход",Постоянные!$AE$8:$AE$367,$C$32,Постоянные!$Y$8:$Y$367,">="&$X40,Постоянные!$Y$8:$Y$367,"<="&$B40)+SUMIFS(Операции!$Q$10:$Q$1009,Операции!$D$10:$D$1009,"Перевод",Операции!$I$10:$I$1009,$C$32,Операции!$C$10:$C$1009,">="&$X40,Операции!$C$10:$C$1009,"<="&$B40)-SUMIFS(Операции!$Q$10:$Q$1009,Операции!$D$10:$D$1009,"Перевод",Операции!$H$10:$H$1009,$C$32,Операции!$C$10:$C$1009,">="&$X40,Операции!$C$10:$C$1009,"<="&$B40)) | G40: =C40+D40+E40+F40 | H40: =DATE(YEAR(B40),MONTH(B40),MAX(1,MIN(28,N($C$36)))) | I40: =IF($C$33="Да",-MIN(0,G40),0) | X40: =B39+1 | Y40: =IF(AND(H40<=$Y$4,H40>=$C$4),I40,0)
B41: =DATE(Настройки!$C$8,Настройки!$D$9+2,MAX(1,MIN(28,N($C$35)))) | C41: =G40 | D41: =I40 | E41: =IF($C$32="",0,-(SUMIFS(Операции!$Q$10:$Q$1009,Операции!$D$10:$D$1009,"Расход",Операции!$H$10:$H$1009,$C$32,Операции!$C$10:$C$1009,">="&$X41,Операции!$C$10:$C$1009,"<="&$B41)+SUMIFS(Журнал!$P$10:$P$1509,Журнал!$D$10:$D$1509,"<>Доход",Журнал!$J$10:$J$1509,$C$32,Журнал!$C$10:$C$1509,">="&$X41,Журнал!$C$10:$C$1509,"<="&$B41)+SUMIFS(Постоянные!$AC$8:$AC$367,Постоянные!$Z$8:$Z$367,"Расход",Постоянные!$AE$8:$AE$367,$C$32,Постоянные!$Y$8:$Y$367,">="&$X41,Постоянные!$Y$8:$Y$367,"<="&$B41)+SUMIFS(Покупки!$S$7:$S$18,Покупки!$P$7:$P$18,$C$32,Покупки!$G$7:$G$18,">="&$X41,Покупки!$G$7:$G$18,"<="&$B41))) | F41: =IF($C$32="",0,SUMIFS(Операции!$Q$10:$Q$1009,Операции!$D$10:$D$1009,"Доход",Операции!$H$10:$H$1009,$C$32,Операции!$C$10:$C$1009,">="&$X41,Операции!$C$10:$C$1009,"<="&$B41)+SUMIFS(Журнал!$P$10:$P$1509,Журнал!$D$10:$D$1509,"Доход",Журнал!$J$10:$J$1509,$C$32,Журнал!$C$10:$C$1509,">="&$X41,Журнал!$C$10:$C$1509,"<="&$B41)+SUMIFS(Постоянные!$AC$8:$AC$367,Постоянные!$Z$8:$Z$367,"Доход",Постоянные!$AE$8:$AE$367,$C$32,Постоянные!$Y$8:$Y$367,">="&$X41,Постоянные!$Y$8:$Y$367,"<="&$B41)+SUMIFS(Операции!$Q$10:$Q$1009,Операции!$D$10:$D$1009,"Перевод",Операции!$I$10:$I$1009,$C$32,Операции!$C$10:$C$1009,">="&$X41,Операции!$C$10:$C$1009,"<="&$B41)-SUMIFS(Операции!$Q$10:$Q$1009,Операции!$D$10:$D$1009,"Перевод",Операции!$H$10:$H$1009,$C$32,Операции!$C$10:$C$1009,">="&$X41,Операции!$C$10:$C$1009,"<="&$B41)) | G41: =C41+D41+E41+F41 | H41: =DATE(YEAR(B41),MONTH(B41),MAX(1,MIN(28,N($C$36)))) | I41: =IF($C$33="Да",-MIN(0,G41),0) | X41: =B40+1 | Y41: =IF(AND(H41<=$Y$4,H41>=$C$4),I41,0)
B42: =DATE(Настройки!$C$8,Настройки!$D$9+3,MAX(1,MIN(28,N($C$35)))) | C42: =G41 | D42: =I41 | E42: =IF($C$32="",0,-(SUMIFS(Операции!$Q$10:$Q$1009,Операции!$D$10:$D$1009,"Расход",Операции!$H$10:$H$1009,$C$32,Операции!$C$10:$C$1009,">="&$X42,Операции!$C$10:$C$1009,"<="&$B42)+SUMIFS(Журнал!$P$10:$P$1509,Журнал!$D$10:$D$1509,"<>Доход",Журнал!$J$10:$J$1509,$C$32,Журнал!$C$10:$C$1509,">="&$X42,Журнал!$C$10:$C$1509,"<="&$B42)+SUMIFS(Постоянные!$AC$8:$AC$367,Постоянные!$Z$8:$Z$367,"Расход",Постоянные!$AE$8:$AE$367,$C$32,Постоянные!$Y$8:$Y$367,">="&$X42,Постоянные!$Y$8:$Y$367,"<="&$B42)+SUMIFS(Покупки!$S$7:$S$18,Покупки!$P$7:$P$18,$C$32,Покупки!$G$7:$G$18,">="&$X42,Покупки!$G$7:$G$18,"<="&$B42))) | F42: =IF($C$32="",0,SUMIFS(Операции!$Q$10:$Q$1009,Операции!$D$10:$D$1009,"Доход",Операции!$H$10:$H$1009,$C$32,Операции!$C$10:$C$1009,">="&$X42,Операции!$C$10:$C$1009,"<="&$B42)+SUMIFS(Журнал!$P$10:$P$1509,Журнал!$D$10:$D$1509,"Доход",Журнал!$J$10:$J$1509,$C$32,Журнал!$C$10:$C$1509,">="&$X42,Журнал!$C$10:$C$1509,"<="&$B42)+SUMIFS(Постоянные!$AC$8:$AC$367,Постоянные!$Z$8:$Z$367,"Доход",Постоянные!$AE$8:$AE$367,$C$32,Постоянные!$Y$8:$Y$367,">="&$X42,Постоянные!$Y$8:$Y$367,"<="&$B42)+SUMIFS(Операции!$Q$10:$Q$1009,Операции!$D$10:$D$1009,"Перевод",Операции!$I$10:$I$1009,$C$32,Операции!$C$10:$C$1009,">="&$X42,Операции!$C$10:$C$1009,"<="&$B42)-SUMIFS(Операции!$Q$10:$Q$1009,Операции!$D$10:$D$1009,"Перевод",Операции!$H$10:$H$1009,$C$32,Операции!$C$10:$C$1009,">="&$X42,Операции!$C$10:$C$1009,"<="&$B42)) | G42: =C42+D42+E42+F42 | H42: =DATE(YEAR(B42),MONTH(B42),MAX(1,MIN(28,N($C$36)))) | I42: =IF($C$33="Да",-MIN(0,G42),0) | X42: =B41+1 | Y42: =IF(AND(H42<=$Y$4,H42>=$C$4),I42,0)
B43: =DATE(Настройки!$C$8,Настройки!$D$9+4,MAX(1,MIN(28,N($C$35)))) | C43: =G42 | D43: =I42 | E43: =IF($C$32="",0,-(SUMIFS(Операции!$Q$10:$Q$1009,Операции!$D$10:$D$1009,"Расход",Операции!$H$10:$H$1009,$C$32,Операции!$C$10:$C$1009,">="&$X43,Операции!$C$10:$C$1009,"<="&$B43)+SUMIFS(Журнал!$P$10:$P$1509,Журнал!$D$10:$D$1509,"<>Доход",Журнал!$J$10:$J$1509,$C$32,Журнал!$C$10:$C$1509,">="&$X43,Журнал!$C$10:$C$1509,"<="&$B43)+SUMIFS(Постоянные!$AC$8:$AC$367,Постоянные!$Z$8:$Z$367,"Расход",Постоянные!$AE$8:$AE$367,$C$32,Постоянные!$Y$8:$Y$367,">="&$X43,Постоянные!$Y$8:$Y$367,"<="&$B43)+SUMIFS(Покупки!$S$7:$S$18,Покупки!$P$7:$P$18,$C$32,Покупки!$G$7:$G$18,">="&$X43,Покупки!$G$7:$G$18,"<="&$B43))) | F43: =IF($C$32="",0,SUMIFS(Операции!$Q$10:$Q$1009,Операции!$D$10:$D$1009,"Доход",Операции!$H$10:$H$1009,$C$32,Операции!$C$10:$C$1009,">="&$X43,Операции!$C$10:$C$1009,"<="&$B43)+SUMIFS(Журнал!$P$10:$P$1509,Журнал!$D$10:$D$1509,"Доход",Журнал!$J$10:$J$1509,$C$32,Журнал!$C$10:$C$1509,">="&$X43,Журнал!$C$10:$C$1509,"<="&$B43)+SUMIFS(Постоянные!$AC$8:$AC$367,Постоянные!$Z$8:$Z$367,"Доход",Постоянные!$AE$8:$AE$367,$C$32,Постоянные!$Y$8:$Y$367,">="&$X43,Постоянные!$Y$8:$Y$367,"<="&$B43)+SUMIFS(Операции!$Q$10:$Q$1009,Операции!$D$10:$D$1009,"Перевод",Операции!$I$10:$I$1009,$C$32,Операции!$C$10:$C$1009,">="&$X43,Операции!$C$10:$C$1009,"<="&$B43)-SUMIFS(Операции!$Q$10:$Q$1009,Операции!$D$10:$D$1009,"Перевод",Операции!$H$10:$H$1009,$C$32,Операции!$C$10:$C$1009,">="&$X43,Операции!$C$10:$C$1009,"<="&$B43)) | G43: =C43+D43+E43+F43 | H43: =DATE(YEAR(B43),MONTH(B43),MAX(1,MIN(28,N($C$36)))) | I43: =IF($C$33="Да",-MIN(0,G43),0) | X43: =B42+1 | Y43: =IF(AND(H43<=$Y$4,H43>=$C$4),I43,0)
B44: =DATE(Настройки!$C$8,Настройки!$D$9+5,MAX(1,MIN(28,N($C$35)))) | C44: =G43 | D44: =I43 | E44: =IF($C$32="",0,-(SUMIFS(Операции!$Q$10:$Q$1009,Операции!$D$10:$D$1009,"Расход",Операции!$H$10:$H$1009,$C$32,Операции!$C$10:$C$1009,">="&$X44,Операции!$C$10:$C$1009,"<="&$B44)+SUMIFS(Журнал!$P$10:$P$1509,Журнал!$D$10:$D$1509,"<>Доход",Журнал!$J$10:$J$1509,$C$32,Журнал!$C$10:$C$1509,">="&$X44,Журнал!$C$10:$C$1509,"<="&$B44)+SUMIFS(Постоянные!$AC$8:$AC$367,Постоянные!$Z$8:$Z$367,"Расход",Постоянные!$AE$8:$AE$367,$C$32,Постоянные!$Y$8:$Y$367,">="&$X44,Постоянные!$Y$8:$Y$367,"<="&$B44)+SUMIFS(Покупки!$S$7:$S$18,Покупки!$P$7:$P$18,$C$32,Покупки!$G$7:$G$18,">="&$X44,Покупки!$G$7:$G$18,"<="&$B44))) | F44: =IF($C$32="",0,SUMIFS(Операции!$Q$10:$Q$1009,Операции!$D$10:$D$1009,"Доход",Операции!$H$10:$H$1009,$C$32,Операции!$C$10:$C$1009,">="&$X44,Операции!$C$10:$C$1009,"<="&$B44)+SUMIFS(Журнал!$P$10:$P$1509,Журнал!$D$10:$D$1509,"Доход",Журнал!$J$10:$J$1509,$C$32,Журнал!$C$10:$C$1509,">="&$X44,Журнал!$C$10:$C$1509,"<="&$B44)+SUMIFS(Постоянные!$AC$8:$AC$367,Постоянные!$Z$8:$Z$367,"Доход",Постоянные!$AE$8:$AE$367,$C$32,Постоянные!$Y$8:$Y$367,">="&$X44,Постоянные!$Y$8:$Y$367,"<="&$B44)+SUMIFS(Операции!$Q$10:$Q$1009,Операции!$D$10:$D$1009,"Перевод",Операции!$I$10:$I$1009,$C$32,Операции!$C$10:$C$1009,">="&$X44,Операции!$C$10:$C$1009,"<="&$B44)-SUMIFS(Операции!$Q$10:$Q$1009,Операции!$D$10:$D$1009,"Перевод",Операции!$H$10:$H$1009,$C$32,Операции!$C$10:$C$1009,">="&$X44,Операции!$C$10:$C$1009,"<="&$B44)) | G44: =C44+D44+E44+F44 | H44: =DATE(YEAR(B44),MONTH(B44),MAX(1,MIN(28,N($C$36)))) | I44: =IF($C$33="Да",-MIN(0,G44),0) | X44: =B43+1 | Y44: =IF(AND(H44<=$Y$4,H44>=$C$4),I44,0)
B45: =DATE(Настройки!$C$8,Настройки!$D$9+6,MAX(1,MIN(28,N($C$35)))) | C45: =G44 | D45: =I44 | E45: =IF($C$32="",0,-(SUMIFS(Операции!$Q$10:$Q$1009,Операции!$D$10:$D$1009,"Расход",Операции!$H$10:$H$1009,$C$32,Операции!$C$10:$C$1009,">="&$X45,Операции!$C$10:$C$1009,"<="&$B45)+SUMIFS(Журнал!$P$10:$P$1509,Журнал!$D$10:$D$1509,"<>Доход",Журнал!$J$10:$J$1509,$C$32,Журнал!$C$10:$C$1509,">="&$X45,Журнал!$C$10:$C$1509,"<="&$B45)+SUMIFS(Постоянные!$AC$8:$AC$367,Постоянные!$Z$8:$Z$367,"Расход",Постоянные!$AE$8:$AE$367,$C$32,Постоянные!$Y$8:$Y$367,">="&$X45,Постоянные!$Y$8:$Y$367,"<="&$B45)+SUMIFS(Покупки!$S$7:$S$18,Покупки!$P$7:$P$18,$C$32,Покупки!$G$7:$G$18,">="&$X45,Покупки!$G$7:$G$18,"<="&$B45))) | F45: =IF($C$32="",0,SUMIFS(Операции!$Q$10:$Q$1009,Операции!$D$10:$D$1009,"Доход",Операции!$H$10:$H$1009,$C$32,Операции!$C$10:$C$1009,">="&$X45,Операции!$C$10:$C$1009,"<="&$B45)+SUMIFS(Журнал!$P$10:$P$1509,Журнал!$D$10:$D$1509,"Доход",Журнал!$J$10:$J$1509,$C$32,Журнал!$C$10:$C$1509,">="&$X45,Журнал!$C$10:$C$1509,"<="&$B45)+SUMIFS(Постоянные!$AC$8:$AC$367,Постоянные!$Z$8:$Z$367,"Доход",Постоянные!$AE$8:$AE$367,$C$32,Постоянные!$Y$8:$Y$367,">="&$X45,Постоянные!$Y$8:$Y$367,"<="&$B45)+SUMIFS(Операции!$Q$10:$Q$1009,Операции!$D$10:$D$1009,"Перевод",Операции!$I$10:$I$1009,$C$32,Операции!$C$10:$C$1009,">="&$X45,Операции!$C$10:$C$1009,"<="&$B45)-SUMIFS(Операции!$Q$10:$Q$1009,Операции!$D$10:$D$1009,"Перевод",Операции!$H$10:$H$1009,$C$32,Операции!$C$10:$C$1009,">="&$X45,Операции!$C$10:$C$1009,"<="&$B45)) | G45: =C45+D45+E45+F45 | H45: =DATE(YEAR(B45),MONTH(B45),MAX(1,MIN(28,N($C$36)))) | I45: =IF($C$33="Да",-MIN(0,G45),0) | X45: =B44+1 | Y45: =IF(AND(H45<=$Y$4,H45>=$C$4),I45,0)
B46: =DATE(Настройки!$C$8,Настройки!$D$9+7,MAX(1,MIN(28,N($C$35)))) | C46: =G45 | D46: =I45 | E46: =IF($C$32="",0,-(SUMIFS(Операции!$Q$10:$Q$1009,Операции!$D$10:$D$1009,"Расход",Операции!$H$10:$H$1009,$C$32,Операции!$C$10:$C$1009,">="&$X46,Операции!$C$10:$C$1009,"<="&$B46)+SUMIFS(Журнал!$P$10:$P$1509,Журнал!$D$10:$D$1509,"<>Доход",Журнал!$J$10:$J$1509,$C$32,Журнал!$C$10:$C$1509,">="&$X46,Журнал!$C$10:$C$1509,"<="&$B46)+SUMIFS(Постоянные!$AC$8:$AC$367,Постоянные!$Z$8:$Z$367,"Расход",Постоянные!$AE$8:$AE$367,$C$32,Постоянные!$Y$8:$Y$367,">="&$X46,Постоянные!$Y$8:$Y$367,"<="&$B46)+SUMIFS(Покупки!$S$7:$S$18,Покупки!$P$7:$P$18,$C$32,Покупки!$G$7:$G$18,">="&$X46,Покупки!$G$7:$G$18,"<="&$B46))) | F46: =IF($C$32="",0,SUMIFS(Операции!$Q$10:$Q$1009,Операции!$D$10:$D$1009,"Доход",Операции!$H$10:$H$1009,$C$32,Операции!$C$10:$C$1009,">="&$X46,Операции!$C$10:$C$1009,"<="&$B46)+SUMIFS(Журнал!$P$10:$P$1509,Журнал!$D$10:$D$1509,"Доход",Журнал!$J$10:$J$1509,$C$32,Журнал!$C$10:$C$1509,">="&$X46,Журнал!$C$10:$C$1509,"<="&$B46)+SUMIFS(Постоянные!$AC$8:$AC$367,Постоянные!$Z$8:$Z$367,"Доход",Постоянные!$AE$8:$AE$367,$C$32,Постоянные!$Y$8:$Y$367,">="&$X46,Постоянные!$Y$8:$Y$367,"<="&$B46)+SUMIFS(Операции!$Q$10:$Q$1009,Операции!$D$10:$D$1009,"Перевод",Операции!$I$10:$I$1009,$C$32,Операции!$C$10:$C$1009,">="&$X46,Операции!$C$10:$C$1009,"<="&$B46)-SUMIFS(Операции!$Q$10:$Q$1009,Операции!$D$10:$D$1009,"Перевод",Операции!$H$10:$H$1009,$C$32,Операции!$C$10:$C$1009,">="&$X46,Операции!$C$10:$C$1009,"<="&$B46)) | G46: =C46+D46+E46+F46 | H46: =DATE(YEAR(B46),MONTH(B46),MAX(1,MIN(28,N($C$36)))) | I46: =IF($C$33="Да",-MIN(0,G46),0) | X46: =B45+1 | Y46: =IF(AND(H46<=$Y$4,H46>=$C$4),I46,0)
B47: =DATE(Настройки!$C$8,Настройки!$D$9+8,MAX(1,MIN(28,N($C$35)))) | C47: =G46 | D47: =I46 | E47: =IF($C$32="",0,-(SUMIFS(Операции!$Q$10:$Q$1009,Операции!$D$10:$D$1009,"Расход",Операции!$H$10:$H$1009,$C$32,Операции!$C$10:$C$1009,">="&$X47,Операции!$C$10:$C$1009,"<="&$B47)+SUMIFS(Журнал!$P$10:$P$1509,Журнал!$D$10:$D$1509,"<>Доход",Журнал!$J$10:$J$1509,$C$32,Журнал!$C$10:$C$1509,">="&$X47,Журнал!$C$10:$C$1509,"<="&$B47)+SUMIFS(Постоянные!$AC$8:$AC$367,Постоянные!$Z$8:$Z$367,"Расход",Постоянные!$AE$8:$AE$367,$C$32,Постоянные!$Y$8:$Y$367,">="&$X47,Постоянные!$Y$8:$Y$367,"<="&$B47)+SUMIFS(Покупки!$S$7:$S$18,Покупки!$P$7:$P$18,$C$32,Покупки!$G$7:$G$18,">="&$X47,Покупки!$G$7:$G$18,"<="&$B47))) | F47: =IF($C$32="",0,SUMIFS(Операции!$Q$10:$Q$1009,Операции!$D$10:$D$1009,"Доход",Операции!$H$10:$H$1009,$C$32,Операции!$C$10:$C$1009,">="&$X47,Операции!$C$10:$C$1009,"<="&$B47)+SUMIFS(Журнал!$P$10:$P$1509,Журнал!$D$10:$D$1509,"Доход",Журнал!$J$10:$J$1509,$C$32,Журнал!$C$10:$C$1509,">="&$X47,Журнал!$C$10:$C$1509,"<="&$B47)+SUMIFS(Постоянные!$AC$8:$AC$367,Постоянные!$Z$8:$Z$367,"Доход",Постоянные!$AE$8:$AE$367,$C$32,Постоянные!$Y$8:$Y$367,">="&$X47,Постоянные!$Y$8:$Y$367,"<="&$B47)+SUMIFS(Операции!$Q$10:$Q$1009,Операции!$D$10:$D$1009,"Перевод",Операции!$I$10:$I$1009,$C$32,Операции!$C$10:$C$1009,">="&$X47,Операции!$C$10:$C$1009,"<="&$B47)-SUMIFS(Операции!$Q$10:$Q$1009,Операции!$D$10:$D$1009,"Перевод",Операции!$H$10:$H$1009,$C$32,Операции!$C$10:$C$1009,">="&$X47,Операции!$C$10:$C$1009,"<="&$B47)) | G47: =C47+D47+E47+F47 | H47: =DATE(YEAR(B47),MONTH(B47),MAX(1,MIN(28,N($C$36)))) | I47: =IF($C$33="Да",-MIN(0,G47),0) | X47: =B46+1 | Y47: =IF(AND(H47<=$Y$4,H47>=$C$4),I47,0)
B48: =DATE(Настройки!$C$8,Настройки!$D$9+9,MAX(1,MIN(28,N($C$35)))) | C48: =G47 | D48: =I47 | E48: =IF($C$32="",0,-(SUMIFS(Операции!$Q$10:$Q$1009,Операции!$D$10:$D$1009,"Расход",Операции!$H$10:$H$1009,$C$32,Операции!$C$10:$C$1009,">="&$X48,Операции!$C$10:$C$1009,"<="&$B48)+SUMIFS(Журнал!$P$10:$P$1509,Журнал!$D$10:$D$1509,"<>Доход",Журнал!$J$10:$J$1509,$C$32,Журнал!$C$10:$C$1509,">="&$X48,Журнал!$C$10:$C$1509,"<="&$B48)+SUMIFS(Постоянные!$AC$8:$AC$367,Постоянные!$Z$8:$Z$367,"Расход",Постоянные!$AE$8:$AE$367,$C$32,Постоянные!$Y$8:$Y$367,">="&$X48,Постоянные!$Y$8:$Y$367,"<="&$B48)+SUMIFS(Покупки!$S$7:$S$18,Покупки!$P$7:$P$18,$C$32,Покупки!$G$7:$G$18,">="&$X48,Покупки!$G$7:$G$18,"<="&$B48))) | F48: =IF($C$32="",0,SUMIFS(Операции!$Q$10:$Q$1009,Операции!$D$10:$D$1009,"Доход",Операции!$H$10:$H$1009,$C$32,Операции!$C$10:$C$1009,">="&$X48,Операции!$C$10:$C$1009,"<="&$B48)+SUMIFS(Журнал!$P$10:$P$1509,Журнал!$D$10:$D$1509,"Доход",Журнал!$J$10:$J$1509,$C$32,Журнал!$C$10:$C$1509,">="&$X48,Журнал!$C$10:$C$1509,"<="&$B48)+SUMIFS(Постоянные!$AC$8:$AC$367,Постоянные!$Z$8:$Z$367,"Доход",Постоянные!$AE$8:$AE$367,$C$32,Постоянные!$Y$8:$Y$367,">="&$X48,Постоянные!$Y$8:$Y$367,"<="&$B48)+SUMIFS(Операции!$Q$10:$Q$1009,Операции!$D$10:$D$1009,"Перевод",Операции!$I$10:$I$1009,$C$32,Операции!$C$10:$C$1009,">="&$X48,Операции!$C$10:$C$1009,"<="&$B48)-SUMIFS(Операции!$Q$10:$Q$1009,Операции!$D$10:$D$1009,"Перевод",Операции!$H$10:$H$1009,$C$32,Операции!$C$10:$C$1009,">="&$X48,Операции!$C$10:$C$1009,"<="&$B48)) | G48: =C48+D48+E48+F48 | H48: =DATE(YEAR(B48),MONTH(B48),MAX(1,MIN(28,N($C$36)))) | I48: =IF($C$33="Да",-MIN(0,G48),0) | X48: =B47+1 | Y48: =IF(AND(H48<=$Y$4,H48>=$C$4),I48,0)
B49: =DATE(Настройки!$C$8,Настройки!$D$9+10,MAX(1,MIN(28,N($C$35)))) | C49: =G48 | D49: =I48 | E49: =IF($C$32="",0,-(SUMIFS(Операции!$Q$10:$Q$1009,Операции!$D$10:$D$1009,"Расход",Операции!$H$10:$H$1009,$C$32,Операции!$C$10:$C$1009,">="&$X49,Операции!$C$10:$C$1009,"<="&$B49)+SUMIFS(Журнал!$P$10:$P$1509,Журнал!$D$10:$D$1509,"<>Доход",Журнал!$J$10:$J$1509,$C$32,Журнал!$C$10:$C$1509,">="&$X49,Журнал!$C$10:$C$1509,"<="&$B49)+SUMIFS(Постоянные!$AC$8:$AC$367,Постоянные!$Z$8:$Z$367,"Расход",Постоянные!$AE$8:$AE$367,$C$32,Постоянные!$Y$8:$Y$367,">="&$X49,Постоянные!$Y$8:$Y$367,"<="&$B49)+SUMIFS(Покупки!$S$7:$S$18,Покупки!$P$7:$P$18,$C$32,Покупки!$G$7:$G$18,">="&$X49,Покупки!$G$7:$G$18,"<="&$B49))) | F49: =IF($C$32="",0,SUMIFS(Операции!$Q$10:$Q$1009,Операции!$D$10:$D$1009,"Доход",Операции!$H$10:$H$1009,$C$32,Операции!$C$10:$C$1009,">="&$X49,Операции!$C$10:$C$1009,"<="&$B49)+SUMIFS(Журнал!$P$10:$P$1509,Журнал!$D$10:$D$1509,"Доход",Журнал!$J$10:$J$1509,$C$32,Журнал!$C$10:$C$1509,">="&$X49,Журнал!$C$10:$C$1509,"<="&$B49)+SUMIFS(Постоянные!$AC$8:$AC$367,Постоянные!$Z$8:$Z$367,"Доход",Постоянные!$AE$8:$AE$367,$C$32,Постоянные!$Y$8:$Y$367,">="&$X49,Постоянные!$Y$8:$Y$367,"<="&$B49)+SUMIFS(Операции!$Q$10:$Q$1009,Операции!$D$10:$D$1009,"Перевод",Операции!$I$10:$I$1009,$C$32,Операции!$C$10:$C$1009,">="&$X49,Операции!$C$10:$C$1009,"<="&$B49)-SUMIFS(Операции!$Q$10:$Q$1009,Операции!$D$10:$D$1009,"Перевод",Операции!$H$10:$H$1009,$C$32,Операции!$C$10:$C$1009,">="&$X49,Операции!$C$10:$C$1009,"<="&$B49)) | G49: =C49+D49+E49+F49 | H49: =DATE(YEAR(B49),MONTH(B49),MAX(1,MIN(28,N($C$36)))) | I49: =IF($C$33="Да",-MIN(0,G49),0) | X49: =B48+1 | Y49: =IF(AND(H49<=$Y$4,H49>=$C$4),I49,0)
B50: =DATE(Настройки!$C$8,Настройки!$D$9+11,MAX(1,MIN(28,N($C$35)))) | C50: =G49 | D50: =I49 | E50: =IF($C$32="",0,-(SUMIFS(Операции!$Q$10:$Q$1009,Операции!$D$10:$D$1009,"Расход",Операции!$H$10:$H$1009,$C$32,Операции!$C$10:$C$1009,">="&$X50,Операции!$C$10:$C$1009,"<="&$B50)+SUMIFS(Журнал!$P$10:$P$1509,Журнал!$D$10:$D$1509,"<>Доход",Журнал!$J$10:$J$1509,$C$32,Журнал!$C$10:$C$1509,">="&$X50,Журнал!$C$10:$C$1509,"<="&$B50)+SUMIFS(Постоянные!$AC$8:$AC$367,Постоянные!$Z$8:$Z$367,"Расход",Постоянные!$AE$8:$AE$367,$C$32,Постоянные!$Y$8:$Y$367,">="&$X50,Постоянные!$Y$8:$Y$367,"<="&$B50)+SUMIFS(Покупки!$S$7:$S$18,Покупки!$P$7:$P$18,$C$32,Покупки!$G$7:$G$18,">="&$X50,Покупки!$G$7:$G$18,"<="&$B50))) | F50: =IF($C$32="",0,SUMIFS(Операции!$Q$10:$Q$1009,Операции!$D$10:$D$1009,"Доход",Операции!$H$10:$H$1009,$C$32,Операции!$C$10:$C$1009,">="&$X50,Операции!$C$10:$C$1009,"<="&$B50)+SUMIFS(Журнал!$P$10:$P$1509,Журнал!$D$10:$D$1509,"Доход",Журнал!$J$10:$J$1509,$C$32,Журнал!$C$10:$C$1509,">="&$X50,Журнал!$C$10:$C$1509,"<="&$B50)+SUMIFS(Постоянные!$AC$8:$AC$367,Постоянные!$Z$8:$Z$367,"Доход",Постоянные!$AE$8:$AE$367,$C$32,Постоянные!$Y$8:$Y$367,">="&$X50,Постоянные!$Y$8:$Y$367,"<="&$B50)+SUMIFS(Операции!$Q$10:$Q$1009,Операции!$D$10:$D$1009,"Перевод",Операции!$I$10:$I$1009,$C$32,Операции!$C$10:$C$1009,">="&$X50,Операции!$C$10:$C$1009,"<="&$B50)-SUMIFS(Операции!$Q$10:$Q$1009,Операции!$D$10:$D$1009,"Перевод",Операции!$H$10:$H$1009,$C$32,Операции!$C$10:$C$1009,">="&$X50,Операции!$C$10:$C$1009,"<="&$B50)) | G50: =C50+D50+E50+F50 | H50: =DATE(YEAR(B50),MONTH(B50),MAX(1,MIN(28,N($C$36)))) | I50: =IF($C$33="Да",-MIN(0,G50),0) | X50: =B49+1 | Y50: =IF(AND(H50<=$Y$4,H50>=$C$4),I50,0)
B51: Покупки с 5-го по 4-е число попадают в выписку на 4-е; её долг переносится и списывается в указанное число со счёта погашения. При автоматическом погашении списание вручную не вносите — оно посчитается дважды.

Sheet Журнал
B2: Журнал
B3: Запланированные траты и поступления. Заплатила — «Оплачено» и счёт; ежедневные траты — в «Операциях»
B5: Сводка: | C5: К оплате (запланировано) | E5: Потрачено (факт) | F5: Получено (факт) | G5: Просрочено | I5: Ближайший платёж | K5: …на сумму | M5: Возможных дублей
C6: =SUMIFS($Q$10:$Q$1509,$D$10:$D$1509,"<>Доход",$I$10:$I$1509,"<>Оплачено",$I$10:$I$1509,"<>Отменено",$H$10:$H$1509,"") | E6: =SUMIFS($P$10:$P$1509,$D$10:$D$1509,"<>Доход") | F6: =SUMIFS($P$10:$P$1509,$D$10:$D$1509,"Доход") | G6: =SUMIFS($Q$10:$Q$1509,$C$10:$C$1509,"<"&TODAY(),$C$10:$C$1509,">0",$D$10:$D$1509,"<>Доход",$I$10:$I$1509,"<>Оплачено",$I$10:$I$1509,"<>Отменено",$H$10:$H$1509,"") | I6: =IF(COUNT($T$10:$T$1509)=0,"—",MIN($T$10:$T$1509)) | K6: =IF(COUNT($T$10:$T$1509)=0,0,SUMIFS($Q$10:$Q$1509,$T$10:$T$1509,MIN($T$10:$T$1509))) | M6: =COUNTIF($N$10:$N$1509,"?*")
B9: № | C9: Дата | D9: Тип | E9: Категория | F9: Что | G9: Сумма план | H9: Сумма факт | I9: Статус | J9: Счёт | K9: Приоритет | L9: Дней до | M9: Месяц учёта | N9: Возможный дубль
B10: =IF(AND($C10="",$F10=""),"",ROW()-9) | C10: 46300 | D10: Расход | E10: Продукты | F10: Еда | G10: 100 | J10: Карта | L10: =IF(OR($C10="",$I10="Оплачено",$I10="Отменено",$H10<>""),"",$C10-TODAY()) | M10: =IF($C10="","",INDEX(Настройки!$V$6:$V$17,MONTH($C10))&" "&YEAR($C10)) | N10: =IF($F10="","",IF(COUNTIF(Постоянные!$C$8:$C$37,$F10)>0,"есть в Постоянных",IF(COUNTIF(Покупки!$C$7:$C$18,$F10)>0,"есть в Покупках",""))) | P10: =IF($H10<>"",$H10,IF($I10="Оплачено",N($G10),0)) | Q10: =IF($I10="Отменено",0,IF($G10<>"",$G10,N($H10))) | R10: =IF($C10="","",IFERROR(DATE(Настройки!$C$8,Настройки!$D$9+MATCH($M10,Настройки!$X$6:$X$17,0)-1,1),DATE(YEAR($C10),MONTH($C10),1))) | S10: =IF(OR($I10="Оплачено",$H10<>""),$P10,$Q10) | T10: =IF(OR($C10="",$D10="Доход",$I10="Оплачено",$I10="Отменено",$H10<>"",$C10<TODAY()),"",$C10) | U10: =IF(AND($D10<>"Доход",COUNTIFS(Счета!$B$10:$B$21,$J10,Счета!$C$10:$C$21,"Кредитная")>0),1,0)
B11: =IF(AND($C11="",$F11=""),"",ROW()-9) | C11: 46301 | D11: Расход | E11: Продукты | F11: Кафе | G11: 100 | I11: Оплачено | J11: Карта | L11: =IF(OR($C11="",$I11="Оплачено",$I11="Отменено",$H11<>""),"",$C11-TODAY()) | M11: =IF($C11="","",INDEX(Настройки!$V$6:$V$17,MONTH($C11))&" "&YEAR($C11)) | N11: =IF($F11="","",IF(COUNTIF(Постоянные!$C$8:$C$37,$F11)>0,"есть в Постоянных",IF(COUNTIF(Покупки!$C$7:$C$18,$F11)>0,"есть в Покупках",""))) | P11: =IF($H11<>"",$H11,IF($I11="Оплачено",N($G11),0)) | Q11: =IF($I11="Отменено",0,IF($G11<>"",$G11,N($H11))) | R11: =IF($C11="","",IFERROR(DATE(Настройки!$C$8,Настройки!$D$9+MATCH($M11,Настройки!$X$6:$X$17,0)-1,1),DATE(YEAR($C11),MONTH($C11),1))) | S11: =IF(OR($I11="Оплачено",$H11<>""),$P11,$Q11) | T11: =IF(OR($C11="",$D11="Доход",$I11="Оплачено",$I11="Отменено",$H11<>"",$C11<TODAY()),"",$C11) | U11: =IF(AND($D11<>"Доход",COUNTIFS(Счета!$B$10:$B$21,$J11,Счета!$C$10:$C$21,"Кредитная")>0),1,0)
B12: =IF(AND($C12="",$F12=""),"",ROW()-9) | C12: 46302 | D12: Расход | E12: Транспорт | F12: Такси | G12: 100 | H12: 90 | I12: Оплачено | J12: Карта | L12: =IF(OR($C12="",$I12="Оплачено",$I12="Отменено",$H12<>""),"",$C12-TODAY()) | M12: =IF($C12="","",INDEX(Настройки!$V$6:$V$17,MONTH($C12))&" "&YEAR($C12)) | N12: =IF($F12="","",IF(COUNTIF(Постоянные!$C$8:$C$37,$F12)>0,"есть в Постоянных",IF(COUNTIF(Покупки!$C$7:$C$18,$F12)>0,"есть в Покупках",""))) | P12: =IF($H12<>"",$H12,IF($I12="Оплачено",N($G12),0)) | Q12: =IF($I12="Отменено",0,IF($G12<>"",$G12,N($H12))) | R12: =IF($C12="","",IFERROR(DATE(Настройки!$C$8,Настройки!$D$9+MATCH($M12,Настройки!$X$6:$X$17,0)-1,1),DATE(YEAR($C12),MONTH($C12),1))) | S12: =IF(OR($I12="Оплачено",$H12<>""),$P12,$Q12) | T12: =IF(OR($C12="",$D12="Доход",$I12="Оплачено",$I12="Отменено",$H12<>"",$C12<TODAY()),"",$C12) | U12: =IF(AND($D12<>"Доход",COUNTIFS(Счета!$B$10:$B$21,$J12,Счета!$C$10:$C$21,"Кредитная")>0),1,0)
B13: =IF(AND($C13="",$F13=""),"",ROW()-9) | C13: 46303 | D13: Расход | E13: Транспорт | F13: Отмена | G13: 100 | I13: Отменено | J13: Карта | L13: =IF(OR($C13="",$I13="Оплачено",$I13="Отменено",$H13<>""),"",$C13-TODAY()) | M13: =IF($C13="","",INDEX(Настройки!$V$6:$V$17,MONTH($C13))&" "&YEAR($C13)) | N13: =IF($F13="","",IF(COUNTIF(Постоянные!$C$8:$C$37,$F13)>0,"есть в Постоянных",IF(COUNTIF(Покупки!$C$7:$C$18,$F13)>0,"есть в Покупках",""))) | P13: =IF($H13<>"",$H13,IF($I13="Оплачено",N($G13),0)) | Q13: =IF($I13="Отменено",0,IF($G13<>"",$G13,N($H13))) | R13: =IF($C13="","",IFERROR(DATE(Настройки!$C$8,Настройки!$D$9+MATCH($M13,Настройки!$X$6:$X$17,0)-1,1),DATE(YEAR($C13),MONTH($C13),1))) | S13: =IF(OR($I13="Оплачено",$H13<>""),$P13,$Q13) | T13: =IF(OR($C13="",$D13="Доход",$I13="Оплачено",$I13="Отменено",$H13<>"",$C13<TODAY()),"",$C13) | U13: =IF(AND($D13<>"Доход",COUNTIFS(Счета!$B$10:$B$21,$J13,Счета!$C$10:$C$21,"Кредитная")>0),1,0)
B14: =IF(AND($C14="",$F14=""),"",ROW()-9) | C14: 46304 | D14: Расход | E14: Транспорт | F14: Штраф | G14: 100 | H14: 15 | I14: Отменено | J14: Карта | L14: =IF(OR($C14="",$I14="Оплачено",$I14="Отменено",$H14<>""),"",$C14-TODAY()) | M14: =IF($C14="","",INDEX(Настройки!$V$6:$V$17,MONTH($C14))&" "&YEAR($C14)) | N14: =IF($F14="","",IF(COUNTIF(Постоянные!$C$8:$C$37,$F14)>0,"есть в Постоянных",IF(COUNTIF(Покупки!$C$7:$C$18,$F14)>0,"есть в Покупках",""))) | P14: =IF($H14<>"",$H14,IF($I14="Оплачено",N($G14),0)) | Q14: =IF($I14="Отменено",0,IF($G14<>"",$G14,N($H14))) | R14: =IF($C14="","",IFERROR(DATE(Настройки!$C$8,Настройки!$D$9+MATCH($M14,Настройки!$X$6:$X$17,0)-1,1),DATE(YEAR($C14),MONTH($C14),1))) | S14: =IF(OR($I14="Оплачено",$H14<>""),$P14,$Q14) | T14: =IF(OR($C14="",$D14="Доход",$I14="Оплачено",$I14="Отменено",$H14<>"",$C14<TODAY()),"",$C14) | U14: =IF(AND($D14<>"Доход",COUNTIFS(Счета!$B$10:$B$21,$J14,Счета!$C$10:$C$21,"Кредитная")>0),1,0)
B15: =IF(AND($C15="",$F15=""),"",ROW()-9) | C15: 46305 | D15: Расход | E15: Продукты | F15: Возврат | H15: -20 | I15: Оплачено | J15: Карта | L15: =IF(OR($C15="",$I15="Оплачено",$I15="Отменено",$H15<>""),"",$C15-TODAY()) | M15: =IF($C15="","",INDEX(Настройки!$V$6:$V$17,MONTH($C15))&" "&YEAR($C15)) | N15: =IF($F15="","",IF(COUNTIF(Постоянные!$C$8:$C$37,$F15)>0,"есть в Постоянных",IF(COUNTIF(Покупки!$C$7:$C$18,$F15)>0,"есть в Покупках",""))) | P15: =IF($H15<>"",$H15,IF($I15="Оплачено",N($G15),0)) | Q15: =IF($I15="Отменено",0,IF($G15<>"",$G15,N($H15))) | R15: =IF($C15="","",IFERROR(DATE(Настройки!$C$8,Настройки!$D$9+MATCH($M15,Настройки!$X$6:$X$17,0)-1,1),DATE(YEAR($C15),MONTH($C15),1))) | S15: =IF(OR($I15="Оплачено",$H15<>""),$P15,$Q15) | T15: =IF(OR($C15="",$D15="Доход",$I15="Оплачено",$I15="Отменено",$H15<>"",$C15<TODAY()),"",$C15) | U15: =IF(AND($D15<>"Доход",COUNTIFS(Счета!$B$10:$B$21,$J15,Счета!$C$10:$C$21,"Кредитная")>0),1,0)
B16: =IF(AND($C16="",$F16=""),"",ROW()-9) | C16: 46296 | D16: Доход | E16: Зарплата | F16: ЗП | G16: 3000 | I16: Оплачено | J16: Карта | L16: =IF(OR($C16="",$I16="Оплачено",$I16="Отменено",$H16<>""),"",$C16-TODAY()) | M16: =IF($C16="","",INDEX(Настройки!$V$6:$V$17,MONTH($C16))&" "&YEAR($C16)) | N16: =IF($F16="","",IF(COUNTIF(Постоянные!$C$8:$C$37,$F16)>0,"есть в Постоянных",IF(COUNTIF(Покупки!$C$7:$C$18,$F16)>0,"есть в Покупках",""))) | P16: =IF($H16<>"",$H16,IF($I16="Оплачено",N($G16),0)) | Q16: =IF($I16="Отменено",0,IF($G16<>"",$G16,N($H16))) | R16: =IF($C16="","",IFERROR(DATE(Настройки!$C$8,Настройки!$D$9+MATCH($M16,Настройки!$X$6:$X$17,0)-1,1),DATE(YEAR($C16),MONTH($C16),1))) | S16: =IF(OR($I16="Оплачено",$H16<>""),$P16,$Q16) | T16: =IF(OR($C16="",$D16="Доход",$I16="Оплачено",$I16="Отменено",$H16<>"",$C16<TODAY()),"",$C16) | U16: =IF(AND($D16<>"Доход",COUNTIFS(Счета!$B$10:$B$21,$J16,Счета!$C$10:$C$21,"Кредитная")>0),1,0)
B17: =IF(AND($C17="",$F17=""),"",ROW()-9) | C17: 46341 | D17: Расход | E17: Продукты | F17: Ноябрь | G17: 50 | H17: 50 | I17: Оплачено | J17: Карта | L17: =IF(OR($C17="",$I17="Оплачено",$I17="Отменено",$H17<>""),"",$C17-TODAY()) | M17: =IF($C17="","",INDEX(Настройки!$V$6:$V$17,MONTH($C17))&" "&YEAR($C17)) | N17: =IF($F17="","",IF(COUNTIF(Постоянные!$C$8:$C$37,$F17)>0,"есть в Постоянных",IF(COUNTIF(Покупки!$C$7:$C$18,$F17)>0,"есть в Покупках",""))) | P17: =IF($H17<>"",$H17,IF($I17="Оплачено",N($G17),0)) | Q17: =IF($I17="Отменено",0,IF($G17<>"",$G17,N($H17))) | R17: =IF($C17="","",IFERROR(DATE(Настройки!$C$8,Настройки!$D$9+MATCH($M17,Настройки!$X$6:$X$17,0)-1,1),DATE(YEAR($C17),MONTH($C17),1))) | S17: =IF(OR($I17="Оплачено",$H17<>""),$P17,$Q17) | T17: =IF(OR($C17="",$D17="Доход",$I17="Оплачено",$I17="Отменено",$H17<>"",$C17<TODAY()),"",$C17) | U17: =IF(AND($D17<>"Доход",COUNTIFS(Счета!$B$10:$B$21,$J17,Счета!$C$10:$C$21,"Кредитная")>0),1,0)
B18: =IF(AND($C18="",$F18=""),"",ROW()-9) | C18: 46315 | D18: Расход | E18: Жильё | F18: Аренда | J18: Карта | L18: =IF(OR($C18="",$I18="Оплачено",$I18="Отменено",$H18<>""),"",$C18-TODAY()) | M18: =IF($C18="","",INDEX(Настройки!$V$6:$V$17,MONTH($C18))&" "&YEAR($C18)) | N18: =IF($F18="","",IF(COUNTIF(Постоянные!$C$8:$C$37,$F18)>0,"есть в Постоянных",IF(COUNTIF(Покупки!$C$7:$C$18,$F18)>0,"есть в Покупках",""))) | P18: =IF($H18<>"",$H18,IF($I18="Оплачено",N($G18),0)) | Q18: =IF($I18="Отменено",0,IF($G18<>"",$G18,N($H18))) | R18: =IF($C18="","",IFERROR(DATE(Настройки!$C$8,Настройки!$D$9+MATCH($M18,Настройки!$X$6:$X$17,0)-1,1),DATE(YEAR($C18),MONTH($C18),1))) | S18: =IF(OR($I18="Оплачено",$H18<>""),$P18,$Q18) | T18: =IF(OR($C18="",$D18="Доход",$I18="Оплачено",$I18="Отменено",$H18<>"",$C18<TODAY()),"",$C18) | U18: =IF(AND($D18<>"Доход",COUNTIFS(Счета!$B$10:$B$21,$J18,Счета!$C$10:$C$21,"Кредитная")>0),1,0)
B19: =IF(AND($C19="",$F19=""),"",ROW()-9) | C19: 46270 | D19: Расход | E19: Продукты | F19: Сентябрь | G19: 10 | J19: Карта | L19: =IF(OR($C19="",$I19="Оплачено",$I19="Отменено",$H19<>""),"",$C19-TODAY()) | M19: =IF($C19="","",INDEX(Настройки!$V$6:$V$17,MONTH($C19))&" "&YEAR($C19)) | N19: =IF($F19="","",IF(COUNTIF(Постоянные!$C$8:$C$37,$F19)>0,"есть в Постоянных",IF(COUNTIF(Покупки!$C$7:$C$18,$F19)>0,"есть в Покупках",""))) | P19: =IF($H19<>"",$H19,IF($I19="Оплачено",N($G19),0)) | Q19: =IF($I19="Отменено",0,IF($G19<>"",$G19,N($H19))) | R19: =IF($C19="","",IFERROR(DATE(Настройки!$C$8,Настройки!$D$9+MATCH($M19,Настройки!$X$6:$X$17,0)-1,1),DATE(YEAR($C19),MONTH($C19),1))) | S19: =IF(OR($I19="Оплачено",$H19<>""),$P19,$Q19) | T19: =IF(OR($C19="",$D19="Доход",$I19="Оплачено",$I19="Отменено",$H19<>"",$C19<TODAY()),"",$C19) | U19: =IF(AND($D19<>"Доход",COUNTIFS(Счета!$B$10:$B$21,$J19,Счета!$C$10:$C$21,"Кредитная")>0),1,0)
B20: =IF(AND($C20="",$F20=""),"",ROW()-9) | L20: =IF(OR($C20="",$I20="Оплачено",$I20="Отменено",$H20<>""),"",$C20-TODAY()) | M20: =IF($C20="","",INDEX(Настройки!$V$6:$V$17,MONTH($C20))&" "&YEAR($C20)) | N20: =IF($F20="","",IF(COUNTIF(Постоянные!$C$8:$C$37,$F20)>0,"есть в Постоянных",IF(COUNTIF(Покупки!$C$7:$C$18,$F20)>0,"есть в Покупках",""))) | P20: =IF($H20<>"",$H20,IF($I20="Оплачено",N($G20),0)) | Q20: =IF($I20="Отменено",0,IF($G20<>"",$G20,N($H20))) | R20: =IF($C20="","",IFERROR(DATE(Настройки!$C$8,Настройки!$D$9+MATCH($M20,Настройки!$X$6:$X$17,0)-1,1),DATE(YEAR($C20),MONTH($C20),1))) | S20: =IF(OR($I20="Оплачено",$H20<>""),$P20,$Q20) | T20: =IF(OR($C20="",$D20="Доход",$I20="Оплачено",$I20="Отменено",$H20<>"",$C20<TODAY()),"",$C20) | U20: =IF(AND($D20<>"Доход",COUNTIFS(Счета!$B$10:$B$21,$J20,Счета!$C$10:$C$21,"Кредитная")>0),1,0)
B21: =IF(AND($C21="",$F21=""),"",ROW()-9) | L21: =IF(OR($C21="",$I21="Оплачено",$I21="Отменено",$H21<>""),"",$C21-TODAY()) | M21: =IF($C21="","",INDEX(Настройки!$V$6:$V$17,MONTH($C21))&" "&YEAR($C21)) | N21: =IF($F21="","",IF(COUNTIF(Постоянные!$C$8:$C$37,$F21)>0,"есть в Постоянных",IF(COUNTIF(Покупки!$C$7:$C$18,$F21)>0,"есть в Покупках",""))) | P21: =IF($H21<>"",$H21,IF($I21="Оплачено",N($G21),0)) | Q21: =IF($I21="Отменено",0,IF($G21<>"",$G21,N($H21))) | R21: =IF($C21="","",IFERROR(DATE(Настройки!$C$8,Настройки!$D$9+MATCH($M21,Настройки!$X$6:$X$17,0)-1,1),DATE(YEAR($C21),MONTH($C21),1))) | S21: =IF(OR($I21="Оплачено",$H21<>""),$P21,$Q21) | T21: =IF(OR($C21="",$D21="Доход",$I21="Оплачено",$I21="Отменено",$H21<>"",$C21<TODAY()),"",$C21) | U21: =IF(AND($D21<>"Доход",COUNTIFS(Счета!$B$10:$B$21,$J21,Счета!$C$10:$C$21,"Кредитная")>0),1,0)
B22: =IF(AND($C22="",$F22=""),"",ROW()-9) | L22: =IF(OR($C22="",$I22="Оплачено",$I22="Отменено",$H22<>""),"",$C22-TODAY()) | M22: =IF($C22="","",INDEX(Настройки!$V$6:$V$17,MONTH($C22))&" "&YEAR($C22)) | N22: =IF($F22="","",IF(COUNTIF(Постоянные!$C$8:$C$37,$F22)>0,"есть в Постоянных",IF(COUNTIF(Покупки!$C$7:$C$18,$F22)>0,"есть в Покупках",""))) | P22: =IF($H22<>"",$H22,IF($I22="Оплачено",N($G22),0)) | Q22: =IF($I22="Отменено",0,IF($G22<>"",$G22,N($H22))) | R22: =IF($C22="","",IFERROR(DATE(Настройки!$C$8,Настройки!$D$9+MATCH($M22,Настройки!$X$6:$X$17,0)-1,1),DATE(YEAR($C22),MONTH($C22),1))) | S22: =IF(OR($I22="Оплачено",$H22<>""),$P22,$Q22) | T22: =IF(OR($C22="",$D22="Доход",$I22="Оплачено",$I22="Отменено",$H22<>"",$C22<TODAY()),"",$C22) | U22: =IF(AND($D22<>"Доход",COUNTIFS(Счета!$B$10:$B$21,$J22,Счета!$C$10:$C$21,"Кредитная")>0),1,0)
B23: =IF(AND($C23="",$F23=""),"",ROW()-9) | L23: =IF(OR($C23="",$I23="Оплачено",$I23="Отменено",$H23<>""),"",$C23-TODAY()) | M23: =IF($C23="","",INDEX(Настройки!$V$6:$V$17,MONTH($C23))&" "&YEAR($C23)) | N23: =IF($F23="","",IF(COUNTIF(Постоянные!$C$8:$C$37,$F23)>0,"есть в Постоянных",IF(COUNTIF(Покупки!$C$7:$C$18,$F23)>0,"есть в Покупках",""))) | P23: =IF($H23<>"",$H23,IF($I23="Оплачено",N($G23),0)) | Q23: =IF($I23="Отменено",0,IF($G23<>"",$G23,N($H23))) | R23: =IF($C23="","",IFERROR(DATE(Настройки!$C$8,Настройки!$D$9+MATCH($M23,Настройки!$X$6:$X$17,0)-1,1),DATE(YEAR($C23),MONTH($C23),1))) | S23: =IF(OR($I23="Оплачено",$H23<>""),$P23,$Q23) | T23: =IF(OR($C23="",$D23="Доход",$I23="Оплачено",$I23="Отменено",$H23<>"",$C23<TODAY()),"",$C23) | U23: =IF(AND($D23<>"Доход",COUNTIFS(Счета!$B$10:$B$21,$J23,Счета!$C$10:$C$21,"Кредитная")>0),1,0)
B24: =IF(AND($C24="",$F24=""),"",ROW()-9) | L24: =IF(OR($C24="",$I24="Оплачено",$I24="Отменено",$H24<>""),"",$C24-TODAY()) | M24: =IF($C24="","",INDEX(Настройки!$V$6:$V$17,MONTH($C24))&" "&YEAR($C24)) | N24: =IF($F24="","",IF(COUNTIF(Постоянные!$C$8:$C$37,$F24)>0,"есть в Постоянных",IF(COUNTIF(Покупки!$C$7:$C$18,$F24)>0,"есть в Покупках",""))) | P24: =IF($H24<>"",$H24,IF($I24="Оплачено",N($G24),0)) | Q24: =IF($I24="Отменено",0,IF($G24<>"",$G24,N($H24))) | R24: =IF($C24="","",IFERROR(DATE(Настройки!$C$8,Настройки!$D$9+MATCH($M24,Настройки!$X$6:$X$17,0)-1,1),DATE(YEAR($C24),MONTH($C24),1))) | S24: =IF(OR($I24="Оплачено",$H24<>""),$P24,$Q24) | T24: =IF(OR($C24="",$D24="Доход",$I24="Оплачено",$I24="Отменено",$H24<>"",$C24<TODAY()),"",$C24) | U24: =IF(AND($D24<>"Доход",COUNTIFS(Счета!$B$10:$B$21,$J24,Счета!$C$10:$C$21,"Кредитная")>0),1,0)
B25: =IF(AND($C25="",$F25=""),"",ROW()-9) | L25: =IF(OR($C25="",$I25="Оплачено",$I25="Отменено",$H25<>""),"",$C25-TODAY()) | M25: =IF($C25="","",INDEX(Настройки!$V$6:$V$17,MONTH($C25))&" "&YEAR($C25)) | N25: =IF($F25="","",IF(COUNTIF(Постоянные!$C$8:$C$37,$F25)>0,"есть в Постоянных",IF(COUNTIF(Покупки!$C$7:$C$18,$F25)>0,"есть в Покупках",""))) | P25: =IF($H25<>"",$H25,IF($I25="Оплачено",N($G25),0)) | Q25: =IF($I25="Отменено",0,IF($G25<>"",$G25,N($H25))) | R25: =IF($C25="","",IFERROR(DATE(Настройки!$C$8,Настройки!$D$9+MATCH($M25,Настройки!$X$6:$X$17,0)-1,1),DATE(YEAR($C25),MONTH($C25),1))) | S25: =IF(OR($I25="Оплачено",$H25<>""),$P25,$Q25) | T25: =IF(OR($C25="",$D25="Доход",$I25="Оплачено",$I25="Отменено",$H25<>"",$C25<TODAY()),"",$C25) | U25: =IF(AND($D25<>"Доход",COUNTIFS(Счета!$B$10:$B$21,$J25,Счета!$C$10:$C$21,"Кредитная")>0),1,0)
B26: =IF(AND($C26="",$F26=""),"",ROW()-9) | L26: =IF(OR($C26="",$I26="Оплачено",$I26="Отменено",$H26<>""),"",$C26-TODAY()) | M26: =IF($C26="","",INDEX(Настройки!$V$6:$V$17,MONTH($C26))&" "&YEAR($C26)) | N26: =IF($F26="","",IF(COUNTIF(Постоянные!$C$8:$C$37,$F26)>0,"есть в Постоянных",IF(COUNTIF(Покупки!$C$7:$C$18,$F26)>0,"есть в Покупках",""))) | P26: =IF($H26<>"",$H26,IF($I26="Оплачено",N($G26),0)) | Q26: =IF($I26="Отменено",0,IF($G26<>"",$G26,N($H26))) | R26: =IF($C26="","",IFERROR(DATE(Настройки!$C$8,Настройки!$D$9+MATCH($M26,Настройки!$X$6:$X$17,0)-1,1),DATE(YEAR($C26),MONTH($C26),1))) | S26: =IF(OR($I26="Оплачено",$H26<>""),$P26,$Q26) | T26: =IF(OR($C26="",$D26="Доход",$I26="Оплачено",$I26="Отменено",$H26<>"",$C26<TODAY()),"",$C26) | U26: =IF(AND($D26<>"Доход",COUNTIFS(Счета!$B$10:$B$21,$J26,Счета!$C$10:$C$21,"Кредитная")>0),1,0)
B27: =IF(AND($C27="",$F27=""),"",ROW()-9) | L27: =IF(OR($C27="",$I27="Оплачено",$I27="Отменено",$H27<>""),"",$C27-TODAY()) | M27: =IF($C27="","",INDEX(Настройки!$V$6:$V$17,MONTH($C27))&" "&YEAR($C27)) | N27: =IF($F27="","",IF(COUNTIF(Постоянные!$C$8:$C$37,$F27)>0,"есть в Постоянных",IF(COUNTIF(Покупки!$C$7:$C$18,$F27)>0,"есть в Покупках",""))) | P27: =IF($H27<>"",$H27,IF($I27="Оплачено",N($G27),0)) | Q27: =IF($I27="Отменено",0,IF($G27<>"",$G27,N($H27))) | R27: =IF($C27="","",IFERROR(DATE(Настройки!$C$8,Настройки!$D$9+MATCH($M27,Настройки!$X$6:$X$17,0)-1,1),DATE(YEAR($C27),MONTH($C27),1))) | S27: =IF(OR($I27="Оплачено",$H27<>""),$P27,$Q27) | T27: =IF(OR($C27="",$D27="Доход",$I27="Оплачено",$I27="Отменено",$H27<>"",$C27<TODAY()),"",$C27) | U27: =IF(AND($D27<>"Доход",COUNTIFS(Счета!$B$10:$B$21,$J27,Счета!$C$10:$C$21,"Кредитная")>0),1,0)
B28: =IF(AND($C28="",$F28=""),"",ROW()-9) | L28: =IF(OR($C28="",$I28="Оплачено",$I28="Отменено",$H28<>""),"",$C28-TODAY()) | M28: =IF($C28="","",INDEX(Настройки!$V$6:$V$17,MONTH($C28))&" "&YEAR($C28)) | N28: =IF($F28="","",IF(COUNTIF(Постоянные!$C$8:$C$37,$F28)>0,"есть в Постоянных",IF(COUNTIF(Покупки!$C$7:$C$18,$F28)>0,"есть в Покупках",""))) | P28: =IF($H28<>"",$H28,IF($I28="Оплачено",N($G28),0)) | Q28: =IF($I28="Отменено",0,IF($G28<>"",$G28,N($H28))) | R28: =IF($C28="","",IFERROR(DATE(Настройки!$C$8,Настройки!$D$9+MATCH($M28,Настройки!$X$6:$X$17,0)-1,1),DATE(YEAR($C28),MONTH($C28),1))) | S28: =IF(OR($I28="Оплачено",$H28<>""),$P28,$Q28) | T28: =IF(OR($C28="",$D28="Доход",$I28="Оплачено",$I28="Отменено",$H28<>"",$C28<TODAY()),"",$C28) | U28: =IF(AND($D28<>"Доход",COUNTIFS(Счета!$B$10:$B$21,$J28,Счета!$C$10:$C$21,"Кредитная")>0),1,0)
B29: =IF(AND($C29="",$F29=""),"",ROW()-9) | L29: =IF(OR($C29="",$I29="Оплачено",$I29="Отменено",$H29<>""),"",$C29-TODAY()) | M29: =IF($C29="","",INDEX(Настройки!$V$6:$V$17,MONTH($C29))&" "&YEAR($C29)) | N29: =IF($F29="","",IF(COUNTIF(Постоянные!$C$8:$C$37,$F29)>0,"есть в Постоянных",IF(COUNTIF(Покупки!$C$7:$C$18,$F29)>0,"есть в Покупках",""))) | P29: =IF($H29<>"",$H29,IF($I29="Оплачено",N($G29),0)) | Q29: =IF($I29="Отменено",0,IF($G29<>"",$G29,N($H29))) | R29: =IF($C29="","",IFERROR(DATE(Настройки!$C$8,Настройки!$D$9+MATCH($M29,Настройки!$X$6:$X$17,0)-1,1),DATE(YEAR($C29),MONTH($C29),1))) | S29: =IF(OR($I29="Оплачено",$H29<>""),$P29,$Q29) | T29: =IF(OR($C29="",$D29="Доход",$I29="Оплачено",$I29="Отменено",$H29<>"",$C29<TODAY()),"",$C29) | U29: =IF(AND($D29<>"Доход",COUNTIFS(Счета!$B$10:$B$21,$J29,Счета!$C$10:$C$21,"Кредитная")>0),1,0)
B30: =IF(AND($C30="",$F30=""),"",ROW()-9) | L30: =IF(OR($C30="",$I30="Оплачено",$I30="Отменено",$H30<>""),"",$C30-TODAY()) | M30: =IF($C30="","",INDEX(Настройки!$V$6:$V$17,MONTH($C30))&" "&YEAR($C30)) | N30: =IF($F30="","",IF(COUNTIF(Постоянные!$C$8:$C$37,$F30)>0,"есть в Постоянных",IF(COUNTIF(Покупки!$C$7:$C$18,$F30)>0,"есть в Покупках",""))) | P30: =IF($H30<>"",$H30,IF($I30="Оплачено",N($G30),0)) | Q30: =IF($I30="Отменено",0,IF($G30<>"",$G30,N($H30))) | R30: =IF($C30="","",IFERROR(DATE(Настройки!$C$8,Настройки!$D$9+MATCH($M30,Настройки!$X$6:$X$17,0)-1,1),DATE(YEAR($C30),MONTH($C30),1))) | S30: =IF(OR($I30="Оплачено",$H30<>""),$P30,$Q30) | T30: =IF(OR($C30="",$D30="Доход",$I30="Оплачено",$I30="Отменено",$H30<>"",$C30<TODAY()),"",$C30) | U30: =IF(AND($D30<>"Доход",COUNTIFS(Счета!$B$10:$B$21,$J30,Счета!$C$10:$C$21,"Кредитная")>0),1,0)
B31: =IF(AND($C31="",$F31=""),"",ROW()-9) | L31: =IF(OR($C31="",$I31="Оплачено",$I31="Отменено",$H31<>""),"",$C31-TODAY()) | M31: =IF($C31="","",INDEX(Настройки!$V$6:$V$17,MONTH($C31))&" "&YEAR($C31)) | N31: =IF($F31="","",IF(COUNTIF(Постоянные!$C$8:$C$37,$F31)>0,"есть в Постоянных",IF(COUNTIF(Покупки!$C$7:$C$18,$F31)>0,"есть в Покупках",""))) | P31: =IF($H31<>"",$H31,IF($I31="Оплачено",N($G31),0)) | Q31: =IF($I31="Отменено",0,IF($G31<>"",$G31,N($H31))) | R31: =IF($C31="","",IFERROR(DATE(Настройки!$C$8,Настройки!$D$9+MATCH($M31,Настройки!$X$6:$X$17,0)-1,1),DATE(YEAR($C31),MONTH($C31),1))) | S31: =IF(OR($I31="Оплачено",$H31<>""),$P31,$Q31) | T31: =IF(OR($C31="",$D31="Доход",$I31="Оплачено",$I31="Отменено",$H31<>"",$C31<TODAY()),"",$C31) | U31: =IF(AND($D31<>"Доход",COUNTIFS(Счета!$B$10:$B$21,$J31,Счета!$C$10:$C$21,"Кредитная")>0),1,0)
... B1509: =IF(AND($C1509="",$F1509=""),"",ROW()-9) | L1509: =IF(OR($C1509="",$I1509="Оплачено",$I1509="Отменено",$H1509<>""),"",$C1509-TODAY()) | M1509: =IF($C1509="","",INDEX(Настройки!$V$6:$V$17,MONTH($C1509))&" "&YEAR($C1509)) | N1509: =IF($F1509="","",IF(COUNTIF(Постоянные!$C$8:$C$37,$F1509)>0,"есть в Постоянных",IF(COUNTIF(Покупки!$C$7:$C$18,$F1509)>0,"есть в Покупках",""))) | P1509: =IF($H1509<>"",$H1509,IF($I1509="Оплачено",N($G1509),0)) | Q1509: =IF($I1509="Отменено",0,IF($G1509<>"",$G1509,N($H1509))) | R1509: =IF($C1509="","",IFERROR(DATE(Настройки!$C$8,Настройки!$D$9+MATCH($M1509,Настройки!$X$6:$X$17,0)-1,1),DATE(YEAR($C1509),MONTH($C1509),1))) | S1509: =IF(OR($I1509="Оплачено",$H1509<>""),$P1509,$Q1509) | T1509: =IF(OR($C1509="",$D1509="Доход",$I1509="Оплачено",$I1509="Отменено",$H1509<>"",$C1509<TODAY()),"",$C1509) | U1509: =IF(AND($D1509<>"Доход",COUNTIFS(Счета!$B$10:$B$21,$J1509,Счета!$C$10:$C$21,"Кредитная")>0),1,0)
C1511: Факт: вписанная «Сумма факт», а если её нет и статус «Оплачено» — сумма план. «Отменено» убирает трату из плана. Возврат денег — отрицательная сумма факт. «Месяц учёта» — в какой месяц статистики идёт строка (зарплата в конце месяца → следующий).

Sheet Постоянные
B2: Постоянные платежи и доходы
B3: Вводишь один раз. Заплатила — ✓ в клетке месяца; другая сумма — впиши число
B4: ✓ — оплачено по плану · число — оплачено столько · пусто — ещё нет. Серые клетки — месяцы без списания. «Раз в N мес.»: пусто — каждый месяц, 3 — раз в квартал (с месяца «Действует с»).
Y5: Развёртка на учётный год — считается сама | AG5: Развёртка на прогноз
L6: =DATE(Настройки!$C$8,Настройки!$D$9+0,1) | M6: =DATE(Настройки!$C$8,Настройки!$D$9+1,1) | N6: =DATE(Настройки!$C$8,Настройки!$D$9+2,1) | O6: =DATE(Настройки!$C$8,Настройки!$D$9+3,1) | P6: =DATE(Настройки!$C$8,Настройки!$D$9+4,1) | Q6: =DATE(Настройки!$C$8,Настройки!$D$9+5,1) | R6: =DATE(Настройки!$C$8,Настройки!$D$9+6,1) | S6: =DATE(Настройки!$C$8,Настройки!$D$9+7,1) | T6: =DATE(Настройки!$C$8,Настройки!$D$9+8,1) | U6: =DATE(Настройки!$C$8,Настройки!$D$9+9,1) | V6: =DATE(Настройки!$C$8,Настройки!$D$9+10,1) | W6: =DATE(Настройки!$C$8,Настройки!$D$9+11,1)
B7: № | C7: Что | D7: Тип | E7: Категория | F7: День | G7: Сумма | H7: Раз в N мес. | I7: Действует с | J7: по | K7: Счёт | L7: =Настройки!$X$6 | M7: =Настройки!$X$7 | N7: =Настройки!$X$8 | O7: =Настройки!$X$9 | P7: =Настройки!$X$10 | Q7: =Настройки!$X$11 | R7: =Настройки!$X$12 | S7: =Настройки!$X$13 | T7: =Настройки!$X$14 | U7: =Настройки!$X$15 | V7: =Настройки!$X$16 | W7: =Настройки!$X$17 | Y7: Дата | Z7: Тип | AA7: Категория | AB7: План | AC7: Факт | AD7: Месяц | AE7: Счёт | AG7: Дата | AH7: Тип | AI7: Категория | AJ7: Ожидаемо
B8: 1 | C8: Аренда | D8: Расход | E8: Жильё | F8: 5 | G8: 900 | I8: 46296 | K8: Карта | L8: ✓ | M8: 950 | Y8: =IF(OR($C8="",$F8=""),"",DATE(YEAR($L$6),MONTH($L$6),MIN($F8,DAY((DATE(YEAR($L$6),MONTH($L$6)+1,1)-1))))) | Z8: =IF($C8="","",IF($D8="Доход","Доход","Расход")) | AA8: =IF($C8="","",$E8) | AB8: =IF($C8="",0,IF(AND(OR($I8="",$I8<=(DATE(YEAR($L$6),MONTH($L$6)+1,1)-1)),OR($J8="",$J8>=$L$6),MOD((YEAR($L$6)*12+MONTH($L$6))-(YEAR(IF($I8="",$L$6,$I8))*12+MONTH(IF($I8="",$L$6,$I8))),MAX(1,N($H8)))=0),N($G8),0)) | AC8: =IF($C8="",0,IF(L8="✓",N($G8),IF(ISNUMBER(L8),L8,0))) | AD8: =IF($C8="","",$L$6) | AE8: =IF($C8="","",$K8) | AG8: =IF(OR($C8="",$F8=""),"",DATE(YEAR(DATE(Настройки!$C$6,Настройки!$D$7+0,1)),MONTH(DATE(Настройки!$C$6,Настройки!$D$7+0,1)),MIN($F8,DAY((DATE(Настройки!$C$6,Настройки!$D$7+0+1,1)-1))))) | AH8: =IF($C8="","",IF($D8="Доход","Доход","Расход")) | AI8: =IF($C8="","",$E8) | AJ8: =IF($C8="",0,IF(AND(((YEAR(DATE(Настройки!$C$6,Настройки!$D$7+0,1))*12+MONTH(DATE(Настройки!$C$6,Настройки!$D$7+0,1)))-(YEAR($L$6)*12+MONTH($L$6)))>=0,((YEAR(DATE(Настройки!$C$6,Настройки!$D$7+0,1))*12+MONTH(DATE(Настройки!$C$6,Настройки!$D$7+0,1)))-(YEAR($L$6)*12+MONTH($L$6)))<=11),IF(INDEX($L8:$W8,((YEAR(DATE(Настройки!$C$6,Настройки!$D$7+0,1))*12+MONTH(DATE(Настройки!$C$6,Настройки!$D$7+0,1)))-(YEAR($L$6)*12+MONTH($L$6)))+1)="✓",N($G8),IF(ISNUMBER(INDEX($L8:$W8,((YEAR(DATE(Настройки!$C$6,Настройки!$D$7+0,1))*12+MONTH(DATE(Настройки!$C$6,Настройки!$D$7+0,1)))-(YEAR($L$6)*12+MONTH($L$6)))+1)),INDEX($L8:$W8,((YEAR(DATE(Настройки!$C$6,Настройки!$D$7+0,1))*12+MONTH(DATE(Настройки!$C$6,Настройки!$D$7+0,1)))-(YEAR($L$6)*12+MONTH($L$6)))+1),IF(AND(OR($I8="",$I8<=(DATE(Настройки!$C$6,Настройки!$D$7+0+1,1)-1)),OR($J8="",$J8>=DATE(Настройки!$C$6,Настройки!$D$7+0,1)),MOD((YEAR(DATE(Настройки!$C$6,Настройки!$D$7+0,1))*12+MONTH(DATE(Настройки!$C$6,Настройки!$D$7+0,1)))-(YEAR(IF($I8="",$L$6,$I8))*12+MONTH(IF($I8="",$L$6,$I8))),MAX(1,N($H8)))=0),N($G8),0))),IF(AND(OR($I8="",$I8<=(DATE(Настройки!$C$6,Настройки!$D$7+0+1,1)-1)),OR($J8="",$J8>=DATE(Настройки!$C$6,Настройки!$D$7+0,1)),MOD((YEAR(DATE(Настройки!$C$6,Настройки!$D$7+0,1))*12+MONTH(DATE(Настройки!$C$6,Настройки!$D$7+0,1)))-(YEAR(IF($I8="",$L$6,$I8))*12+MONTH(IF($I8="",$L$6,$I8))),MAX(1,N($H8)))=0),N($G8),0)))
B9: 2 | C9: Подписка | D9: Расход | E9: Подписки | F9: 10 | G9: 10 | I9: 46327 | K9: Кредитка | M9: ✓ | Y9: =IF(OR($C9="",$F9=""),"",DATE(YEAR($L$6),MONTH($L$6),MIN($F9,DAY((DATE(YEAR($L$6),MONTH($L$6)+1,1)-1))))) | Z9: =IF($C9="","",IF($D9="Доход","Доход","Расход")) | AA9: =IF($C9="","",$E9) | AB9: =IF($C9="",0,IF(AND(OR($I9="",$I9<=(DATE(YEAR($L$6),MONTH($L$6)+1,1)-1)),OR($J9="",$J9>=$L$6),MOD((YEAR($L$6)*12+MONTH($L$6))-(YEAR(IF($I9="",$L$6,$I9))*12+MONTH(IF($I9="",$L$6,$I9))),MAX(1,N($H9)))=0),N($G9),0)) | AC9: =IF($C9="",0,IF(L9="✓",N($G9),IF(ISNUMBER(L9),L9,0))) | AD9: =IF($C9="","",$L$6) | AE9: =IF($C9="","",$K9) | AG9: =IF(OR($C9="",$F9=""),"",DATE(YEAR(DATE(Настройки!$C$6,Настройки!$D$7+0,1)),MONTH(DATE(Настройки!$C$6,Настройки!$D$7+0,1)),MIN($F9,DAY((DATE(Настройки!$C$6,Настройки!$D$7+0+1,1)-1))))) | AH9: =IF($C9="","",IF($D9="Доход","Доход","Расход")) | AI9: =IF($C9="","",$E9) | AJ9: =IF($C9="",0,IF(AND(((YEAR(DATE(Настройки!$C$6,Настройки!$D$7+0,1))*12+MONTH(DATE(Настройки!$C$6,Настройки!$D$7+0,1)))-(YEAR($L$6)*12+MONTH($L$6)))>=0,((YEAR(DATE(Настройки!$C$6,Настройки!$D$7+0,1))*12+MONTH(DATE(Настройки!$C$6,Настройки!$D$7+0,1)))-(YEAR($L$6)*12+MONTH($L$6)))<=11),IF(INDEX($L9:$W9,((YEAR(DATE(Настройки!$C$6,Настройки!$D$7+0,1))*12+MONTH(DATE(Настройки!$C$6,Настройки!$D$7+0,1)))-(YEAR($L$6)*12+MONTH($L$6)))+1)="✓",N($G9),IF(ISNUMBER(INDEX($L9:$W9,((YEAR(DATE(Настройки!$C$6,Настройки!$D$7+0,1))*12+MONTH(DATE(Настройки!$C$6,Настройки!$D$7+0,1)))-(YEAR($L$6)*12+MONTH($L$6)))+1)),INDEX($L9:$W9,((YEAR(DATE(Настройки!$C$6,Настройки!$D$7+0,1))*12+MONTH(DATE(Настройки!$C$6,Настройки!$D$7+0,1)))-(YEAR($L$6)*12+MONTH($L$6)))+1),IF(AND(OR($I9="",$I9<=(DATE(Настройки!$C$6,Настройки!$D$7+0+1,1)-1)),OR($J9="",$J9>=DATE(Настройки!$C$6,Настройки!$D$7+0,1)),MOD((YEAR(DATE(Настройки!$C$6,Настройки!$D$7+0,1))*12+MONTH(DATE(Настройки!$C$6,Настройки!$D$7+0,1)))-(YEAR(IF($I9="",$L$6,$I9))*12+MONTH(IF($I9="",$L$6,$I9))),MAX(1,N($H9)))=0),N($G9),0))),IF(AND(OR($I9="",$I9<=(DATE(Настройки!$C$6,Настройки!$D$7+0+1,1)-1)),OR($J9="",$J9>=DATE(Настройки!$C$6,Настройки!$D$7+0,1)),MOD((YEAR(DATE(Настройки!$C$6,Настройки!$D$7+0,1))*12+MONTH(DATE(Настройки!$C$6,Настройки!$D$7+0,1)))-(YEAR(IF($I9="",$L$6,$I9))*12+MONTH(IF($I9="",$L$6,$I9))),MAX(1,N($H9)))=0),N($G9),0)))
B10: 3 | C10: ЗП бонус | D10: Доход | E10: Премия | F10: 20 | G10: 200 | K10: Карта | L10: ✓ | Y10: =IF(OR($C10="",$F10=""),"",DATE(YEAR($L$6),MONTH($L$6),MIN($F10,DAY((DATE(YEAR($L$6),MONTH($L$6)+1,1)-1))))) | Z10: =IF($C10="","",IF($D10="Доход","Доход","Расход")) | AA10: =IF($C10="","",$E10) | AB10: =IF($C10="",0,IF(AND(OR($I10="",$I10<=(DATE(YEAR($L$6),MONTH($L$6)+1,1)-1)),OR($J10="",$J10>=$L$6),MOD((YEAR($L$6)*12+MONTH($L$6))-(YEAR(IF($I10="",$L$6,$I10))*12+MONTH(IF($I10="",$L$6,$I10))),MAX(1,N($H10)))=0),N($G10),0)) | AC10: =IF($C10="",0,IF(L10="✓",N($G10),IF(ISNUMBER(L10),L10,0))) | AD10: =IF($C10="","",$L$6) | AE10: =IF($C10="","",$K10) | AG10: =IF(OR($C10="",$F10=""),"",DATE(YEAR(DATE(Настройки!$C$6,Настройки!$D$7+0,1)),MONTH(DATE(Настройки!$C$6,Настройки!$D$7+0,1)),MIN($F10,DAY((DATE(Настройки!$C$6,Настройки!$D$7+0+1,1)-1))))) | AH10: =IF($C10="","",IF($D10="Доход","Доход","Расход")) | AI10: =IF($C10="","",$E10) | AJ10: =IF($C10="",0,IF(AND(((YEAR(DATE(Настройки!$C$6,Настройки!$D$7+0,1))*12+MONTH(DATE(Настройки!$C$6,Настройки!$D$7+0,1)))-(YEAR($L$6)*12+MONTH($L$6)))>=0,((YEAR(DATE(Настройки!$C$6,Настройки!$D$7+0,1))*12+MONTH(DATE(Настройки!$C$6,Настройки!$D$7+0,1)))-(YEAR($L$6)*12+MONTH($L$6)))<=11),IF(INDEX($L10:$W10,((YEAR(DATE(Настройки!$C$6,Настройки!$D$7+0,1))*12+MONTH(DATE(Настройки!$C$6,Настройки!$D$7+0,1)))-(YEAR($L$6)*12+MONTH($L$6)))+1)="✓",N($G10),IF(ISNUMBER(INDEX($L10:$W10,((YEAR(DATE(Настройки!$C$6,Настройки!$D$7+0,1))*12+MONTH(DATE(Настройки!$C$6,Настройки!$D$7+0,1)))-(YEAR($L$6)*12+MONTH($L$6)))+1)),INDEX($L10:$W10,((YEAR(DATE(Настройки!$C$6,Настройки!$D$7+0,1))*12+MONTH(DATE(Настройки!$C$6,Настройки!$D$7+0,1)))-(YEAR($L$6)*12+MONTH($L$6)))+1),IF(AND(OR($I10="",$I10<=(DATE(Настройки!$C$6,Настройки!$D$7+0+1,1)-1)),OR($J10="",$J10>=DATE(Настройки!$C$6,Настройки!$D$7+0,1)),MOD((YEAR(DATE(Настройки!$C$6,Настройки!$D$7+0,1))*12+MONTH(DATE(Настройки!$C$6,Настройки!$D$7+0,1)))-(YEAR(IF($I10="",$L$6,$I10))*12+MONTH(IF($I10="",$L$6,$I10))),MAX(1,N($H10)))=0),N($G10),0))),IF(AND(OR($I10="",$I10<=(DATE(Настройки!$C$6,Настройки!$D$7+0+1,1)-1)),OR($J10="",$J10>=DATE(Настройки!$C$6,Настройки!$D$7+0,1)),MOD((YEAR(DATE(Настройки!$C$6,Настройки!$D$7+0,1))*12+MONTH(DATE(Настройки!$C$6,Настройки!$D$7+0,1)))-(YEAR(IF($I10="",$L$6,$I10))*12+MONTH(IF($I10="",$L$6,$I10))),MAX(1,N($H10)))=0),N($G10),0)))
B11: 4 | C11: Страховка | D11: Расход | E11: Подписки | F11: 15 | G11: 30 | H11: 3 | I11: 46327 | K11: Карта | Y11: =IF(OR($C11="",$F11=""),"",DATE(YEAR($L$6),MONTH($L$6),MIN($F11,DAY((DATE(YEAR($L$6),MONTH($L$6)+1,1)-1))))) | Z11: =IF($C11="","",IF($D11="Доход","Доход","Расход")) | AA11: =IF($C11="","",$E11) | AB11: =IF($C11="",0,IF(AND(OR($I11="",$I11<=(DATE(YEAR($L$6),MONTH($L$6)+1,1)-1)),OR($J11="",$J11>=$L$6),MOD((YEAR($L$6)*12+MONTH($L$6))-(YEAR(IF($I11="",$L$6,$I11))*12+MONTH(IF($I11="",$L$6,$I11))),MAX(1,N($H11)))=0),N($G11),0)) | AC11: =IF($C11="",0,IF(L11="✓",N($G11),IF(ISNUMBER(L11),L11,0))) | AD11: =IF($C11="","",$L$6) | AE11: =IF($C11="","",$K11) | AG11: =IF(OR($C11="",$F11=""),"",DATE(YEAR(DATE(Настройки!$C$6,Настройки!$D$7+0,1)),MONTH(DATE(Настройки!$C$6,Настройки!$D$7+0,1)),MIN($F11,DAY((DATE(Настройки!$C$6,Настройки!$D$7+0+1,1)-1))))) | AH11: =IF($C11="","",IF($D11="Доход","Доход","Расход")) | AI11: =IF($C11="","",$E11) | AJ11: =IF($C11="",0,IF(AND(((YEAR(DATE(Настройки!$C$6,Настройки!$D$7+0,1))*12+MONTH(DATE(Настройки!$C$6,Настройки!$D$7+0,1)))-(YEAR($L$6)*12+MONTH($L$6)))>=0,((YEAR(DATE(Настройки!$C$6,Настройки!$D$7+0,1))*12+MONTH(DATE(Настройки!$C$6,Настройки!$D$7+0,1)))-(YEAR($L$6)*12+MONTH($L$6)))<=11),IF(INDEX($L11:$W11,((YEAR(DATE(Настройки!$C$6,Настройки!$D$7+0,1))*12+MONTH(DATE(Настройки!$C$6,Настройки!$D$7+0,1)))-(YEAR($L$6)*12+MONTH($L$6)))+1)="✓",N($G11),IF(ISNUMBER(INDEX($L11:$W11,((YEAR(DATE(Настройки!$C$6,Настройки!$D$7+0,1))*12+MONTH(DATE(Настройки!$C$6,Настройки!$D$7+0,1)))-(YEAR($L$6)*12+MONTH($L$6)))+1)),INDEX($L11:$W11,((YEAR(DATE(Настройки!$C$6,Настройки!$D$7+0,1))*12+MONTH(DATE(Настройки!$C$6,Настройки!$D$7+0,1)))-(YEAR($L$6)*12+MONTH($L$6)))+1),IF(AND(OR($I11="",$I11<=(DATE(Настройки!$C$6,Настройки!$D$7+0+1,1)-1)),OR($J11="",$J11>=DATE(Настройки!$C$6,Настройки!$D$7+0,1)),MOD((YEAR(DATE(Настройки!$C$6,Настройки!$D$7+0,1))*12+MONTH(DATE(Настройки!$C$6,Настройки!$D$7+0,1)))-(YEAR(IF($I11="",$L$6,$I11))*12+MONTH(IF($I11="",$L$6,$I11))),MAX(1,N($H11)))=0),N($G11),0))),IF(AND(OR($I11="",$I11<=(DATE(Настройки!$C$6,Настройки!$D$7+0+1,1)-1)),OR($J11="",$J11>=DATE(Настройки!$C$6,Настройки!$D$7+0,1)),MOD((YEAR(DATE(Настройки!$C$6,Настройки!$D$7+0,1))*12+MONTH(DATE(Настройки!$C$6,Настройки!$D$7+0,1)))-(YEAR(IF($I11="",$L$6,$I11))*12+MONTH(IF($I11="",$L$6,$I11))),MAX(1,N($H11)))=0),N($G11),0)))
B12: 5 | Y12: =IF(OR($C12="",$F12=""),"",DATE(YEAR($L$6),MONTH($L$6),MIN($F12,DAY((DATE(YEAR($L$6),MONTH($L$6)+1,1)-1))))) | Z12: =IF($C12="","",IF($D12="Доход","Доход","Расход")) | AA12: =IF($C12="","",$E12) | AB12: =IF($C12="",0,IF(AND(OR($I12="",$I12<=(DATE(YEAR($L$6),MONTH($L$6)+1,1)-1)),OR($J12="",$J12>=$L$6),MOD((YEAR($L$6)*12+MONTH($L$6))-(YEAR(IF($I12="",$L$6,$I12))*12+MONTH(IF($I12="",$L$6,$I12))),MAX(1,N($H12)))=0),N($G12),0)) | AC12: =IF($C12="",0,IF(L12="✓",N($G12),IF(ISNUMBER(L12),L12,0))) | AD12: =IF($C12="","",$L$6) | AE12: =IF($C12="","",$K12) | AG12: =IF(OR($C12="",$F12=""),"",DATE(YEAR(DATE(Настройки!$C$6,Настройки!$D$7+0,1)),MONTH(DATE(Настройки!$C$6,Настройки!$D$7+0,1)),MIN($F12,DAY((DATE(Настройки!$C$6,Настройки!$D$7+0+1,1)-1))))) | AH12: =IF($C12="","",IF($D12="Доход","Доход","Расход")) | AI12: =IF($C12="","",$E12) | AJ12: =IF($C12="",0,IF(AND(((YEAR(DATE(Настройки!$C$6,Настройки!$D$7+0,1))*12+MONTH(DATE(Настройки!$C$6,Настройки!$D$7+0,1)))-(YEAR($L$6)*12+MONTH($L$6)))>=0,((YEAR(DATE(Настройки!$C$6,Настройки!$D$7+0,1))*12+MONTH(DATE(Настройки!$C$6,Настройки!$D$7+0,1)))-(YEAR($L$6)*12+MONTH($L$6)))<=11),IF(INDEX($L12:$W12,((YEAR(DATE(Настройки!$C$6,Настройки!$D$7+0,1))*12+MONTH(DATE(Настройки!$C$6,Настройки!$D$7+0,1)))-(YEAR($L$6)*12+MONTH($L$6)))+1)="✓",N($G12),IF(ISNUMBER(INDEX($L12:$W12,((YEAR(DATE(Настройки!$C$6,Настройки!$D$7+0,1))*12+MONTH(DATE(Настройки!$C$6,Настройки!$D$7+0,1)))-(YEAR($L$6)*12+MONTH($L$6)))+1)),INDEX($L12:$W12,((YEAR(DATE(Настройки!$C$6,Настройки!$D$7+0,1))*12+MONTH(DATE(Настройки!$C$6,Настройки!$D$7+0,1)))-(YEAR($L$6)*12+MONTH($L$6)))+1),IF(AND(OR($I12="",$I12<=(DATE(Настройки!$C$6,Настройки!$D$7+0+1,1)-1)),OR($J12="",$J12>=DATE(Настройки!$C$6,Настройки!$D$7+0,1)),MOD((YEAR(DATE(Настройки!$C$6,Настройки!$D$7+0,1))*12+MONTH(DATE(Настройки!$C$6,Настройки!$D$7+0,1)))-(YEAR(IF($I12="",$L$6,$I12))*12+MONTH(IF($I12="",$L$6,$I12))),MAX(1,N($H12)))=0),N($G12),0))),IF(AND(OR($I12="",$I12<=(DATE(Настройки!$C$6,Настройки!$D$7+0+1,1)-1)),OR($J12="",$J12>=DATE(Настройки!$C$6,Настройки!$D$7+0,1)),MOD((YEAR(DATE(Настройки!$C$6,Настройки!$D$7+0,1))*12+MONTH(DATE(Настройки!$C$6,Настройки!$D$7+0,1)))-(YEAR(IF($I12="",$L$6,$I12))*12+MONTH(IF($I12="",$L$6,$I12))),MAX(1,N($H12)))=0),N($G12),0)))
B13: 6 | Y13: =IF(OR($C13="",$F13=""),"",DATE(YEAR($L$6),MONTH($L$6),MIN($F13,DAY((DATE(YEAR($L$6),MONTH($L$6)+1,1)-1))))) | Z13: =IF($C13="","",IF($D13="Доход","Доход","Расход")) | AA13: =IF($C13="","",$E13) | AB13: =IF($C13="",0,IF(AND(OR($I13="",$I13<=(DATE(YEAR($L$6),MONTH($L$6)+1,1)-1)),OR($J13="",$J13>=$L$6),MOD((YEAR($L$6)*12+MONTH($L$6))-(YEAR(IF($I13="",$L$6,$I13))*12+MONTH(IF($I13="",$L$6,$I13))),MAX(1,N($H13)))=0),N($G13),0)) | AC13: =IF($C13="",0,IF(L13="✓",N($G13),IF(ISNUMBER(L13),L13,0))) | AD13: =IF($C13="","",$L$6) | AE13: =IF($C13="","",$K13) | AG13: =IF(OR($C13="",$F13=""),"",DATE(YEAR(DATE(Настройки!$C$6,Настройки!$D$7+0,1)),MONTH(DATE(Настройки!$C$6,Настройки!$D$7+0,1)),MIN($F13,DAY((DATE(Настройки!$C$6,Настройки!$D$7+0+1,1)-1))))) | AH13: =IF($C13="","",IF($D13="Доход","Доход","Расход")) | AI13: =IF($C13="","",$E13) | AJ13: =IF($C13="",0,IF(AND(((YEAR(DATE(Настройки!$C$6,Настройки!$D$7+0,1))*12+MONTH(DATE(Настройки!$C$6,Настройки!$D$7+0,1)))-(YEAR($L$6)*12+MONTH($L$6)))>=0,((YEAR(DATE(Настройки!$C$6,Настройки!$D$7+0,1))*12+MONTH(DATE(Настройки!$C$6,Настройки!$D$7+0,1)))-(YEAR($L$6)*12+MONTH($L$6)))<=11),IF(INDEX($L13:$W13,((YEAR(DATE(Настройки!$C$6,Настройки!$D$7+0,1))*12+MONTH(DATE(Настройки!$C$6,Настройки!$D$7+0,1)))-(YEAR($L$6)*12+MONTH($L$6)))+1)="✓",N($G13),IF(ISNUMBER(INDEX($L13:$W13,((YEAR(DATE(Настройки!$C$6,Настройки!$D$7+0,1))*12+MONTH(DATE(Настройки!$C$6,Настройки!$D$7+0,1)))-(YEAR($L$6)*12+MONTH($L$6)))+1)),INDEX($L13:$W13,((YEAR(DATE(Настройки!$C$6,Настройки!$D$7+0,1))*12+MONTH(DATE(Настройки!$C$6,Настройки!$D$7+0,1)))-(YEAR($L$6)*12+MONTH($L$6)))+1),IF(AND(OR($I13="",$I13<=(DATE(Настройки!$C$6,Настройки!$D$7+0+1,1)-1)),OR($J13="",$J13>=DATE(Настройки!$C$6,Настройки!$D$7+0,1)),MOD((YEAR(DATE(Настройки!$C$6,Настройки!$D$7+0,1))*12+MONTH(DATE(Настройки!$C$6,Настройки!$D$7+0,1)))-(YEAR(IF($I13="",$L$6,$I13))*12+MONTH(IF($I13="",$L$6,$I13))),MAX(1,N($H13)))=0),N($G13),0))),IF(AND(OR($I13="",$I13<=(DATE(Настройки!$C$6,Настройки!$D$7+0+1,1)-1)),OR($J13="",$J13>=DATE(Настройки!$C$6,Настройки!$D$7+0,1)),MOD((YEAR(DATE(Настройки!$C$6,Настройки!$D$7+0,1))*12+MONTH(DATE(Настройки!$C$6,Настройки!$D$7+0,1)))-(YEAR(IF($I13="",$L$6,$I13))*12+MONTH(IF($I13="",$L$6,$I13))),MAX(1,N($H13)))=0),N($G13),0)))
B14: 7 | Y14: =IF(OR($C14="",$F14=""),"",DATE(YEAR($L$6),MONTH($L$6),MIN($F14,DAY((DATE(YEAR($L$6),MONTH($L$6)+1,1)-1))))) | Z14: =IF($C14="","",IF($D14="Доход","Доход","Расход")) | AA14: =IF($C14="","",$E14) | AB14: =IF($C14="",0,IF(AND(OR($I14="",$I14<=(DATE(YEAR($L$6),MONTH($L$6)+1,1)-1)),OR($J14="",$J14>=$L$6),MOD((YEAR($L$6)*12+MONTH($L$6))-(YEAR(IF($I14="",$L$6,$I14))*12+MONTH(IF($I14="",$L$6,$I14))),MAX(1,N($H14)))=0),N($G14),0)) | AC14: =IF($C14="",0,IF(L14="✓",N($G14),IF(ISNUMBER(L14),L14,0))) | AD14: =IF($C14="","",$L$6) | AE14: =IF($C14="","",$K14) | AG14: =IF(OR($C14="",$F14=""),"",DATE(YEAR(DATE(Настройки!$C$6,Настройки!$D$7+0,1)),MONTH(DATE(Настройки!$C$6,Настройки!$D$7+0,1)),MIN($F14,DAY((DATE(Настройки!$C$6,Настройки!$D$7+0+1,1)-1))))) | AH14: =IF($C14="","",IF($D14="Доход","Доход","Расход")) | AI14: =IF($C14="","",$E14) | AJ14: =IF($C14="",0,IF(AND(((YEAR(DATE(Настройки!$C$6,Настройки!$D$7+0,1))*12+MONTH(DATE(Настройки!$C$6,Настройки!$D$7+0,1)))-(YEAR($L$6)*12+MONTH($L$6)))>=0,((YEAR(DATE(Настройки!$C$6,Настройки!$D$7+0,1))*12+MONTH(DATE(Настройки!$C$6,Настройки!$D$7+0,1)))-(YEAR($L$6)*12+MONTH($L$6)))<=11),IF(INDEX($L14:$W14,((YEAR(DATE(Настройки!$C$6,Настройки!$D$7+0,1))*12+MONTH(DATE(Настройки!$C$6,Настройки!$D$7+0,1)))-(YEAR($L$6)*12+MONTH($L$6)))+1)="✓",N($G14),IF(ISNUMBER(INDEX($L14:$W14,((YEAR(DATE(Настройки!$C$6,Настройки!$D$7+0,1))*12+MONTH(DATE(Настройки!$C$6,Настройки!$D$7+0,1)))-(YEAR($L$6)*12+MONTH($L$6)))+1)),INDEX($L14:$W14,((YEAR(DATE(Настройки!$C$6,Настройки!$D$7+0,1))*12+MONTH(DATE(Настройки!$C$6,Настройки!$D$7+0,1)))-(YEAR($L$6)*12+MONTH($L$6)))+1),IF(AND(OR($I14="",$I14<=(DATE(Настройки!$C$6,Настройки!$D$7+0+1,1)-1)),OR($J14="",$J14>=DATE(Настройки!$C$6,Настройки!$D$7+0,1)),MOD((YEAR(DATE(Настройки!$C$6,Настройки!$D$7+0,1))*12+MONTH(DATE(Настройки!$C$6,Настройки!$D$7+0,1)))-(YEAR(IF($I14="",$L$6,$I14))*12+MONTH(IF($I14="",$L$6,$I14))),MAX(1,N($H14)))=0),N($G14),0))),IF(AND(OR($I14="",$I14<=(DATE(Настройки!$C$6,Настройки!$D$7+0+1,1)-1)),OR($J14="",$J14>=DATE(Настройки!$C$6,Настройки!$D$7+0,1)),MOD((YEAR(DATE(Настройки!$C$6,Настройки!$D$7+0,1))*12+MONTH(DATE(Настройки!$C$6,Настройки!$D$7+0,1)))-(YEAR(IF($I14="",$L$6,$I14))*12+MONTH(IF($I14="",$L$6,$I14))),MAX(1,N($H14)))=0),N($G14),0)))
B15: 8 | Y15: =IF(OR($C15="",$F15=""),"",DATE(YEAR($L$6),MONTH($L$6),MIN($F15,DAY((DATE(YEAR($L$6),MONTH($L$6)+1,1)-1))))) | Z15: =IF($C15="","",IF($D15="Доход","Доход","Расход")) | AA15: =IF($C15="","",$E15) | AB15: =IF($C15="",0,IF(AND(OR($I15="",$I15<=(DATE(YEAR($L$6),MONTH($L$6)+1,1)-1)),OR($J15="",$J15>=$L$6),MOD((YEAR($L$6)*12+MONTH($L$6))-(YEAR(IF($I15="",$L$6,$I15))*12+MONTH(IF($I15="",$L$6,$I15))),MAX(1,N($H15)))=0),N($G15),0)) | AC15: =IF($C15="",0,IF(L15="✓",N($G15),IF(ISNUMBER(L15),L15,0))) | AD15: =IF($C15="","",$L$6) | AE15: =IF($C15="","",$K15) | AG15: =IF(OR($C15="",$F15=""),"",DATE(YEAR(DATE(Настройки!$C$6,Настройки!$D$7+0,1)),MONTH(DATE(Настройки!$C$6,Настройки!$D$7+0,1)),MIN($F15,DAY((DATE(Настройки!$C$6,Настройки!$D$7+0+1,1)-1))))) | AH15: =IF($C15="","",IF($D15="Доход","Доход","Расход")) | AI15: =IF($C15="","",$E15) | AJ15: =IF($C15="",0,IF(AND(((YEAR(DATE(Настройки!$C$6,Настройки!$D$7+0,1))*12+MONTH(DATE(Настройки!$C$6,Настройки!$D$7+0,1)))-(YEAR($L$6)*12+MONTH($L$6)))>=0,((YEAR(DATE(Настройки!$C$6,Настройки!$D$7+0,1))*12+MONTH(DATE(Настройки!$C$6,Настройки!$D$7+0,1)))-(YEAR($L$6)*12+MONTH($L$6)))<=11),IF(INDEX($L15:$W15,((YEAR(DATE(Настройки!$C$6,Настройки!$D$7+0,1))*12+MONTH(DATE(Настройки!$C$6,Настройки!$D$7+0,1)))-(YEAR($L$6)*12+MONTH($L$6)))+1)="✓",N($G15),IF(ISNUMBER(INDEX($L15:$W15,((YEAR(DATE(Настройки!$C$6,Настройки!$D$7+0,1))*12+MONTH(DATE(Настройки!$C$6,Настройки!$D$7+0,1)))-(YEAR($L$6)*12+MONTH($L$6)))+1)),INDEX($L15:$W15,((YEAR(DATE(Настройки!$C$6,Настройки!$D$7+0,1))*12+MONTH(DATE(Настройки!$C$6,Настройки!$D$7+0,1)))-(YEAR($L$6)*12+MONTH($L$6)))+1),IF(AND(OR($I15="",$I15<=(DATE(Настройки!$C$6,Настройки!$D$7+0+1,1)-1)),OR($J15="",$J15>=DATE(Настройки!$C$6,Настройки!$D$7+0,1)),MOD((YEAR(DATE(Настройки!$C$6,Настройки!$D$7+0,1))*12+MONTH(DATE(Настройки!$C$6,Настройки!$D$7+0,1)))-(YEAR(IF($I15="",$L$6,$I15))*12+MONTH(IF($I15="",$L$6,$I15))),MAX(1,N($H15)))=0),N($G15),0))),IF(AND(OR($I15="",$I15<=(DATE(Настройки!$C$6,Настройки!$D$7+0+1,1)-1)),OR($J15="",$J15>=DATE(Настройки!$C$6,Настройки!$D$7+0,1)),MOD((YEAR(DATE(Настройки!$C$6,Настройки!$D$7+0,1))*12+MONTH(DATE(Настройки!$C$6,Настройки!$D$7+0,1)))-(YEAR(IF($I15="",$L$6,$I15))*12+MONTH(IF($I15="",$L$6,$I15))),MAX(1,N($H15)))=0),N($G15),0)))
B16: 9 | Y16: =IF(OR($C16="",$F16=""),"",DATE(YEAR($L$6),MONTH($L$6),MIN($F16,DAY((DATE(YEAR($L$6),MONTH($L$6)+1,1)-1))))) | Z16: =IF($C16="","",IF($D16="Доход","Доход","Расход")) | AA16: =IF($C16="","",$E16) | AB16: =IF($C16="",0,IF(AND(OR($I16="",$I16<=(DATE(YEAR($L$6),MONTH($L$6)+1,1)-1)),OR($J16="",$J16>=$L$6),MOD((YEAR($L$6)*12+MONTH($L$6))-(YEAR(IF($I16="",$L$6,$I16))*12+MONTH(IF($I16="",$L$6,$I16))),MAX(1,N($H16)))=0),N($G16),0)) | AC16: =IF($C16="",0,IF(L16="✓",N($G16),IF(ISNUMBER(L16),L16,0))) | AD16: =IF($C16="","",$L$6) | AE16: =IF($C16="","",$K16) | AG16: =IF(OR($C16="",$F16=""),"",DATE(YEAR(DATE(Настройки!$C$6,Настройки!$D$7+0,1)),MONTH(DATE(Настройки!$C$6,Настройки!$D$7+0,1)),MIN($F16,DAY((DATE(Настройки!$C$6,Настройки!$D$7+0+1,1)-1))))) | AH16: =IF($C16="","",IF($D16="Доход","Доход","Расход")) | AI16: =IF($C16="","",$E16) | AJ16: =IF($C16="",0,IF(AND(((YEAR(DATE(Настройки!$C$6,Настройки!$D$7+0,1))*12+MONTH(DATE(Настройки!$C$6,Настройки!$D$7+0,1)))-(YEAR($L$6)*12+MONTH($L$6)))>=0,((YEAR(DATE(Настройки!$C$6,Настройки!$D$7+0,1))*12+MONTH(DATE(Настройки!$C$6,Настройки!$D$7+0,1)))-(YEAR($L$6)*12+MONTH($L$6)))<=11),IF(INDEX($L16:$W16,((YEAR(DATE(Настройки!$C$6,Настройки!$D$7+0,1))*12+MONTH(DATE(Настройки!$C$6,Настройки!$D$7+0,1)))-(YEAR($L$6)*12+MONTH($L$6)))+1)="✓",N($G16),IF(ISNUMBER(INDEX($L16:$W16,((YEAR(DATE(Настройки!$C$6,Настройки!$D$7+0,1))*12+MONTH(DATE(Настройки!$C$6,Настройки!$D$7+0,1)))-(YEAR($L$6)*12+MONTH($L$6)))+1)),INDEX($L16:$W16,((YEAR(DATE(Настройки!$C$6,Настройки!$D$7+0,1))*12+MONTH(DATE(Настройки!$C$6,Настройки!$D$7+0,1)))-(YEAR($L$6)*12+MONTH($L$6)))+1),IF(AND(OR($I16="",$I16<=(DATE(Настройки!$C$6,Настройки!$D$7+0+1,1)-1)),OR($J16="",$J16>=DATE(Настройки!$C$6,Настройки!$D$7+0,1)),MOD((YEAR(DATE(Настройки!$C$6,Настройки!$D$7+0,1))*12+MONTH(DATE(Настройки!$C$6,Настройки!$D$7+0,1)))-(YEAR(IF($I16="",$L$6,$I16))*12+MONTH(IF($I16="",$L$6,$I16))),MAX(1,N($H16)))=0),N($G16),0))),IF(AND(OR($I16="",$I16<=(DATE(Настройки!$C$6,Настройки!$D$7+0+1,1)-1)),OR($J16="",$J16>=DATE(Настройки!$C$6,Настройки!$D$7+0,1)),MOD((YEAR(DATE(Настройки!$C$6,Настройки!$D$7+0,1))*12+MONTH(DATE(Настройки!$C$6,Настройки!$D$7+0,1)))-(YEAR(IF($I16="",$L$6,$I16))*12+MONTH(IF($I16="",$L$6,$I16))),MAX(1,N($H16)))=0),N($G16),0)))
B17: 10 | Y17: =IF(OR($C17="",$F17=""),"",DATE(YEAR($L$6),MONTH($L$6),MIN($F17,DAY((DATE(YEAR($L$6),MONTH($L$6)+1,1)-1))))) | Z17: =IF($C17="","",IF($D17="Доход","Доход","Расход")) | AA17: =IF($C17="","",$E17) | AB17: =IF($C17="",0,IF(AND(OR($I17="",$I17<=(DATE(YEAR($L$6),MONTH($L$6)+1,1)-1)),OR($J17="",$J17>=$L$6),MOD((YEAR($L$6)*12+MONTH($L$6))-(YEAR(IF($I17="",$L$6,$I17))*12+MONTH(IF($I17="",$L$6,$I17))),MAX(1,N($H17)))=0),N($G17),0)) | AC17: =IF($C17="",0,IF(L17="✓",N($G17),IF(ISNUMBER(L17),L17,0))) | AD17: =IF($C17="","",$L$6) | AE17: =IF($C17="","",$K17) | AG17: =IF(OR($C17="",$F17=""),"",DATE(YEAR(DATE(Настройки!$C$6,Настройки!$D$7+0,1)),MONTH(DATE(Настройки!$C$6,Настройки!$D$7+0,1)),MIN($F17,DAY((DATE(Настройки!$C$6,Настройки!$D$7+0+1,1)-1))))) | AH17: =IF($C17="","",IF($D17="Доход","Доход","Расход")) | AI17: =IF($C17="","",$E17) | AJ17: =IF($C17="",0,IF(AND(((YEAR(DATE(Настройки!$C$6,Настройки!$D$7+0,1))*12+MONTH(DATE(Настройки!$C$6,Настройки!$D$7+0,1)))-(YEAR($L$6)*12+MONTH($L$6)))>=0,((YEAR(DATE(Настройки!$C$6,Настройки!$D$7+0,1))*12+MONTH(DATE(Настройки!$C$6,Настройки!$D$7+0,1)))-(YEAR($L$6)*12+MONTH($L$6)))<=11),IF(INDEX($L17:$W17,((YEAR(DATE(Настройки!$C$6,Настройки!$D$7+0,1))*12+MONTH(DATE(Настройки!$C$6,Настройки!$D$7+0,1)))-(YEAR($L$6)*12+MONTH($L$6)))+1)="✓",N($G17),IF(ISNUMBER(INDEX($L17:$W17,((YEAR(DATE(Настройки!$C$6,Настройки!$D$7+0,1))*12+MONTH(DATE(Настройки!$C$6,Настройки!$D$7+0,1)))-(YEAR($L$6)*12+MONTH($L$6)))+1)),INDEX($L17:$W17,((YEAR(DATE(Настройки!$C$6,Настройки!$D$7+0,1))*12+MONTH(DATE(Настройки!$C$6,Настройки!$D$7+0,1)))-(YEAR($L$6)*12+MONTH($L$6)))+1),IF(AND(OR($I17="",$I17<=(DATE(Настройки!$C$6,Настройки!$D$7+0+1,1)-1)),OR($J17="",$J17>=DATE(Настройки!$C$6,Настройки!$D$7+0,1)),MOD((YEAR(DATE(Настройки!$C$6,Настройки!$D$7+0,1))*12+MONTH(DATE(Настройки!$C$6,Настройки!$D$7+0,1)))-(YEAR(IF($I17="",$L$6,$I17))*12+MONTH(IF($I17="",$L$6,$I17))),MAX(1,N($H17)))=0),N($G17),0))),IF(AND(OR($I17="",$I17<=(DATE(Настройки!$C$6,Настройки!$D$7+0+1,1)-1)),OR($J17="",$J17>=DATE(Настройки!$C$6,Настройки!$D$7+0,1)),MOD((YEAR(DATE(Настройки!$C$6,Настройки!$D$7+0,1))*12+MONTH(DATE(Настройки!$C$6,Настройки!$D$7+0,1)))-(YEAR(IF($I17="",$L$6,$I17))*12+MONTH(IF($I17="",$L$6,$I17))),MAX(1,N($H17)))=0),N($G17),0)))
B18: 11 | Y18: =IF(OR($C18="",$F18=""),"",DATE(YEAR($L$6),MONTH($L$6),MIN($F18,DAY((DATE(YEAR($L$6),MONTH($L$6)+1,1)-1))))) | Z18: =IF($C18="","",IF($D18="Доход","Доход","Расход")) | AA18: =IF($C18="","",$E18) | AB18: =IF($C18="",0,IF(AND(OR($I18="",$I18<=(DATE(YEAR($L$6),MONTH($L$6)+1,1)-1)),OR($J18="",$J18>=$L$6),MOD((YEAR($L$6)*12+MONTH($L$6))-(YEAR(IF($I18="",$L$6,$I18))*12+MONTH(IF($I18="",$L$6,$I18))),MAX(1,N($H18)))=0),N($G18),0)) | AC18: =IF($C18="",0,IF(L18="✓",N($G18),IF(ISNUMBER(L18),L18,0))) | AD18: =IF($C18="","",$L$6) | AE18: =IF($C18="","",$K18) | AG18: =IF(OR($C18="",$F18=""),"",DATE(YEAR(DATE(Настройки!$C$6,Настройки!$D$7+0,1)),MONTH(DATE(Настройки!$C$6,Настройки!$D$7+0,1)),MIN($F18,DAY((DATE(Настройки!$C$6,Настройки!$D$7+0+1,1)-1))))) | AH18: =IF($C18="","",IF($D18="Доход","Доход","Расход")) | AI18: =IF($C18="","",$E18) | AJ18: =IF($C18="",0,IF(AND(((YEAR(DATE(Настройки!$C$6,Настройки!$D$7+0,1))*12+MONTH(DATE(Настройки!$C$6,Настройки!$D$7+0,1)))-(YEAR($L$6)*12+MONTH($L$6)))>=0,((YEAR(DATE(Настройки!$C$6,Настройки!$D$7+0,1))*12+MONTH(DATE(Настройки!$C$6,Настройки!$D$7+0,1)))-(YEAR($L$6)*12+MONTH($L$6)))<=11),IF(INDEX($L18:$W18,((YEAR(DATE(Настройки!$C$6,Настройки!$D$7+0,1))*12+MONTH(DATE(Настройки!$C$6,Настройки!$D$7+0,1)))-(YEAR($L$6)*12+MONTH($L$6)))+1)="✓",N($G18),IF(ISNUMBER(INDEX($L18:$W18,((YEAR(DATE(Настройки!$C$6,Настройки!$D$7+0,1))*12+MONTH(DATE(Настройки!$C$6,Настройки!$D$7+0,1)))-(YEAR($L$6)*12+MONTH($L$6)))+1)),INDEX($L18:$W18,((YEAR(DATE(Настройки!$C$6,Настройки!$D$7+0,1))*12+MONTH(DATE(Настройки!$C$6,Настройки!$D$7+0,1)))-(YEAR($L$6)*12+MONTH($L$6)))+1),IF(AND(OR($I18="",$I18<=(DATE(Настройки!$C$6,Настройки!$D$7+0+1,1)-1)),OR($J18="",$J18>=DATE(Настройки!$C$6,Настройки!$D$7+0,1)),MOD((YEAR(DATE(Настройки!$C$6,Настройки!$D$7+0,1))*12+MONTH(DATE(Настройки!$C$6,Настройки!$D$7+0,1)))-(YEAR(IF($I18="",$L$6,$I18))*12+MONTH(IF($I18="",$L$6,$I18))),MAX(1,N($H18)))=0),N($G18),0))),IF(AND(OR($I18="",$I18<=(DATE(Настройки!$C$6,Настройки!$D$7+0+1,1)-1)),OR($J18="",$J18>=DATE(Настройки!$C$6,Настройки!$D$7+0,1)),MOD((YEAR(DATE(Настройки!$C$6,Настройки!$D$7+0,1))*12+MONTH(DATE(Настройки!$C$6,Настройки!$D$7+0,1)))-(YEAR(IF($I18="",$L$6,$I18))*12+MONTH(IF($I18="",$L$6,$I18))),MAX(1,N($H18)))=0),N($G18),0)))
B19: 12 | Y19: =IF(OR($C19="",$F19=""),"",DATE(YEAR($L$6),MONTH($L$6),MIN($F19,DAY((DATE(YEAR($L$6),MONTH($L$6)+1,1)-1))))) | Z19: =IF($C19="","",IF($D19="Доход","Доход","Расход")) | AA19: =IF($C19="","",$E19) | AB19: =IF($C19="",0,IF(AND(OR($I19="",$I19<=(DATE(YEAR($L$6),MONTH($L$6)+1,1)-1)),OR($J19="",$J19>=$L$6),MOD((YEAR($L$6)*12+MONTH($L$6))-(YEAR(IF($I19="",$L$6,$I19))*12+MONTH(IF($I19="",$L$6,$I19))),MAX(1,N($H19)))=0),N($G19),0)) | AC19: =IF($C19="",0,IF(L19="✓",N($G19),IF(ISNUMBER(L19),L19,0))) | AD19: =IF($C19="","",$L$6) | AE19: =IF($C19="","",$K19) | AG19: =IF(OR($C19="",$F19=""),"",DATE(YEAR(DATE(Настройки!$C$6,Настройки!$D$7+0,1)),MONTH(DATE(Настройки!$C$6,Настройки!$D$7+0,1)),MIN($F19,DAY((DATE(Настройки!$C$6,Настройки!$D$7+0+1,1)-1))))) | AH19: =IF($C19="","",IF($D19="Доход","Доход","Расход")) | AI19: =IF($C19="","",$E19) | AJ19: =IF($C19="",0,IF(AND(((YEAR(DATE(Настройки!$C$6,Настройки!$D$7+0,1))*12+MONTH(DATE(Настройки!$C$6,Настройки!$D$7+0,1)))-(YEAR($L$6)*12+MONTH($L$6)))>=0,((YEAR(DATE(Настройки!$C$6,Настройки!$D$7+0,1))*12+MONTH(DATE(Настройки!$C$6,Настройки!$D$7+0,1)))-(YEAR($L$6)*12+MONTH($L$6)))<=11),IF(INDEX($L19:$W19,((YEAR(DATE(Настройки!$C$6,Настройки!$D$7+0,1))*12+MONTH(DATE(Настройки!$C$6,Настройки!$D$7+0,1)))-(YEAR($L$6)*12+MONTH($L$6)))+1)="✓",N($G19),IF(ISNUMBER(INDEX($L19:$W19,((YEAR(DATE(Настройки!$C$6,Настройки!$D$7+0,1))*12+MONTH(DATE(Настройки!$C$6,Настройки!$D$7+0,1)))-(YEAR($L$6)*12+MONTH($L$6)))+1)),INDEX($L19:$W19,((YEAR(DATE(Настройки!$C$6,Настройки!$D$7+0,1))*12+MONTH(DATE(Настройки!$C$6,Настройки!$D$7+0,1)))-(YEAR($L$6)*12+MONTH($L$6)))+1),IF(AND(OR($I19="",$I19<=(DATE(Настройки!$C$6,Настройки!$D$7+0+1,1)-1)),OR($J19="",$J19>=DATE(Настройки!$C$6,Настройки!$D$7+0,1)),MOD((YEAR(DATE(Настройки!$C$6,Настройки!$D$7+0,1))*12+MONTH(DATE(Настройки!$C$6,Настройки!$D$7+0,1)))-(YEAR(IF($I19="",$L$6,$I19))*12+MONTH(IF($I19="",$L$6,$I19))),MAX(1,N($H19)))=0),N($G19),0))),IF(AND(OR($I19="",$I19<=(DATE(Настройки!$C$6,Настройки!$D$7+0+1,1)-1)),OR($J19="",$J19>=DATE(Настройки!$C$6,Настройки!$D$7+0,1)),MOD((YEAR(DATE(Настройки!$C$6,Настройки!$D$7+0,1))*12+MONTH(DATE(Настройки!$C$6,Настройки!$D$7+0,1)))-(YEAR(IF($I19="",$L$6,$I19))*12+MONTH(IF($I19="",$L$6,$I19))),MAX(1,N($H19)))=0),N($G19),0)))
B20: 13 | Y20: =IF(OR($C20="",$F20=""),"",DATE(YEAR($L$6),MONTH($L$6),MIN($F20,DAY((DATE(YEAR($L$6),MONTH($L$6)+1,1)-1))))) | Z20: =IF($C20="","",IF($D20="Доход","Доход","Расход")) | AA20: =IF($C20="","",$E20) | AB20: =IF($C20="",0,IF(AND(OR($I20="",$I20<=(DATE(YEAR($L$6),MONTH($L$6)+1,1)-1)),OR($J20="",$J20>=$L$6),MOD((YEAR($L$6)*12+MONTH($L$6))-(YEAR(IF($I20="",$L$6,$I20))*12+MONTH(IF($I20="",$L$6,$I20))),MAX(1,N($H20)))=0),N($G20),0)) | AC20: =IF($C20="",0,IF(L20="✓",N($G20),IF(ISNUMBER(L20),L20,0))) | AD20: =IF($C20="","",$L$6) | AE20: =IF($C20="","",$K20) | AG20: =IF(OR($C20="",$F20=""),"",DATE(YEAR(DATE(Настройки!$C$6,Настройки!$D$7+0,1)),MONTH(DATE(Настройки!$C$6,Настройки!$D$7+0,1)),MIN($F20,DAY((DATE(Настройки!$C$6,Настройки!$D$7+0+1,1)-1))))) | AH20: =IF($C20="","",IF($D20="Доход","Доход","Расход")) | AI20: =IF($C20="","",$E20) | AJ20: =IF($C20="",0,IF(AND(((YEAR(DATE(Настройки!$C$6,Настройки!$D$7+0,1))*12+MONTH(DATE(Настройки!$C$6,Настройки!$D$7+0,1)))-(YEAR($L$6)*12+MONTH($L$6)))>=0,((YEAR(DATE(Настройки!$C$6,Настройки!$D$7+0,1))*12+MONTH(DATE(Настройки!$C$6,Настройки!$D$7+0,1)))-(YEAR($L$6)*12+MONTH($L$6)))<=11),IF(INDEX($L20:$W20,((YEAR(DATE(Настройки!$C$6,Настройки!$D$7+0,1))*12+MONTH(DATE(Настройки!$C$6,Настройки!$D$7+0,1)))-(YEAR($L$6)*12+MONTH($L$6)))+1)="✓",N($G20),IF(ISNUMBER(INDEX($L20:$W20,((YEAR(DATE(Настройки!$C$6,Настройки!$D$7+0,1))*12+MONTH(DATE(Настройки!$C$6,Настройки!$D$7+0,1)))-(YEAR($L$6)*12+MONTH($L$6)))+1)),INDEX($L20:$W20,((YEAR(DATE(Настройки!$C$6,Настройки!$D$7+0,1))*12+MONTH(DATE(Настройки!$C$6,Настройки!$D$7+0,1)))-(YEAR($L$6)*12+MONTH($L$6)))+1),IF(AND(OR($I20="",$I20<=(DATE(Настройки!$C$6,Настройки!$D$7+0+1,1)-1)),OR($J20="",$J20>=DATE(Настройки!$C$6,Настройки!$D$7+0,1)),MOD((YEAR(DATE(Настройки!$C$6,Настройки!$D$7+0,1))*12+MONTH(DATE(Настройки!$C$6,Настройки!$D$7+0,1)))-(YEAR(IF($I20="",$L$6,$I20))*12+MONTH(IF($I20="",$L$6,$I20))),MAX(1,N($H20)))=0),N($G20),0))),IF(AND(OR($I20="",$I20<=(DATE(Настройки!$C$6,Настройки!$D$7+0+1,1)-1)),OR($J20="",$J20>=DATE(Настройки!$C$6,Настройки!$D$7+0,1)),MOD((YEAR(DATE(Настройки!$C$6,Настройки!$D$7+0,1))*12+MONTH(DATE(Настройки!$C$6,Настройки!$D$7+0,1)))-(YEAR(IF($I20="",$L$6,$I20))*12+MONTH(IF($I20="",$L$6,$I20))),MAX(1,N($H20)))=0),N($G20),0)))
B21: 14 | Y21: =IF(OR($C21="",$F21=""),"",DATE(YEAR($L$6),MONTH($L$6),MIN($F21,DAY((DATE(YEAR($L$6),MONTH($L$6)+1,1)-1))))) | Z21: =IF($C21="","",IF($D21="Доход","Доход","Расход")) | AA21: =IF($C21="","",$E21) | AB21: =IF($C21="",0,IF(AND(OR($I21="",$I21<=(DATE(YEAR($L$6),MONTH($L$6)+1,1)-1)),OR($J21="",$J21>=$L$6),MOD((YEAR($L$6)*12+MONTH($L$6))-(YEAR(IF($I21="",$L$6,$I21))*12+MONTH(IF($I21="",$L$6,$I21))),MAX(1,N($H21)))=0),N($G21),0)) | AC21: =IF($C21="",0,IF(L21="✓",N($G21),IF(ISNUMBER(L21),L21,0))) | AD21: =IF($C21="","",$L$6) | AE21: =IF($C21="","",$K21) | AG21: =IF(OR($C21="",$F21=""),"",DATE(YEAR(DATE(Настройки!$C$6,Настройки!$D$7+0,1)),MONTH(DATE(Настройки!$C$6,Настройки!$D$7+0,1)),MIN($F21,DAY((DATE(Настройки!$C$6,Настройки!$D$7+0+1,1)-1))))) | AH21: =IF($C21="","",IF($D21="Доход","Доход","Расход")) | AI21: =IF($C21="","",$E21) | AJ21: =IF($C21="",0,IF(AND(((YEAR(DATE(Настройки!$C$6,Настройки!$D$7+0,1))*12+MONTH(DATE(Настройки!$C$6,Настройки!$D$7+0,1)))-(YEAR($L$6)*12+MONTH($L$6)))>=0,((YEAR(DATE(Настройки!$C$6,Настройки!$D$7+0,1))*12+MONTH(DATE(Настройки!$C$6,Настройки!$D$7+0,1)))-(YEAR($L$6)*12+MONTH($L$6)))<=11),IF(INDEX($L21:$W21,((YEAR(DATE(Настройки!$C$6,Настройки!$D$7+0,1))*12+MONTH(DATE(Настройки!$C$6,Настройки!$D$7+0,1)))-(YEAR($L$6)*12+MONTH($L$6)))+1)="✓",N($G21),IF(ISNUMBER(INDEX($L21:$W21,((YEAR(DATE(Настройки!$C$6,Настройки!$D$7+0,1))*12+MONTH(DATE(Настройки!$C$6,Настройки!$D$7+0,1)))-(YEAR($L$6)*12+MONTH($L$6)))+1)),INDEX($L21:$W21,((YEAR(DATE(Настройки!$C$6,Настройки!$D$7+0,1))*12+MONTH(DATE(Настройки!$C$6,Настройки!$D$7+0,1)))-(YEAR($L$6)*12+MONTH($L$6)))+1),IF(AND(OR($I21="",$I21<=(DATE(Настройки!$C$6,Настройки!$D$7+0+1,1)-1)),OR($J21="",$J21>=DATE(Настройки!$C$6,Настройки!$D$7+0,1)),MOD((YEAR(DATE(Настройки!$C$6,Настройки!$D$7+0,1))*12+MONTH(DATE(Настройки!$C$6,Настройки!$D$7+0,1)))-(YEAR(IF($I21="",$L$6,$I21))*12+MONTH(IF($I21="",$L$6,$I21))),MAX(1,N($H21)))=0),N($G21),0))),IF(AND(OR($I21="",$I21<=(DATE(Настройки!$C$6,Настройки!$D$7+0+1,1)-1)),OR($J21="",$J21>=DATE(Настройки!$C$6,Настройки!$D$7+0,1)),MOD((YEAR(DATE(Настройки!$C$6,Настройки!$D$7+0,1))*12+MONTH(DATE(Настройки!$C$6,Настройки!$D$7+0,1)))-(YEAR(IF($I21="",$L$6,$I21))*12+MONTH(IF($I21="",$L$6,$I21))),MAX(1,N($H21)))=0),N($G21),0)))
B22: 15 | Y22: =IF(OR($C22="",$F22=""),"",DATE(YEAR($L$6),MONTH($L$6),MIN($F22,DAY((DATE(YEAR($L$6),MONTH($L$6)+1,1)-1))))) | Z22: =IF($C22="","",IF($D22="Доход","Доход","Расход")) | AA22: =IF($C22="","",$E22) | AB22: =IF($C22="",0,IF(AND(OR($I22="",$I22<=(DATE(YEAR($L$6),MONTH($L$6)+1,1)-1)),OR($J22="",$J22>=$L$6),MOD((YEAR($L$6)*12+MONTH($L$6))-(YEAR(IF($I22="",$L$6,$I22))*12+MONTH(IF($I22="",$L$6,$I22))),MAX(1,N($H22)))=0),N($G22),0)) | AC22: =IF($C22="",0,IF(L22="✓",N($G22),IF(ISNUMBER(L22),L22,0))) | AD22: =IF($C22="","",$L$6) | AE22: =IF($C22="","",$K22) | AG22: =IF(OR($C22="",$F22=""),"",DATE(YEAR(DATE(Настройки!$C$6,Настройки!$D$7+0,1)),MONTH(DATE(Настройки!$C$6,Настройки!$D$7+0,1)),MIN($F22,DAY((DATE(Настройки!$C$6,Настройки!$D$7+0+1,1)-1))))) | AH22: =IF($C22="","",IF($D22="Доход","Доход","Расход")) | AI22: =IF($C22="","",$E22) | AJ22: =IF($C22="",0,IF(AND(((YEAR(DATE(Настройки!$C$6,Настройки!$D$7+0,1))*12+MONTH(DATE(Настройки!$C$6,Настройки!$D$7+0,1)))-(YEAR($L$6)*12+MONTH($L$6)))>=0,((YEAR(DATE(Настройки!$C$6,Настройки!$D$7+0,1))*12+MONTH(DATE(Настройки!$C$6,Настройки!$D$7+0,1)))-(YEAR($L$6)*12+MONTH($L$6)))<=11),IF(INDEX($L22:$W22,((YEAR(DATE(Настройки!$C$6,Настройки!$D$7+0,1))*12+MONTH(DATE(Настройки!$C$6,Настройки!$D$7+0,1)))-(YEAR($L$6)*12+MONTH($L$6)))+1)="✓",N($G22),IF(ISNUMBER(INDEX($L22:$W22,((YEAR(DATE(Настройки!$C$6,Настройки!$D$7+0,1))*12+MONTH(DATE(Настройки!$C$6,Настройки!$D$7+0,1)))-(YEAR($L$6)*12+MONTH($L$6)))+1)),INDEX($L22:$W22,((YEAR(DATE(Настройки!$C$6,Настройки!$D$7+0,1))*12+MONTH(DATE(Настройки!$C$6,Настройки!$D$7+0,1)))-(YEAR($L$6)*12+MONTH($L$6)))+1),IF(AND(OR($I22="",$I22<=(DATE(Настройки!$C$6,Настройки!$D$7+0+1,1)-1)),OR($J22="",$J22>=DATE(Настройки!$C$6,Настройки!$D$7+0,1)),MOD((YEAR(DATE(Настройки!$C$6,Настройки!$D$7+0,1))*12+MONTH(DATE(Настройки!$C$6,Настройки!$D$7+0,1)))-(YEAR(IF($I22="",$L$6,$I22))*12+MONTH(IF($I22="",$L$6,$I22))),MAX(1,N($H22)))=0),N($G22),0))),IF(AND(OR($I22="",$I22<=(DATE(Настройки!$C$6,Настройки!$D$7+0+1,1)-1)),OR($J22="",$J22>=DATE(Настройки!$C$6,Настройки!$D$7+0,1)),MOD((YEAR(DATE(Настройки!$C$6,Настройки!$D$7+0,1))*12+MONTH(DATE(Настройки!$C$6,Настройки!$D$7+0,1)))-(YEAR(IF($I22="",$L$6,$I22))*12+MONTH(IF($I22="",$L$6,$I22))),MAX(1,N($H22)))=0),N($G22),0)))
B23: 16 | Y23: =IF(OR($C23="",$F23=""),"",DATE(YEAR($L$6),MONTH($L$6),MIN($F23,DAY((DATE(YEAR($L$6),MONTH($L$6)+1,1)-1))))) | Z23: =IF($C23="","",IF($D23="Доход","Доход","Расход")) | AA23: =IF($C23="","",$E23) | AB23: =IF($C23="",0,IF(AND(OR($I23="",$I23<=(DATE(YEAR($L$6),MONTH($L$6)+1,1)-1)),OR($J23="",$J23>=$L$6),MOD((YEAR($L$6)*12+MONTH($L$6))-(YEAR(IF($I23="",$L$6,$I23))*12+MONTH(IF($I23="",$L$6,$I23))),MAX(1,N($H23)))=0),N($G23),0)) | AC23: =IF($C23="",0,IF(L23="✓",N($G23),IF(ISNUMBER(L23),L23,0))) | AD23: =IF($C23="","",$L$6) | AE23: =IF($C23="","",$K23) | AG23: =IF(OR($C23="",$F23=""),"",DATE(YEAR(DATE(Настройки!$C$6,Настройки!$D$7+0,1)),MONTH(DATE(Настройки!$C$6,Настройки!$D$7+0,1)),MIN($F23,DAY((DATE(Настройки!$C$6,Настройки!$D$7+0+1,1)-1))))) | AH23: =IF($C23="","",IF($D23="Доход","Доход","Расход")) | AI23: =IF($C23="","",$E23) | AJ23: =IF($C23="",0,IF(AND(((YEAR(DATE(Настройки!$C$6,Настройки!$D$7+0,1))*12+MONTH(DATE(Настройки!$C$6,Настройки!$D$7+0,1)))-(YEAR($L$6)*12+MONTH($L$6)))>=0,((YEAR(DATE(Настройки!$C$6,Настройки!$D$7+0,1))*12+MONTH(DATE(Настройки!$C$6,Настройки!$D$7+0,1)))-(YEAR($L$6)*12+MONTH($L$6)))<=11),IF(INDEX($L23:$W23,((YEAR(DATE(Настройки!$C$6,Настройки!$D$7+0,1))*12+MONTH(DATE(Настройки!$C$6,Настройки!$D$7+0,1)))-(YEAR($L$6)*12+MONTH($L$6)))+1)="✓",N($G23),IF(ISNUMBER(INDEX($L23:$W23,((YEAR(DATE(Настройки!$C$6,Настройки!$D$7+0,1))*12+MONTH(DATE(Настройки!$C$6,Настройки!$D$7+0,1)))-(YEAR($L$6)*12+MONTH($L$6)))+1)),INDEX($L23:$W23,((YEAR(DATE(Настройки!$C$6,Настройки!$D$7+0,1))*12+MONTH(DATE(Настройки!$C$6,Настройки!$D$7+0,1)))-(YEAR($L$6)*12+MONTH($L$6)))+1),IF(AND(OR($I23="",$I23<=(DATE(Настройки!$C$6,Настройки!$D$7+0+1,1)-1)),OR($J23="",$J23>=DATE(Настройки!$C$6,Настройки!$D$7+0,1)),MOD((YEAR(DATE(Настройки!$C$6,Настройки!$D$7+0,1))*12+MONTH(DATE(Настройки!$C$6,Настройки!$D$7+0,1)))-(YEAR(IF($I23="",$L$6,$I23))*12+MONTH(IF($I23="",$L$6,$I23))),MAX(1,N($H23)))=0),N($G23),0))),IF(AND(OR($I23="",$I23<=(DATE(Настройки!$C$6,Настройки!$D$7+0+1,1)-1)),OR($J23="",$J23>=DATE(Настройки!$C$6,Настройки!$D$7+0,1)),MOD((YEAR(DATE(Настройки!$C$6,Настройки!$D$7+0,1))*12+MONTH(DATE(Настройки!$C$6,Настройки!$D$7+0,1)))-(YEAR(IF($I23="",$L$6,$I23))*12+MONTH(IF($I23="",$L$6,$I23))),MAX(1,N($H23)))=0),N($G23),0)))
... B37: 30 | Y37: =IF(OR($C37="",$F37=""),"",DATE(YEAR($L$6),MONTH($L$6),MIN($F37,DAY((DATE(YEAR($L$6),MONTH($L$6)+1,1)-1))))) | Z37: =IF($C37="","",IF($D37="Доход","Доход","Расход")) | AA37: =IF($C37="","",$E37) | AB37: =IF($C37="",0,IF(AND(OR($I37="",$I37<=(DATE(YEAR($L$6),MONTH($L$6)+1,1)-1)),OR($J37="",$J37>=$L$6),MOD((YEAR($L$6)*12+MONTH($L$6))-(YEAR(IF($I37="",$L$6,$I37))*12+MONTH(IF($I37="",$L$6,$I37))),MAX(1,N($H37)))=0),N($G37),0)) | AC37: =IF($C37="",0,IF(L37="✓",N($G37),IF(ISNUMBER(L37),L37,0))) | AD37: =IF($C37="","",$L$6) | AE37: =IF($C37="","",$K37) | AG37: =IF(OR($C37="",$F37=""),"",DATE(YEAR(DATE(Настройки!$C$6,Настройки!$D$7+0,1)),MONTH(DATE(Настройки!$C$6,Настройки!$D$7+0,1)),MIN($F37,DAY((DATE(Настройки!$C$6,Настройки!$D$7+0+1,1)-1))))) | AH37: =IF($C37="","",IF($D37="Доход","Доход","Расход")) | AI37: =IF($C37="","",$E37) | AJ37: =IF($C37="",0,IF(AND(((YEAR(DATE(Настройки!$C$6,Настройки!$D$7+0,1))*12+MONTH(DATE(Настройки!$C$6,Настройки!$D$7+0,1)))-(YEAR($L$6)*12+MONTH($L$6)))>=0,((YEAR(DATE(Настройки!$C$6,Настройки!$D$7+0,1))*12+MONTH(DATE(Настройки!$C$6,Настройки!$D$7+0,1)))-(YEAR($L$6)*12+MONTH($L$6)))<=11),IF(INDEX($L37:$W37,((YEAR(DATE(Настройки!$C$6,Настройки!$D$7+0,1))*12+MONTH(DATE(Настройки!$C$6,Настройки!$D$7+0,1)))-(YEAR($L$6)*12+MONTH($L$6)))+1)="✓",N($G37),IF(ISNUMBER(INDEX($L37:$W37,((YEAR(DATE(Настройки!$C$6,Настройки!$D$7+0,1))*12+MONTH(DATE(Настройки!$C$6,Настройки!$D$7+0,1)))-(YEAR($L$6)*12+MONTH($L$6)))+1)),INDEX($L37:$W37,((YEAR(DATE(Настройки!$C$6,Настройки!$D$7+0,1))*12+MONTH(DATE(Настройки!$C$6,Настройки!$D$7+0,1)))-(YEAR($L$6)*12+MONTH($L$6)))+1),IF(AND(OR($I37="",$I37<=(DATE(Настройки!$C$6,Настройки!$D$7+0+1,1)-1)),OR($J37="",$J37>=DATE(Настройки!$C$6,Настройки!$D$7+0,1)),MOD((YEAR(DATE(Настройки!$C$6,Настройки!$D$7+0,1))*12+MONTH(DATE(Настройки!$C$6,Настройки!$D$7+0,1)))-(YEAR(IF($I37="",$L$6,$I37))*12+MONTH(IF($I37="",$L$6,$I37))),MAX(1,N($H37)))=0),N($G37),0))),IF(AND(OR($I37="",$I37<=(DATE(Настройки!$C$6,Настройки!$D$7+0+1,1)-1)),OR($J37="",$J37>=DATE(Настройки!$C$6,Настройки!$D$7+0,1)),MOD((YEAR(DATE(Настройки!$C$6,Настройки!$D$7+0,1))*12+MONTH(DATE(Настройки!$C$6,Настройки!$D$7+0,1)))-(YEAR(IF($I37="",$L$6,$I37))*12+MONTH(IF($I37="",$L$6,$I37))),MAX(1,N($H37)))=0),N($G37),0)))
B38: Оплачено расходов | G38: =SUMPRODUCT(($D$8:$D$37<>"Доход")*$G$8:$G$37/(($H$8:$H$37<=1)+($H$8:$H$37>1)*$H$8:$H$37)) | H38: ← в среднем в месяц | L38: =SUMIFS(Постоянные!$AC$8:$AC$367,Постоянные!$Z$8:$Z$367,"Расход",Постоянные!$AD$8:$AD$367,L$6) | M38: =SUMIFS(Постоянные!$AC$8:$AC$367,Постоянные!$Z$8:$Z$367,"Расход",Постоянные!$AD$8:$AD$367,M$6) | N38: =SUMIFS(Постоянные!$AC$8:$AC$367,Постоянные!$Z$8:$Z$367,"Расход",Постоянные!$AD$8:$AD$367,N$6) | O38: =SUMIFS(Постоянные!$AC$8:$AC$367,Постоянные!$Z$8:$Z$367,"Расход",Постоянные!$AD$8:$AD$367,O$6) | P38: =SUMIFS(Постоянные!$AC$8:$AC$367,Постоянные!$Z$8:$Z$367,"Расход",Постоянные!$AD$8:$AD$367,P$6) | Q38: =SUMIFS(Постоянные!$AC$8:$AC$367,Постоянные!$Z$8:$Z$367,"Расход",Постоянные!$AD$8:$AD$367,Q$6) | R38: =SUMIFS(Постоянные!$AC$8:$AC$367,Постоянные!$Z$8:$Z$367,"Расход",Постоянные!$AD$8:$AD$367,R$6) | S38: =SUMIFS(Постоянные!$AC$8:$AC$367,Постоянные!$Z$8:$Z$367,"Расход",Постоянные!$AD$8:$AD$367,S$6) | ... W38: =SUMIFS(Постоянные!$AC$8:$AC$367,Постоянные!$Z$8:$Z$367,"Расход",Постоянные!$AD$8:$AD$367,W$6) | Y38: =IF(OR($C8="",$F8=""),"",DATE(YEAR($M$6),MONTH($M$6),MIN($F8,DAY((DATE(YEAR($M$6),MONTH($M$6)+1,1)-1))))) | Z38: =IF($C8="","",IF($D8="Доход","Доход","Расход")) | AA38: =IF($C8="","",$E8) | AB38: =IF($C8="",0,IF(AND(OR($I8="",$I8<=(DATE(YEAR($M$6),MONTH($M$6)+1,1)-1)),OR($J8="",$J8>=$M$6),MOD((YEAR($M$6)*12+MONTH($M$6))-(YEAR(IF($I8="",$L$6,$I8))*12+MONTH(IF($I8="",$L$6,$I8))),MAX(1,N($H8)))=0),N($G8),0)) | AC38: =IF($C8="",0,IF(M8="✓",N($G8),IF(ISNUMBER(M8),M8,0))) | AD38: =IF($C8="","",$M$6) | AE38: =IF($C8="","",$K8) | AG38: =IF(OR($C8="",$F8=""),"",DATE(YEAR(DATE(Настройки!$C$6,Настройки!$D$7+1,1)),MONTH(DATE(Настройки!$C$6,Настройки!$D$7+1,1)),MIN($F8,DAY((DATE(Настройки!$C$6,Настройки!$D$7+1+1,1)-1))))) | AH38: =IF($C8="","",IF($D8="Доход","Доход","Расход")) | AI38: =IF($C8="","",$E8) | AJ38: =IF($C8="",0,IF(AND(((YEAR(DATE(Настройки!$C$6,Настройки!$D$7+1,1))*12+MONTH(DATE(Настройки!$C$6,Настройки!$D$7+1,1)))-(YEAR($L$6)*12+MONTH($L$6)))>=0,((YEAR(DATE(Настройки!$C$6,Настройки!$D$7+1,1))*12+MONTH(DATE(Настройки!$C$6,Настройки!$D$7+1,1)))-(YEAR($L$6)*12+MONTH($L$6)))<=11),IF(INDEX($L8:$W8,((YEAR(DATE(Настройки!$C$6,Настройки!$D$7+1,1))*12+MONTH(DATE(Настройки!$C$6,Настройки!$D$7+1,1)))-(YEAR($L$6)*12+MONTH($L$6)))+1)="✓",N($G8),IF(ISNUMBER(INDEX($L8:$W8,((YEAR(DATE(Настройки!$C$6,Настройки!$D$7+1,1))*12+MONTH(DATE(Настройки!$C$6,Настройки!$D$7+1,1)))-(YEAR($L$6)*12+MONTH($L$6)))+1)),INDEX($L8:$W8,((YEAR(DATE(Настройки!$C$6,Настройки!$D$7+1,1))*12+MONTH(DATE(Настройки!$C$6,Настройки!$D$7+1,1)))-(YEAR($L$6)*12+MONTH($L$6)))+1),IF(AND(OR($I8="",$I8<=(DATE(Настройки!$C$6,Настройки!$D$7+1+1,1)-1)),OR($J8="",$J8>=DATE(Настройки!$C$6,Настройки!$D$7+1,1)),MOD((YEAR(DATE(Настройки!$C$6,Настройки!$D$7+1,1))*12+MONTH(DATE(Настройки!$C$6,Настройки!$D$7+1,1)))-(YEAR(IF($I8="",$L$6,$I8))*12+MONTH(IF($I8="",$L$6,$I8))),MAX(1,N($H8)))=0),N($G8),0))),IF(AND(OR($I8="",$I8<=(DATE(Настройки!$C$6,Настройки!$D$7+1+1,1)-1)),OR($J8="",$J8>=DATE(Настройки!$C$6,Настройки!$D$7+1,1)),MOD((YEAR(DATE(Настройки!$C$6,Настройки!$D$7+1,1))*12+MONTH(DATE(Настройки!$C$6,Настройки!$D$7+1,1)))-(YEAR(IF($I8="",$L$6,$I8))*12+MONTH(IF($I8="",$L$6,$I8))),MAX(1,N($H8)))=0),N($G8),0)))
B39: Получено доходов | G39: =SUMPRODUCT(($D$8:$D$37="Доход")*$G$8:$G$37/(($H$8:$H$37<=1)+($H$8:$H$37>1)*$H$8:$H$37)) | L39: =SUMIFS(Постоянные!$AC$8:$AC$367,Постоянные!$Z$8:$Z$367,"Доход",Постоянные!$AD$8:$AD$367,L$6) | M39: =SUMIFS(Постоянные!$AC$8:$AC$367,Постоянные!$Z$8:$Z$367,"Доход",Постоянные!$AD$8:$AD$367,M$6) | N39: =SUMIFS(Постоянные!$AC$8:$AC$367,Постоянные!$Z$8:$Z$367,"Доход",Постоянные!$AD$8:$AD$367,N$6) | O39: =SUMIFS(Постоянные!$AC$8:$AC$367,Постоянные!$Z$8:$Z$367,"Доход",Постоянные!$AD$8:$AD$367,O$6) | P39: =SUMIFS(Постоянные!$AC$8:$AC$367,Постоянные!$Z$8:$Z$367,"Доход",Постоянные!$AD$8:$AD$367,P$6) | Q39: =SUMIFS(Постоянные!$AC$8:$AC$367,Постоянные!$Z$8:$Z$367,"Доход",Постоянные!$AD$8:$AD$367,Q$6) | R39: =SUMIFS(Постоянные!$AC$8:$AC$367,Постоянные!$Z$8:$Z$367,"Доход",Постоянные!$AD$8:$AD$367,R$6) | S39: =SUMIFS(Постоянные!$AC$8:$AC$367,Постоянные!$Z$8:$Z$367,"Доход",Постоянные!$AD$8:$AD$367,S$6) | ... W39: =SUMIFS(Постоянные!$AC$8:$AC$367,Постоянные!$Z$8:$Z$367,"Доход",Постоянные!$AD$8:$AD$367,W$6) | Y39: =IF(OR($C9="",$F9=""),"",DATE(YEAR($M$6),MONTH($M$6),MIN($F9,DAY((DATE(YEAR($M$6),MONTH($M$6)+1,1)-1))))) | Z39: =IF($C9="","",IF($D9="Доход","Доход","Расход")) | AA39: =IF($C9="","",$E9) | AB39: =IF($C9="",0,IF(AND(OR($I9="",$I9<=(DATE(YEAR($M$6),MONTH($M$6)+1,1)-1)),OR($J9="",$J9>=$M$6),MOD((YEAR($M$6)*12+MONTH($M$6))-(YEAR(IF($I9="",$L$6,$I9))*12+MONTH(IF($I9="",$L$6,$I9))),MAX(1,N($H9)))=0),N($G9),0)) | AC39: =IF($C9="",0,IF(M9="✓",N($G9),IF(ISNUMBER(M9),M9,0))) | AD39: =IF($C9="","",$M$6) | AE39: =IF($C9="","",$K9) | AG39: =IF(OR($C9="",$F9=""),"",DATE(YEAR(DATE(Настройки!$C$6,Настройки!$D$7+1,1)),MONTH(DATE(Настройки!$C$6,Настройки!$D$7+1,1)),MIN($F9,DAY((DATE(Настройки!$C$6,Настройки!$D$7+1+1,1)-1))))) | AH39: =IF($C9="","",IF($D9="Доход","Доход","Расход")) | AI39: =IF($C9="","",$E9) | AJ39: =IF($C9="",0,IF(AND(((YEAR(DATE(Настройки!$C$6,Настройки!$D$7+1,1))*12+MONTH(DATE(Настройки!$C$6,Настройки!$D$7+1,1)))-(YEAR($L$6)*12+MONTH($L$6)))>=0,((YEAR(DATE(Настройки!$C$6,Настройки!$D$7+1,1))*12+MONTH(DATE(Настройки!$C$6,Настройки!$D$7+1,1)))-(YEAR($L$6)*12+MONTH($L$6)))<=11),IF(INDEX($L9:$W9,((YEAR(DATE(Настройки!$C$6,Настройки!$D$7+1,1))*12+MONTH(DATE(Настройки!$C$6,Настройки!$D$7+1,1)))-(YEAR($L$6)*12+MONTH($L$6)))+1)="✓",N($G9),IF(ISNUMBER(INDEX($L9:$W9,((YEAR(DATE(Настройки!$C$6,Настройки!$D$7+1,1))*12+MONTH(DATE(Настройки!$C$6,Настройки!$D$7+1,1)))-(YEAR($L$6)*12+MONTH($L$6)))+1)),INDEX($L9:$W9,((YEAR(DATE(Настройки!$C$6,Настройки!$D$7+1,1))*12+MONTH(DATE(Настройки!$C$6,Настройки!$D$7+1,1)))-(YEAR($L$6)*12+MONTH($L$6)))+1),IF(AND(OR($I9="",$I9<=(DATE(Настройки!$C$6,Настройки!$D$7+1+1,1)-1)),OR($J9="",$J9>=DATE(Настройки!$C$6,Настройки!$D$7+1,1)),MOD((YEAR(DATE(Настройки!$C$6,Настройки!$D$7+1,1))*12+MONTH(DATE(Настройки!$C$6,Настройки!$D$7+1,1)))-(YEAR(IF($I9="",$L$6,$I9))*12+MONTH(IF($I9="",$L$6,$I9))),MAX(1,N($H9)))=0),N($G9),0))),IF(AND(OR($I9="",$I9<=(DATE(Настройки!$C$6,Настройки!$D$7+1+1,1)-1)),OR($J9="",$J9>=DATE(Настройки!$C$6,Настройки!$D$7+1,1)),MOD((YEAR(DATE(Настройки!$C$6,Настройки!$D$7+1,1))*12+MONTH(DATE(Настройки!$C$6,Настройки!$D$7+1,1)))-(YEAR(IF($I9="",$L$6,$I9))*12+MONTH(IF($I9="",$L$6,$I9))),MAX(1,N($H9)))=0),N($G9),0)))
Y40: =IF(OR($C10="",$F10=""),"",DATE(YEAR($M$6),MONTH($M$6),MIN($F10,DAY((DATE(YEAR($M$6),MONTH($M$6)+1,1)-1))))) | Z40: =IF($C10="","",IF($D10="Доход","Доход","Расход")) | AA40: =IF($C10="","",$E10) | AB40: =IF($C10="",0,IF(AND(OR($I10="",$I10<=(DATE(YEAR($M$6),MONTH($M$6)+1,1)-1)),OR($J10="",$J10>=$M$6),MOD((YEAR($M$6)*12+MONTH($M$6))-(YEAR(IF($I10="",$L$6,$I10))*12+MONTH(IF($I10="",$L$6,$I10))),MAX(1,N($H10)))=0),N($G10),0)) | AC40: =IF($C10="",0,IF(M10="✓",N($G10),IF(ISNUMBER(M10),M10,0))) | AD40: =IF($C10="","",$M$6) | AE40: =IF($C10="","",$K10) | AG40: =IF(OR($C10="",$F10=""),"",DATE(YEAR(DATE(Настройки!$C$6,Настройки!$D$7+1,1)),MONTH(DATE(Настройки!$C$6,Настройки!$D$7+1,1)),MIN($F10,DAY((DATE(Настройки!$C$6,Настройки!$D$7+1+1,1)-1))))) | AH40: =IF($C10="","",IF($D10="Доход","Доход","Расход")) | AI40: =IF($C10="","",$E10) | AJ40: =IF($C10="",0,IF(AND(((YEAR(DATE(Настройки!$C$6,Настройки!$D$7+1,1))*12+MONTH(DATE(Настройки!$C$6,Настройки!$D$7+1,1)))-(YEAR($L$6)*12+MONTH($L$6)))>=0,((YEAR(DATE(Настройки!$C$6,Настройки!$D$7+1,1))*12+MONTH(DATE(Настройки!$C$6,Настройки!$D$7+1,1)))-(YEAR($L$6)*12+MONTH($L$6)))<=11),IF(INDEX($L10:$W10,((YEAR(DATE(Настройки!$C$6,Настройки!$D$7+1,1))*12+MONTH(DATE(Настройки!$C$6,Настройки!$D$7+1,1)))-(YEAR($L$6)*12+MONTH($L$6)))+1)="✓",N($G10),IF(ISNUMBER(INDEX($L10:$W10,((YEAR(DATE(Настройки!$C$6,Настройки!$D$7+1,1))*12+MONTH(DATE(Настройки!$C$6,Настройки!$D$7+1,1)))-(YEAR($L$6)*12+MONTH($L$6)))+1)),INDEX($L10:$W10,((YEAR(DATE(Настройки!$C$6,Настройки!$D$7+1,1))*12+MONTH(DATE(Настройки!$C$6,Настройки!$D$7+1,1)))-(YEAR($L$6)*12+MONTH($L$6)))+1),IF(AND(OR($I10="",$I10<=(DATE(Настройки!$C$6,Настройки!$D$7+1+1,1)-1)),OR($J10="",$J10>=DATE(Настройки!$C$6,Настройки!$D$7+1,1)),MOD((YEAR(DATE(Настройки!$C$6,Настройки!$D$7+1,1))*12+MONTH(DATE(Настройки!$C$6,Настройки!$D$7+1,1)))-(YEAR(IF($I10="",$L$6,$I10))*12+MONTH(IF($I10="",$L$6,$I10))),MAX(1,N($H10)))=0),N($G10),0))),IF(AND(OR($I10="",$I10<=(DATE(Настройки!$C$6,Настройки!$D$7+1+1,1)-1)),OR($J10="",$J10>=DATE(Настройки!$C$6,Настройки!$D$7+1,1)),MOD((YEAR(DATE(Настройки!$C$6,Настройки!$D$7+1,1))*12+MONTH(DATE(Настройки!$C$6,Настройки!$D$7+1,1)))-(YEAR(IF($I10="",$L$6,$I10))*12+MONTH(IF($I10="",$L$6,$I10))),MAX(1,N($H10)))=0),N($G10),0)))
Y41: =IF(OR($C11="",$F11=""),"",DATE(YEAR($M$6),MONTH($M$6),MIN($F11,DAY((DATE(YEAR($M$6),MONTH($M$6)+1,1)-1))))) | Z41: =IF($C11="","",IF($D11="Доход","Доход","Расход")) | AA41: =IF($C11="","",$E11) | AB41: =IF($C11="",0,IF(AND(OR($I11="",$I11<=(DATE(YEAR($M$6),MONTH($M$6)+1,1)-1)),OR($J11="",$J11>=$M$6),MOD((YEAR($M$6)*12+MONTH($M$6))-(YEAR(IF($I11="",$L$6,$I11))*12+MONTH(IF($I11="",$L$6,$I11))),MAX(1,N($H11)))=0),N($G11),0)) | AC41: =IF($C11="",0,IF(M11="✓",N($G11),IF(ISNUMBER(M11),M11,0))) | AD41: =IF($C11="","",$M$6) | AE41: =IF($C11="","",$K11) | AG41: =IF(OR($C11="",$F11=""),"",DATE(YEAR(DATE(Настройки!$C$6,Настройки!$D$7+1,1)),MONTH(DATE(Настройки!$C$6,Настройки!$D$7+1,1)),MIN($F11,DAY((DATE(Настройки!$C$6,Настройки!$D$7+1+1,1)-1))))) | AH41: =IF($C11="","",IF($D11="Доход","Доход","Расход")) | AI41: =IF($C11="","",$E11) | AJ41: =IF($C11="",0,IF(AND(((YEAR(DATE(Настройки!$C$6,Настройки!$D$7+1,1))*12+MONTH(DATE(Настройки!$C$6,Настройки!$D$7+1,1)))-(YEAR($L$6)*12+MONTH($L$6)))>=0,((YEAR(DATE(Настройки!$C$6,Настройки!$D$7+1,1))*12+MONTH(DATE(Настройки!$C$6,Настройки!$D$7+1,1)))-(YEAR($L$6)*12+MONTH($L$6)))<=11),IF(INDEX($L11:$W11,((YEAR(DATE(Настройки!$C$6,Настройки!$D$7+1,1))*12+MONTH(DATE(Настройки!$C$6,Настройки!$D$7+1,1)))-(YEAR($L$6)*12+MONTH($L$6)))+1)="✓",N($G11),IF(ISNUMBER(INDEX($L11:$W11,((YEAR(DATE(Настройки!$C$6,Настройки!$D$7+1,1))*12+MONTH(DATE(Настройки!$C$6,Настройки!$D$7+1,1)))-(YEAR($L$6)*12+MONTH($L$6)))+1)),INDEX($L11:$W11,((YEAR(DATE(Настройки!$C$6,Настройки!$D$7+1,1))*12+MONTH(DATE(Настройки!$C$6,Настройки!$D$7+1,1)))-(YEAR($L$6)*12+MONTH($L$6)))+1),IF(AND(OR($I11="",$I11<=(DATE(Настройки!$C$6,Настройки!$D$7+1+1,1)-1)),OR($J11="",$J11>=DATE(Настройки!$C$6,Настройки!$D$7+1,1)),MOD((YEAR(DATE(Настройки!$C$6,Настройки!$D$7+1,1))*12+MONTH(DATE(Настройки!$C$6,Настройки!$D$7+1,1)))-(YEAR(IF($I11="",$L$6,$I11))*12+MONTH(IF($I11="",$L$6,$I11))),MAX(1,N($H11)))=0),N($G11),0))),IF(AND(OR($I11="",$I11<=(DATE(Настройки!$C$6,Настройки!$D$7+1+1,1)-1)),OR($J11="",$J11>=DATE(Настройки!$C$6,Настройки!$D$7+1,1)),MOD((YEAR(DATE(Настройки!$C$6,Настройки!$D$7+1,1))*12+MONTH(DATE(Настройки!$C$6,Настройки!$D$7+1,1)))-(YEAR(IF($I11="",$L$6,$I11))*12+MONTH(IF($I11="",$L$6,$I11))),MAX(1,N($H11)))=0),N($G11),0)))
Y42: =IF(OR($C12="",$F12=""),"",DATE(YEAR($M$6),MONTH($M$6),MIN($F12,DAY((DATE(YEAR($M$6),MONTH($M$6)+1,1)-1))))) | Z42: =IF($C12="","",IF($D12="Доход","Доход","Расход")) | AA42: =IF($C12="","",$E12) | AB42: =IF($C12="",0,IF(AND(OR($I12="",$I12<=(DATE(YEAR($M$6),MONTH($M$6)+1,1)-1)),OR($J12="",$J12>=$M$6),MOD((YEAR($M$6)*12+MONTH($M$6))-(YEAR(IF($I12="",$L$6,$I12))*12+MONTH(IF($I12="",$L$6,$I12))),MAX(1,N($H12)))=0),N($G12),0)) | AC42: =IF($C12="",0,IF(M12="✓",N($G12),IF(ISNUMBER(M12),M12,0))) | AD42: =IF($C12="","",$M$6) | AE42: =IF($C12="","",$K12) | AG42: =IF(OR($C12="",$F12=""),"",DATE(YEAR(DATE(Настройки!$C$6,Настройки!$D$7+1,1)),MONTH(DATE(Настройки!$C$6,Настройки!$D$7+1,1)),MIN($F12,DAY((DATE(Настройки!$C$6,Настройки!$D$7+1+1,1)-1))))) | AH42: =IF($C12="","",IF($D12="Доход","Доход","Расход")) | AI42: =IF($C12="","",$E12) | AJ42: =IF($C12="",0,IF(AND(((YEAR(DATE(Настройки!$C$6,Настройки!$D$7+1,1))*12+MONTH(DATE(Настройки!$C$6,Настройки!$D$7+1,1)))-(YEAR($L$6)*12+MONTH($L$6)))>=0,((YEAR(DATE(Настройки!$C$6,Настройки!$D$7+1,1))*12+MONTH(DATE(Настройки!$C$6,Настройки!$D$7+1,1)))-(YEAR($L$6)*12+MONTH($L$6)))<=11),IF(INDEX($L12:$W12,((YEAR(DATE(Настройки!$C$6,Настройки!$D$7+1,1))*12+MONTH(DATE(Настройки!$C$6,Настройки!$D$7+1,1)))-(YEAR($L$6)*12+MONTH($L$6)))+1)="✓",N($G12),IF(ISNUMBER(INDEX($L12:$W12,((YEAR(DATE(Настройки!$C$6,Настройки!$D$7+1,1))*12+MONTH(DATE(Настройки!$C$6,Настройки!$D$7+1,1)))-(YEAR($L$6)*12+MONTH($L$6)))+1)),INDEX($L12:$W12,((YEAR(DATE(Настройки!$C$6,Настройки!$D$7+1,1))*12+MONTH(DATE(Настройки!$C$6,Настройки!$D$7+1,1)))-(YEAR($L$6)*12+MONTH($L$6)))+1),IF(AND(OR($I12="",$I12<=(DATE(Настройки!$C$6,Настройки!$D$7+1+1,1)-1)),OR($J12="",$J12>=DATE(Настройки!$C$6,Настройки!$D$7+1,1)),MOD((YEAR(DATE(Настройки!$C$6,Настройки!$D$7+1,1))*12+MONTH(DATE(Настройки!$C$6,Настройки!$D$7+1,1)))-(YEAR(IF($I12="",$L$6,$I12))*12+MONTH(IF($I12="",$L$6,$I12))),MAX(1,N($H12)))=0),N($G12),0))),IF(AND(OR($I12="",$I12<=(DATE(Настройки!$C$6,Настройки!$D$7+1+1,1)-1)),OR($J12="",$J12>=DATE(Настройки!$C$6,Настройки!$D$7+1,1)),MOD((YEAR(DATE(Настройки!$C$6,Настройки!$D$7+1,1))*12+MONTH(DATE(Настройки!$C$6,Настройки!$D$7+1,1)))-(YEAR(IF($I12="",$L$6,$I12))*12+MONTH(IF($I12="",$L$6,$I12))),MAX(1,N($H12)))=0),N($G12),0)))
Y43: =IF(OR($C13="",$F13=""),"",DATE(YEAR($M$6),MONTH($M$6),MIN($F13,DAY((DATE(YEAR($M$6),MONTH($M$6)+1,1)-1))))) | Z43: =IF($C13="","",IF($D13="Доход","Доход","Расход")) | AA43: =IF($C13="","",$E13) | AB43: =IF($C13="",0,IF(AND(OR($I13="",$I13<=(DATE(YEAR($M$6),MONTH($M$6)+1,1)-1)),OR($J13="",$J13>=$M$6),MOD((YEAR($M$6)*12+MONTH($M$6))-(YEAR(IF($I13="",$L$6,$I13))*12+MONTH(IF($I13="",$L$6,$I13))),MAX(1,N($H13)))=0),N($G13),0)) | AC43: =IF($C13="",0,IF(M13="✓",N($G13),IF(ISNUMBER(M13),M13,0))) | AD43: =IF($C13="","",$M$6) | AE43: =IF($C13="","",$K13) | AG43: =IF(OR($C13="",$F13=""),"",DATE(YEAR(DATE(Настройки!$C$6,Настройки!$D$7+1,1)),MONTH(DATE(Настройки!$C$6,Настройки!$D$7+1,1)),MIN($F13,DAY((DATE(Настройки!$C$6,Настройки!$D$7+1+1,1)-1))))) | AH43: =IF($C13="","",IF($D13="Доход","Доход","Расход")) | AI43: =IF($C13="","",$E13) | AJ43: =IF($C13="",0,IF(AND(((YEAR(DATE(Настройки!$C$6,Настройки!$D$7+1,1))*12+MONTH(DATE(Настройки!$C$6,Настройки!$D$7+1,1)))-(YEAR($L$6)*12+MONTH($L$6)))>=0,((YEAR(DATE(Настройки!$C$6,Настройки!$D$7+1,1))*12+MONTH(DATE(Настройки!$C$6,Настройки!$D$7+1,1)))-(YEAR($L$6)*12+MONTH($L$6)))<=11),IF(INDEX($L13:$W13,((YEAR(DATE(Настройки!$C$6,Настройки!$D$7+1,1))*12+MONTH(DATE(Настройки!$C$6,Настройки!$D$7+1,1)))-(YEAR($L$6)*12+MONTH($L$6)))+1)="✓",N($G13),IF(ISNUMBER(INDEX($L13:$W13,((YEAR(DATE(Настройки!$C$6,Настройки!$D$7+1,1))*12+MONTH(DATE(Настройки!$C$6,Настройки!$D$7+1,1)))-(YEAR($L$6)*12+MONTH($L$6)))+1)),INDEX($L13:$W13,((YEAR(DATE(Настройки!$C$6,Настройки!$D$7+1,1))*12+MONTH(DATE(Настройки!$C$6,Настройки!$D$7+1,1)))-(YEAR($L$6)*12+MONTH($L$6)))+1),IF(AND(OR($I13="",$I13<=(DATE(Настройки!$C$6,Настройки!$D$7+1+1,1)-1)),OR($J13="",$J13>=DATE(Настройки!$C$6,Настройки!$D$7+1,1)),MOD((YEAR(DATE(Настройки!$C$6,Настройки!$D$7+1,1))*12+MONTH(DATE(Настройки!$C$6,Настройки!$D$7+1,1)))-(YEAR(IF($I13="",$L$6,$I13))*12+MONTH(IF($I13="",$L$6,$I13))),MAX(1,N($H13)))=0),N($G13),0))),IF(AND(OR($I13="",$I13<=(DATE(Настройки!$C$6,Настройки!$D$7+1+1,1)-1)),OR($J13="",$J13>=DATE(Настройки!$C$6,Настройки!$D$7+1,1)),MOD((YEAR(DATE(Настройки!$C$6,Настройки!$D$7+1,1))*12+MONTH(DATE(Настройки!$C$6,Настройки!$D$7+1,1)))-(YEAR(IF($I13="",$L$6,$I13))*12+MONTH(IF($I13="",$L$6,$I13))),MAX(1,N($H13)))=0),N($G13),0)))
Y44: =IF(OR($C14="",$F14=""),"",DATE(YEAR($M$6),MONTH($M$6),MIN($F14,DAY((DATE(YEAR($M$6),MONTH($M$6)+1,1)-1))))) | Z44: =IF($C14="","",IF($D14="Доход","Доход","Расход")) | AA44: =IF($C14="","",$E14) | AB44: =IF($C14="",0,IF(AND(OR($I14="",$I14<=(DATE(YEAR($M$6),MONTH($M$6)+1,1)-1)),OR($J14="",$J14>=$M$6),MOD((YEAR($M$6)*12+MONTH($M$6))-(YEAR(IF($I14="",$L$6,$I14))*12+MONTH(IF($I14="",$L$6,$I14))),MAX(1,N($H14)))=0),N($G14),0)) | AC44: =IF($C14="",0,IF(M14="✓",N($G14),IF(ISNUMBER(M14),M14,0))) | AD44: =IF($C14="","",$M$6) | AE44: =IF($C14="","",$K14) | AG44: =IF(OR($C14="",$F14=""),"",DATE(YEAR(DATE(Настройки!$C$6,Настройки!$D$7+1,1)),MONTH(DATE(Настройки!$C$6,Настройки!$D$7+1,1)),MIN($F14,DAY((DATE(Настройки!$C$6,Настройки!$D$7+1+1,1)-1))))) | AH44: =IF($C14="","",IF($D14="Доход","Доход","Расход")) | AI44: =IF($C14="","",$E14) | AJ44: =IF($C14="",0,IF(AND(((YEAR(DATE(Настройки!$C$6,Настройки!$D$7+1,1))*12+MONTH(DATE(Настройки!$C$6,Настройки!$D$7+1,1)))-(YEAR($L$6)*12+MONTH($L$6)))>=0,((YEAR(DATE(Настройки!$C$6,Настройки!$D$7+1,1))*12+MONTH(DATE(Настройки!$C$6,Настройки!$D$7+1,1)))-(YEAR($L$6)*12+MONTH($L$6)))<=11),IF(INDEX($L14:$W14,((YEAR(DATE(Настройки!$C$6,Настройки!$D$7+1,1))*12+MONTH(DATE(Настройки!$C$6,Настройки!$D$7+1,1)))-(YEAR($L$6)*12+MONTH($L$6)))+1)="✓",N($G14),IF(ISNUMBER(INDEX($L14:$W14,((YEAR(DATE(Настройки!$C$6,Настройки!$D$7+1,1))*12+MONTH(DATE(Настройки!$C$6,Настройки!$D$7+1,1)))-(YEAR($L$6)*12+MONTH($L$6)))+1)),INDEX($L14:$W14,((YEAR(DATE(Настройки!$C$6,Настройки!$D$7+1,1))*12+MONTH(DATE(Настройки!$C$6,Настройки!$D$7+1,1)))-(YEAR($L$6)*12+MONTH($L$6)))+1),IF(AND(OR($I14="",$I14<=(DATE(Настройки!$C$6,Настройки!$D$7+1+1,1)-1)),OR($J14="",$J14>=DATE(Настройки!$C$6,Настройки!$D$7+1,1)),MOD((YEAR(DATE(Настройки!$C$6,Настройки!$D$7+1,1))*12+MONTH(DATE(Настройки!$C$6,Настройки!$D$7+1,1)))-(YEAR(IF($I14="",$L$6,$I14))*12+MONTH(IF($I14="",$L$6,$I14))),MAX(1,N($H14)))=0),N($G14),0))),IF(AND(OR($I14="",$I14<=(DATE(Настройки!$C$6,Настройки!$D$7+1+1,1)-1)),OR($J14="",$J14>=DATE(Настройки!$C$6,Настройки!$D$7+1,1)),MOD((YEAR(DATE(Настройки!$C$6,Настройки!$D$7+1,1))*12+MONTH(DATE(Настройки!$C$6,Настройки!$D$7+1,1)))-(YEAR(IF($I14="",$L$6,$I14))*12+MONTH(IF($I14="",$L$6,$I14))),MAX(1,N($H14)))=0),N($G14),0)))
Y45: =IF(OR($C15="",$F15=""),"",DATE(YEAR($M$6),MONTH($M$6),MIN($F15,DAY((DATE(YEAR($M$6),MONTH($M$6)+1,1)-1))))) | Z45: =IF($C15="","",IF($D15="Доход","Доход","Расход")) | AA45: =IF($C15="","",$E15) | AB45: =IF($C15="",0,IF(AND(OR($I15="",$I15<=(DATE(YEAR($M$6),MONTH($M$6)+1,1)-1)),OR($J15="",$J15>=$M$6),MOD((YEAR($M$6)*12+MONTH($M$6))-(YEAR(IF($I15="",$L$6,$I15))*12+MONTH(IF($I15="",$L$6,$I15))),MAX(1,N($H15)))=0),N($G15),0)) | AC45: =IF($C15="",0,IF(M15="✓",N($G15),IF(ISNUMBER(M15),M15,0))) | AD45: =IF($C15="","",$M$6) | AE45: =IF($C15="","",$K15) | AG45: =IF(OR($C15="",$F15=""),"",DATE(YEAR(DATE(Настройки!$C$6,Настройки!$D$7+1,1)),MONTH(DATE(Настройки!$C$6,Настройки!$D$7+1,1)),MIN($F15,DAY((DATE(Настройки!$C$6,Настройки!$D$7+1+1,1)-1))))) | AH45: =IF($C15="","",IF($D15="Доход","Доход","Расход")) | AI45: =IF($C15="","",$E15) | AJ45: =IF($C15="",0,IF(AND(((YEAR(DATE(Настройки!$C$6,Настройки!$D$7+1,1))*12+MONTH(DATE(Настройки!$C$6,Настройки!$D$7+1,1)))-(YEAR($L$6)*12+MONTH($L$6)))>=0,((YEAR(DATE(Настройки!$C$6,Настройки!$D$7+1,1))*12+MONTH(DATE(Настройки!$C$6,Настройки!$D$7+1,1)))-(YEAR($L$6)*12+MONTH($L$6)))<=11),IF(INDEX($L15:$W15,((YEAR(DATE(Настройки!$C$6,Настройки!$D$7+1,1))*12+MONTH(DATE(Настройки!$C$6,Настройки!$D$7+1,1)))-(YEAR($L$6)*12+MONTH($L$6)))+1)="✓",N($G15),IF(ISNUMBER(INDEX($L15:$W15,((YEAR(DATE(Настройки!$C$6,Настройки!$D$7+1,1))*12+MONTH(DATE(Настройки!$C$6,Настройки!$D$7+1,1)))-(YEAR($L$6)*12+MONTH($L$6)))+1)),INDEX($L15:$W15,((YEAR(DATE(Настройки!$C$6,Настройки!$D$7+1,1))*12+MONTH(DATE(Настройки!$C$6,Настройки!$D$7+1,1)))-(YEAR($L$6)*12+MONTH($L$6)))+1),IF(AND(OR($I15="",$I15<=(DATE(Настройки!$C$6,Настройки!$D$7+1+1,1)-1)),OR($J15="",$J15>=DATE(Настройки!$C$6,Настройки!$D$7+1,1)),MOD((YEAR(DATE(Настройки!$C$6,Настройки!$D$7+1,1))*12+MONTH(DATE(Настройки!$C$6,Настройки!$D$7+1,1)))-(YEAR(IF($I15="",$L$6,$I15))*12+MONTH(IF($I15="",$L$6,$I15))),MAX(1,N($H15)))=0),N($G15),0))),IF(AND(OR($I15="",$I15<=(DATE(Настройки!$C$6,Настройки!$D$7+1+1,1)-1)),OR($J15="",$J15>=DATE(Настройки!$C$6,Настройки!$D$7+1,1)),MOD((YEAR(DATE(Настройки!$C$6,Настройки!$D$7+1,1))*12+MONTH(DATE(Настройки!$C$6,Настройки!$D$7+1,1)))-(YEAR(IF($I15="",$L$6,$I15))*12+MONTH(IF($I15="",$L$6,$I15))),MAX(1,N($H15)))=0),N($G15),0)))
Y46: =IF(OR($C16="",$F16=""),"",DATE(YEAR($M$6),MONTH($M$6),MIN($F16,DAY((DATE(YEAR($M$6),MONTH($M$6)+1,1)-1))))) | Z46: =IF($C16="","",IF($D16="Доход","Доход","Расход")) | AA46: =IF($C16="","",$E16) | AB46: =IF($C16="",0,IF(AND(OR($I16="",$I16<=(DATE(YEAR($M$6),MONTH($M$6)+1,1)-1)),OR($J16="",$J16>=$M$6),MOD((YEAR($M$6)*12+MONTH($M$6))-(YEAR(IF($I16="",$L$6,$I16))*12+MONTH(IF($I16="",$L$6,$I16))),MAX(1,N($H16)))=0),N($G16),0)) | AC46: =IF($C16="",0,IF(M16="✓",N($G16),IF(ISNUMBER(M16),M16,0))) | AD46: =IF($C16="","",$M$6) | AE46: =IF($C16="","",$K16) | AG46: =IF(OR($C16="",$F16=""),"",DATE(YEAR(DATE(Настройки!$C$6,Настройки!$D$7+1,1)),MONTH(DATE(Настройки!$C$6,Настройки!$D$7+1,1)),MIN($F16,DAY((DATE(Настройки!$C$6,Настройки!$D$7+1+1,1)-1))))) | AH46: =IF($C16="","",IF($D16="Доход","Доход","Расход")) | AI46: =IF($C16="","",$E16) | AJ46: =IF($C16="",0,IF(AND(((YEAR(DATE(Настройки!$C$6,Настройки!$D$7+1,1))*12+MONTH(DATE(Настройки!$C$6,Настройки!$D$7+1,1)))-(YEAR($L$6)*12+MONTH($L$6)))>=0,((YEAR(DATE(Настройки!$C$6,Настройки!$D$7+1,1))*12+MONTH(DATE(Настройки!$C$6,Настройки!$D$7+1,1)))-(YEAR($L$6)*12+MONTH($L$6)))<=11),IF(INDEX($L16:$W16,((YEAR(DATE(Настройки!$C$6,Настройки!$D$7+1,1))*12+MONTH(DATE(Настройки!$C$6,Настройки!$D$7+1,1)))-(YEAR($L$6)*12+MONTH($L$6)))+1)="✓",N($G16),IF(ISNUMBER(INDEX($L16:$W16,((YEAR(DATE(Настройки!$C$6,Настройки!$D$7+1,1))*12+MONTH(DATE(Настройки!$C$6,Настройки!$D$7+1,1)))-(YEAR($L$6)*12+MONTH($L$6)))+1)),INDEX($L16:$W16,((YEAR(DATE(Настройки!$C$6,Настройки!$D$7+1,1))*12+MONTH(DATE(Настройки!$C$6,Настройки!$D$7+1,1)))-(YEAR($L$6)*12+MONTH($L$6)))+1),IF(AND(OR($I16="",$I16<=(DATE(Настройки!$C$6,Настройки!$D$7+1+1,1)-1)),OR($J16="",$J16>=DATE(Настройки!$C$6,Настройки!$D$7+1,1)),MOD((YEAR(DATE(Настройки!$C$6,Настройки!$D$7+1,1))*12+MONTH(DATE(Настройки!$C$6,Настройки!$D$7+1,1)))-(YEAR(IF($I16="",$L$6,$I16))*12+MONTH(IF($I16="",$L$6,$I16))),MAX(1,N($H16)))=0),N($G16),0))),IF(AND(OR($I16="",$I16<=(DATE(Настройки!$C$6,Настройки!$D$7+1+1,1)-1)),OR($J16="",$J16>=DATE(Настройки!$C$6,Настройки!$D$7+1,1)),MOD((YEAR(DATE(Настройки!$C$6,Настройки!$D$7+1,1))*12+MONTH(DATE(Настройки!$C$6,Настройки!$D$7+1,1)))-(YEAR(IF($I16="",$L$6,$I16))*12+MONTH(IF($I16="",$L$6,$I16))),MAX(1,N($H16)))=0),N($G16),0)))
Y47: =IF(OR($C17="",$F17=""),"",DATE(YEAR($M$6),MONTH($M$6),MIN($F17,DAY((DATE(YEAR($M$6),MONTH($M$6)+1,1)-1))))) | Z47: =IF($C17="","",IF($D17="Доход","Доход","Расход")) | AA47: =IF($C17="","",$E17) | AB47: =IF($C17="",0,IF(AND(OR($I17="",$I17<=(DATE(YEAR($M$6),MONTH($M$6)+1,1)-1)),OR($J17="",$J17>=$M$6),MOD((YEAR($M$6)*12+MONTH($M$6))-(YEAR(IF($I17="",$L$6,$I17))*12+MONTH(IF($I17="",$L$6,$I17))),MAX(1,N($H17)))=0),N($G17),0)) | AC47: =IF($C17="",0,IF(M17="✓",N($G17),IF(ISNUMBER(M17),M17,0))) | AD47: =IF($C17="","",$M$6) | AE47: =IF($C17="","",$K17) | AG47: =IF(OR($C17="",$F17=""),"",DATE(YEAR(DATE(Настройки!$C$6,Настройки!$D$7+1,1)),MONTH(DATE(Настройки!$C$6,Настройки!$D$7+1,1)),MIN($F17,DAY((DATE(Настройки!$C$6,Настройки!$D$7+1+1,1)-1))))) | AH47: =IF($C17="","",IF($D17="Доход","Доход","Расход")) | AI47: =IF($C17="","",$E17) | AJ47: =IF($C17="",0,IF(AND(((YEAR(DATE(Настройки!$C$6,Настройки!$D$7+1,1))*12+MONTH(DATE(Настройки!$C$6,Настройки!$D$7+1,1)))-(YEAR($L$6)*12+MONTH($L$6)))>=0,((YEAR(DATE(Настройки!$C$6,Настройки!$D$7+1,1))*12+MONTH(DATE(Настройки!$C$6,Настройки!$D$7+1,1)))-(YEAR($L$6)*12+MONTH($L$6)))<=11),IF(INDEX($L17:$W17,((YEAR(DATE(Настройки!$C$6,Настройки!$D$7+1,1))*12+MONTH(DATE(Настройки!$C$6,Настройки!$D$7+1,1)))-(YEAR($L$6)*12+MONTH($L$6)))+1)="✓",N($G17),IF(ISNUMBER(INDEX($L17:$W17,((YEAR(DATE(Настройки!$C$6,Настройки!$D$7+1,1))*12+MONTH(DATE(Настройки!$C$6,Настройки!$D$7+1,1)))-(YEAR($L$6)*12+MONTH($L$6)))+1)),INDEX($L17:$W17,((YEAR(DATE(Настройки!$C$6,Настройки!$D$7+1,1))*12+MONTH(DATE(Настройки!$C$6,Настройки!$D$7+1,1)))-(YEAR($L$6)*12+MONTH($L$6)))+1),IF(AND(OR($I17="",$I17<=(DATE(Настройки!$C$6,Настройки!$D$7+1+1,1)-1)),OR($J17="",$J17>=DATE(Настройки!$C$6,Настройки!$D$7+1,1)),MOD((YEAR(DATE(Настройки!$C$6,Настройки!$D$7+1,1))*12+MONTH(DATE(Настройки!$C$6,Настройки!$D$7+1,1)))-(YEAR(IF($I17="",$L$6,$I17))*12+MONTH(IF($I17="",$L$6,$I17))),MAX(1,N($H17)))=0),N($G17),0))),IF(AND(OR($I17="",$I17<=(DATE(Настройки!$C$6,Настройки!$D$7+1+1,1)-1)),OR($J17="",$J17>=DATE(Настройки!$C$6,Настройки!$D$7+1,1)),MOD((YEAR(DATE(Настройки!$C$6,Настройки!$D$7+1,1))*12+MONTH(DATE(Настройки!$C$6,Настройки!$D$7+1,1)))-(YEAR(IF($I17="",$L$6,$I17))*12+MONTH(IF($I17="",$L$6,$I17))),MAX(1,N($H17)))=0),N($G17),0)))
Y48: =IF(OR($C18="",$F18=""),"",DATE(YEAR($M$6),MONTH($M$6),MIN($F18,DAY((DATE(YEAR($M$6),MONTH($M$6)+1,1)-1))))) | Z48: =IF($C18="","",IF($D18="Доход","Доход","Расход")) | AA48: =IF($C18="","",$E18) | AB48: =IF($C18="",0,IF(AND(OR($I18="",$I18<=(DATE(YEAR($M$6),MONTH($M$6)+1,1)-1)),OR($J18="",$J18>=$M$6),MOD((YEAR($M$6)*12+MONTH($M$6))-(YEAR(IF($I18="",$L$6,$I18))*12+MONTH(IF($I18="",$L$6,$I18))),MAX(1,N($H18)))=0),N($G18),0)) | AC48: =IF($C18="",0,IF(M18="✓",N($G18),IF(ISNUMBER(M18),M18,0))) | AD48: =IF($C18="","",$M$6) | AE48: =IF($C18="","",$K18) | AG48: =IF(OR($C18="",$F18=""),"",DATE(YEAR(DATE(Настройки!$C$6,Настройки!$D$7+1,1)),MONTH(DATE(Настройки!$C$6,Настройки!$D$7+1,1)),MIN($F18,DAY((DATE(Настройки!$C$6,Настройки!$D$7+1+1,1)-1))))) | AH48: =IF($C18="","",IF($D18="Доход","Доход","Расход")) | AI48: =IF($C18="","",$E18) | AJ48: =IF($C18="",0,IF(AND(((YEAR(DATE(Настройки!$C$6,Настройки!$D$7+1,1))*12+MONTH(DATE(Настройки!$C$6,Настройки!$D$7+1,1)))-(YEAR($L$6)*12+MONTH($L$6)))>=0,((YEAR(DATE(Настройки!$C$6,Настройки!$D$7+1,1))*12+MONTH(DATE(Настройки!$C$6,Настройки!$D$7+1,1)))-(YEAR($L$6)*12+MONTH($L$6)))<=11),IF(INDEX($L18:$W18,((YEAR(DATE(Настройки!$C$6,Настройки!$D$7+1,1))*12+MONTH(DATE(Настройки!$C$6,Настройки!$D$7+1,1)))-(YEAR($L$6)*12+MONTH($L$6)))+1)="✓",N($G18),IF(ISNUMBER(INDEX($L18:$W18,((YEAR(DATE(Настройки!$C$6,Настройки!$D$7+1,1))*12+MONTH(DATE(Настройки!$C$6,Настройки!$D$7+1,1)))-(YEAR($L$6)*12+MONTH($L$6)))+1)),INDEX($L18:$W18,((YEAR(DATE(Настройки!$C$6,Настройки!$D$7+1,1))*12+MONTH(DATE(Настройки!$C$6,Настройки!$D$7+1,1)))-(YEAR($L$6)*12+MONTH($L$6)))+1),IF(AND(OR($I18="",$I18<=(DATE(Настройки!$C$6,Настройки!$D$7+1+1,1)-1)),OR($J18="",$J18>=DATE(Настройки!$C$6,Настройки!$D$7+1,1)),MOD((YEAR(DATE(Настройки!$C$6,Настройки!$D$7+1,1))*12+MONTH(DATE(Настройки!$C$6,Настройки!$D$7+1,1)))-(YEAR(IF($I18="",$L$6,$I18))*12+MONTH(IF($I18="",$L$6,$I18))),MAX(1,N($H18)))=0),N($G18),0))),IF(AND(OR($I18="",$I18<=(DATE(Настройки!$C$6,Настройки!$D$7+1+1,1)-1)),OR($J18="",$J18>=DATE(Настройки!$C$6,Настройки!$D$7+1,1)),MOD((YEAR(DATE(Настройки!$C$6,Настройки!$D$7+1,1))*12+MONTH(DATE(Настройки!$C$6,Настройки!$D$7+1,1)))-(YEAR(IF($I18="",$L$6,$I18))*12+MONTH(IF($I18="",$L$6,$I18))),MAX(1,N($H18)))=0),N($G18),0)))
Y49: =IF(OR($C19="",$F19=""),"",DATE(YEAR($M$6),MONTH($M$6),MIN($F19,DAY((DATE(YEAR($M$6),MONTH($M$6)+1,1)-1))))) | Z49: =IF($C19="","",IF($D19="Доход","Доход","Расход")) | AA49: =IF($C19="","",$E19) | AB49: =IF($C19="",0,IF(AND(OR($I19="",$I19<=(DATE(YEAR($M$6),MONTH($M$6)+1,1)-1)),OR($J19="",$J19>=$M$6),MOD((YEAR($M$6)*12+MONTH($M$6))-(YEAR(IF($I19="",$L$6,$I19))*12+MONTH(IF($I19="",$L$6,$I19))),MAX(1,N($H19)))=0),N($G19),0)) | AC49: =IF($C19="",0,IF(M19="✓",N($G19),IF(ISNUMBER(M19),M19,0))) | AD49: =IF($C19="","",$M$6) | AE49: =IF($C19="","",$K19) | AG49: =IF(OR($C19="",$F19=""),"",DATE(YEAR(DATE(Настройки!$C$6,Настройки!$D$7+1,1)),MONTH(DATE(Настройки!$C$6,Настройки!$D$7+1,1)),MIN($F19,DAY((DATE(Настройки!$C$6,Настройки!$D$7+1+1,1)-1))))) | AH49: =IF($C19="","",IF($D19="Доход","Доход","Расход")) | AI49: =IF($C19="","",$E19) | AJ49: =IF($C19="",0,IF(AND(((YEAR(DATE(Настройки!$C$6,Настройки!$D$7+1,1))*12+MONTH(DATE(Настройки!$C$6,Настройки!$D$7+1,1)))-(YEAR($L$6)*12+MONTH($L$6)))>=0,((YEAR(DATE(Настройки!$C$6,Настройки!$D$7+1,1))*12+MONTH(DATE(Настройки!$C$6,Настройки!$D$7+1,1)))-(YEAR($L$6)*12+MONTH($L$6)))<=11),IF(INDEX($L19:$W19,((YEAR(DATE(Настройки!$C$6,Настройки!$D$7+1,1))*12+MONTH(DATE(Настройки!$C$6,Настройки!$D$7+1,1)))-(YEAR($L$6)*12+MONTH($L$6)))+1)="✓",N($G19),IF(ISNUMBER(INDEX($L19:$W19,((YEAR(DATE(Настройки!$C$6,Настройки!$D$7+1,1))*12+MONTH(DATE(Настройки!$C$6,Настройки!$D$7+1,1)))-(YEAR($L$6)*12+MONTH($L$6)))+1)),INDEX($L19:$W19,((YEAR(DATE(Настройки!$C$6,Настройки!$D$7+1,1))*12+MONTH(DATE(Настройки!$C$6,Настройки!$D$7+1,1)))-(YEAR($L$6)*12+MONTH($L$6)))+1),IF(AND(OR($I19="",$I19<=(DATE(Настройки!$C$6,Настройки!$D$7+1+1,1)-1)),OR($J19="",$J19>=DATE(Настройки!$C$6,Настройки!$D$7+1,1)),MOD((YEAR(DATE(Настройки!$C$6,Настройки!$D$7+1,1))*12+MONTH(DATE(Настройки!$C$6,Настройки!$D$7+1,1)))-(YEAR(IF($I19="",$L$6,$I19))*12+MONTH(IF($I19="",$L$6,$I19))),MAX(1,N($H19)))=0),N($G19),0))),IF(AND(OR($I19="",$I19<=(DATE(Настройки!$C$6,Настройки!$D$7+1+1,1)-1)),OR($J19="",$J19>=DATE(Настройки!$C$6,Настройки!$D$7+1,1)),MOD((YEAR(DATE(Настройки!$C$6,Настройки!$D$7+1,1))*12+MONTH(DATE(Настройки!$C$6,Настройки!$D$7+1,1)))-(YEAR(IF($I19="",$L$6,$I19))*12+MONTH(IF($I19="",$L$6,$I19))),MAX(1,N($H19)))=0),N($G19),0)))
Y50: =IF(OR($C20="",$F20=""),"",DATE(YEAR($M$6),MONTH($M$6),MIN($F20,DAY((DATE(YEAR($M$6),MONTH($M$6)+1,1)-1))))) | Z50: =IF($C20="","",IF($D20="Доход","Доход","Расход")) | AA50: =IF($C20="","",$E20) | AB50: =IF($C20="",0,IF(AND(OR($I20="",$I20<=(DATE(YEAR($M$6),MONTH($M$6)+1,1)-1)),OR($J20="",$J20>=$M$6),MOD((YEAR($M$6)*12+MONTH($M$6))-(YEAR(IF($I20="",$L$6,$I20))*12+MONTH(IF($I20="",$L$6,$I20))),MAX(1,N($H20)))=0),N($G20),0)) | AC50: =IF($C20="",0,IF(M20="✓",N($G20),IF(ISNUMBER(M20),M20,0))) | AD50: =IF($C20="","",$M$6) | AE50: =IF($C20="","",$K20) | AG50: =IF(OR($C20="",$F20=""),"",DATE(YEAR(DATE(Настройки!$C$6,Настройки!$D$7+1,1)),MONTH(DATE(Настройки!$C$6,Настройки!$D$7+1,1)),MIN($F20,DAY((DATE(Настройки!$C$6,Настройки!$D$7+1+1,1)-1))))) | AH50: =IF($C20="","",IF($D20="Доход","Доход","Расход")) | AI50: =IF($C20="","",$E20) | AJ50: =IF($C20="",0,IF(AND(((YEAR(DATE(Настройки!$C$6,Настройки!$D$7+1,1))*12+MONTH(DATE(Настройки!$C$6,Настройки!$D$7+1,1)))-(YEAR($L$6)*12+MONTH($L$6)))>=0,((YEAR(DATE(Настройки!$C$6,Настройки!$D$7+1,1))*12+MONTH(DATE(Настройки!$C$6,Настройки!$D$7+1,1)))-(YEAR($L$6)*12+MONTH($L$6)))<=11),IF(INDEX($L20:$W20,((YEAR(DATE(Настройки!$C$6,Настройки!$D$7+1,1))*12+MONTH(DATE(Настройки!$C$6,Настройки!$D$7+1,1)))-(YEAR($L$6)*12+MONTH($L$6)))+1)="✓",N($G20),IF(ISNUMBER(INDEX($L20:$W20,((YEAR(DATE(Настройки!$C$6,Настройки!$D$7+1,1))*12+MONTH(DATE(Настройки!$C$6,Настройки!$D$7+1,1)))-(YEAR($L$6)*12+MONTH($L$6)))+1)),INDEX($L20:$W20,((YEAR(DATE(Настройки!$C$6,Настройки!$D$7+1,1))*12+MONTH(DATE(Настройки!$C$6,Настройки!$D$7+1,1)))-(YEAR($L$6)*12+MONTH($L$6)))+1),IF(AND(OR($I20="",$I20<=(DATE(Настройки!$C$6,Настройки!$D$7+1+1,1)-1)),OR($J20="",$J20>=DATE(Настройки!$C$6,Настройки!$D$7+1,1)),MOD((YEAR(DATE(Настройки!$C$6,Настройки!$D$7+1,1))*12+MONTH(DATE(Настройки!$C$6,Настройки!$D$7+1,1)))-(YEAR(IF($I20="",$L$6,$I20))*12+MONTH(IF($I20="",$L$6,$I20))),MAX(1,N($H20)))=0),N($G20),0))),IF(AND(OR($I20="",$I20<=(DATE(Настройки!$C$6,Настройки!$D$7+1+1,1)-1)),OR($J20="",$J20>=DATE(Настройки!$C$6,Настройки!$D$7+1,1)),MOD((YEAR(DATE(Настройки!$C$6,Настройки!$D$7+1,1))*12+MONTH(DATE(Настройки!$C$6,Настройки!$D$7+1,1)))-(YEAR(IF($I20="",$L$6,$I20))*12+MONTH(IF($I20="",$L$6,$I20))),MAX(1,N($H20)))=0),N($G20),0)))
Y51: =IF(OR($C21="",$F21=""),"",DATE(YEAR($M$6),MONTH($M$6),MIN($F21,DAY((DATE(YEAR($M$6),MONTH($M$6)+1,1)-1))))) | Z51: =IF($C21="","",IF($D21="Доход","Доход","Расход")) | AA51: =IF($C21="","",$E21) | AB51: =IF($C21="",0,IF(AND(OR($I21="",$I21<=(DATE(YEAR($M$6),MONTH($M$6)+1,1)-1)),OR($J21="",$J21>=$M$6),MOD((YEAR($M$6)*12+MONTH($M$6))-(YEAR(IF($I21="",$L$6,$I21))*12+MONTH(IF($I21="",$L$6,$I21))),MAX(1,N($H21)))=0),N($G21),0)) | AC51: =IF($C21="",0,IF(M21="✓",N($G21),IF(ISNUMBER(M21),M21,0))) | AD51: =IF($C21="","",$M$6) | AE51: =IF($C21="","",$K21) | AG51: =IF(OR($C21="",$F21=""),"",DATE(YEAR(DATE(Настройки!$C$6,Настройки!$D$7+1,1)),MONTH(DATE(Настройки!$C$6,Настройки!$D$7+1,1)),MIN($F21,DAY((DATE(Настройки!$C$6,Настройки!$D$7+1+1,1)-1))))) | AH51: =IF($C21="","",IF($D21="Доход","Доход","Расход")) | AI51: =IF($C21="","",$E21) | AJ51: =IF($C21="",0,IF(AND(((YEAR(DATE(Настройки!$C$6,Настройки!$D$7+1,1))*12+MONTH(DATE(Настройки!$C$6,Настройки!$D$7+1,1)))-(YEAR($L$6)*12+MONTH($L$6)))>=0,((YEAR(DATE(Настройки!$C$6,Настройки!$D$7+1,1))*12+MONTH(DATE(Настройки!$C$6,Настройки!$D$7+1,1)))-(YEAR($L$6)*12+MONTH($L$6)))<=11),IF(INDEX($L21:$W21,((YEAR(DATE(Настройки!$C$6,Настройки!$D$7+1,1))*12+MONTH(DATE(Настройки!$C$6,Настройки!$D$7+1,1)))-(YEAR($L$6)*12+MONTH($L$6)))+1)="✓",N($G21),IF(ISNUMBER(INDEX($L21:$W21,((YEAR(DATE(Настройки!$C$6,Настройки!$D$7+1,1))*12+MONTH(DATE(Настройки!$C$6,Настройки!$D$7+1,1)))-(YEAR($L$6)*12+MONTH($L$6)))+1)),INDEX($L21:$W21,((YEAR(DATE(Настройки!$C$6,Настройки!$D$7+1,1))*12+MONTH(DATE(Настройки!$C$6,Настройки!$D$7+1,1)))-(YEAR($L$6)*12+MONTH($L$6)))+1),IF(AND(OR($I21="",$I21<=(DATE(Настройки!$C$6,Настройки!$D$7+1+1,1)-1)),OR($J21="",$J21>=DATE(Настройки!$C$6,Настройки!$D$7+1,1)),MOD((YEAR(DATE(Настройки!$C$6,Настройки!$D$7+1,1))*12+MONTH(DATE(Настройки!$C$6,Настройки!$D$7+1,1)))-(YEAR(IF($I21="",$L$6,$I21))*12+MONTH(IF($I21="",$L$6,$I21))),MAX(1,N($H21)))=0),N($G21),0))),IF(AND(OR($I21="",$I21<=(DATE(Настройки!$C$6,Настройки!$D$7+1+1,1)-1)),OR($J21="",$J21>=DATE(Настройки!$C$6,Настройки!$D$7+1,1)),MOD((YEAR(DATE(Настройки!$C$6,Настройки!$D$7+1,1))*12+MONTH(DATE(Настройки!$C$6,Настройки!$D$7+1,1)))-(YEAR(IF($I21="",$L$6,$I21))*12+MONTH(IF($I21="",$L$6,$I21))),MAX(1,N($H21)))=0),N($G21),0)))
... Y67: =IF(OR($C37="",$F37=""),"",DATE(YEAR($M$6),MONTH($M$6),MIN($F37,DAY((DATE(YEAR($M$6),MONTH($M$6)+1,1)-1))))) | Z67: =IF($C37="","",IF($D37="Доход","Доход","Расход")) | AA67: =IF($C37="","",$E37) | AB67: =IF($C37="",0,IF(AND(OR($I37="",$I37<=(DATE(YEAR($M$6),MONTH($M$6)+1,1)-1)),OR($J37="",$J37>=$M$6),MOD((YEAR($M$6)*12+MONTH($M$6))-(YEAR(IF($I37="",$L$6,$I37))*12+MONTH(IF($I37="",$L$6,$I37))),MAX(1,N($H37)))=0),N($G37),0)) | AC67: =IF($C37="",0,IF(M37="✓",N($G37),IF(ISNUMBER(M37),M37,0))) | AD67: =IF($C37="","",$M$6) | AE67: =IF($C37="","",$K37) | AG67: =IF(OR($C37="",$F37=""),"",DATE(YEAR(DATE(Настройки!$C$6,Настройки!$D$7+1,1)),MONTH(DATE(Настройки!$C$6,Настройки!$D$7+1,1)),MIN($F37,DAY((DATE(Настройки!$C$6,Настройки!$D$7+1+1,1)-1))))) | AH67: =IF($C37="","",IF($D37="Доход","Доход","Расход")) | AI67: =IF($C37="","",$E37) | AJ67: =IF($C37="",0,IF(AND(((YEAR(DATE(Настройки!$C$6,Настройки!$D$7+1,1))*12+MONTH(DATE(Настройки!$C$6,Настройки!$D$7+1,1)))-(YEAR($L$6)*12+MONTH($L$6)))>=0,((YEAR(DATE(Настройки!$C$6,Настройки!$D$7+1,1))*12+MONTH(DATE(Настройки!$C$6,Настройки!$D$7+1,1)))-(YEAR($L$6)*12+MONTH($L$6)))<=11),IF(INDEX($L37:$W37,((YEAR(DATE(Настройки!$C$6,Настройки!$D$7+1,1))*12+MONTH(DATE(Настройки!$C$6,Настройки!$D$7+1,1)))-(YEAR($L$6)*12+MONTH($L$6)))+1)="✓",N($G37),IF(ISNUMBER(INDEX($L37:$W37,((YEAR(DATE(Настройки!$C$6,Настройки!$D$7+1,1))*12+MONTH(DATE(Настройки!$C$6,Настройки!$D$7+1,1)))-(YEAR($L$6)*12+MONTH($L$6)))+1)),INDEX($L37:$W37,((YEAR(DATE(Настройки!$C$6,Настройки!$D$7+1,1))*12+MONTH(DATE(Настройки!$C$6,Настройки!$D$7+1,1)))-(YEAR($L$6)*12+MONTH($L$6)))+1),IF(AND(OR($I37="",$I37<=(DATE(Настройки!$C$6,Настройки!$D$7+1+1,1)-1)),OR($J37="",$J37>=DATE(Настройки!$C$6,Настройки!$D$7+1,1)),MOD((YEAR(DATE(Настройки!$C$6,Настройки!$D$7+1,1))*12+MONTH(DATE(Настройки!$C$6,Настройки!$D$7+1,1)))-(YEAR(IF($I37="",$L$6,$I37))*12+MONTH(IF($I37="",$L$6,$I37))),MAX(1,N($H37)))=0),N($G37),0))),IF(AND(OR($I37="",$I37<=(DATE(Настройки!$C$6,Настройки!$D$7+1+1,1)-1)),OR($J37="",$J37>=DATE(Настройки!$C$6,Настройки!$D$7+1,1)),MOD((YEAR(DATE(Настройки!$C$6,Настройки!$D$7+1,1))*12+MONTH(DATE(Настройки!$C$6,Настройки!$D$7+1,1)))-(YEAR(IF($I37="",$L$6,$I37))*12+MONTH(IF($I37="",$L$6,$I37))),MAX(1,N($H37)))=0),N($G37),0)))
Y68: =IF(OR($C8="",$F8=""),"",DATE(YEAR($N$6),MONTH($N$6),MIN($F8,DAY((DATE(YEAR($N$6),MONTH($N$6)+1,1)-1))))) | Z68: =IF($C8="","",IF($D8="Доход","Доход","Расход")) | AA68: =IF($C8="","",$E8) | AB68: =IF($C8="",0,IF(AND(OR($I8="",$I8<=(DATE(YEAR($N$6),MONTH($N$6)+1,1)-1)),OR($J8="",$J8>=$N$6),MOD((YEAR($N$6)*12+MONTH($N$6))-(YEAR(IF($I8="",$L$6,$I8))*12+MONTH(IF($I8="",$L$6,$I8))),MAX(1,N($H8)))=0),N($G8),0)) | AC68: =IF($C8="",0,IF(N8="✓",N($G8),IF(ISNUMBER(N8),N8,0))) | AD68: =IF($C8="","",$N$6) | AE68: =IF($C8="","",$K8) | AG68: =IF(OR($C8="",$F8=""),"",DATE(YEAR(DATE(Настройки!$C$6,Настройки!$D$7+2,1)),MONTH(DATE(Настройки!$C$6,Настройки!$D$7+2,1)),MIN($F8,DAY((DATE(Настройки!$C$6,Настройки!$D$7+2+1,1)-1))))) | AH68: =IF($C8="","",IF($D8="Доход","Доход","Расход")) | AI68: =IF($C8="","",$E8) | AJ68: =IF($C8="",0,IF(AND(((YEAR(DATE(Настройки!$C$6,Настройки!$D$7+2,1))*12+MONTH(DATE(Настройки!$C$6,Настройки!$D$7+2,1)))-(YEAR($L$6)*12+MONTH($L$6)))>=0,((YEAR(DATE(Настройки!$C$6,Настройки!$D$7+2,1))*12+MONTH(DATE(Настройки!$C$6,Настройки!$D$7+2,1)))-(YEAR($L$6)*12+MONTH($L$6)))<=11),IF(INDEX($L8:$W8,((YEAR(DATE(Настройки!$C$6,Настройки!$D$7+2,1))*12+MONTH(DATE(Настройки!$C$6,Настройки!$D$7+2,1)))-(YEAR($L$6)*12+MONTH($L$6)))+1)="✓",N($G8),IF(ISNUMBER(INDEX($L8:$W8,((YEAR(DATE(Настройки!$C$6,Настройки!$D$7+2,1))*12+MONTH(DATE(Настройки!$C$6,Настройки!$D$7+2,1)))-(YEAR($L$6)*12+MONTH($L$6)))+1)),INDEX($L8:$W8,((YEAR(DATE(Настройки!$C$6,Настройки!$D$7+2,1))*12+MONTH(DATE(Настройки!$C$6,Настройки!$D$7+2,1)))-(YEAR($L$6)*12+MONTH($L$6)))+1),IF(AND(OR($I8="",$I8<=(DATE(Настройки!$C$6,Настройки!$D$7+2+1,1)-1)),OR($J8="",$J8>=DATE(Настройки!$C$6,Настройки!$D$7+2,1)),MOD((YEAR(DATE(Настройки!$C$6,Настройки!$D$7+2,1))*12+MONTH(DATE(Настройки!$C$6,Настройки!$D$7+2,1)))-(YEAR(IF($I8="",$L$6,$I8))*12+MONTH(IF($I8="",$L$6,$I8))),MAX(1,N($H8)))=0),N($G8),0))),IF(AND(OR($I8="",$I8<=(DATE(Настройки!$C$6,Настройки!$D$7+2+1,1)-1)),OR($J8="",$J8>=DATE(Настройки!$C$6,Настройки!$D$7+2,1)),MOD((YEAR(DATE(Настройки!$C$6,Настройки!$D$7+2,1))*12+MONTH(DATE(Настройки!$C$6,Настройки!$D$7+2,1)))-(YEAR(IF($I8="",$L$6,$I8))*12+MONTH(IF($I8="",$L$6,$I8))),MAX(1,N($H8)))=0),N($G8),0)))
Y69: =IF(OR($C9="",$F9=""),"",DATE(YEAR($N$6),MONTH($N$6),MIN($F9,DAY((DATE(YEAR($N$6),MONTH($N$6)+1,1)-1))))) | Z69: =IF($C9="","",IF($D9="Доход","Доход","Расход")) | AA69: =IF($C9="","",$E9) | AB69: =IF($C9="",0,IF(AND(OR($I9="",$I9<=(DATE(YEAR($N$6),MONTH($N$6)+1,1)-1)),OR($J9="",$J9>=$N$6),MOD((YEAR($N$6)*12+MONTH($N$6))-(YEAR(IF($I9="",$L$6,$I9))*12+MONTH(IF($I9="",$L$6,$I9))),MAX(1,N($H9)))=0),N($G9),0)) | AC69: =IF($C9="",0,IF(N9="✓",N($G9),IF(ISNUMBER(N9),N9,0))) | AD69: =IF($C9="","",$N$6) | AE69: =IF($C9="","",$K9) | AG69: =IF(OR($C9="",$F9=""),"",DATE(YEAR(DATE(Настройки!$C$6,Настройки!$D$7+2,1)),MONTH(DATE(Настройки!$C$6,Настройки!$D$7+2,1)),MIN($F9,DAY((DATE(Настройки!$C$6,Настройки!$D$7+2+1,1)-1))))) | AH69: =IF($C9="","",IF($D9="Доход","Доход","Расход")) | AI69: =IF($C9="","",$E9) | AJ69: =IF($C9="",0,IF(AND(((YEAR(DATE(Настройки!$C$6,Настройки!$D$7+2,1))*12+MONTH(DATE(Настройки!$C$6,Настройки!$D$7+2,1)))-(YEAR($L$6)*12+MONTH($L$6)))>=0,((YEAR(DATE(Настройки!$C$6,Настройки!$D$7+2,1))*12+MONTH(DATE(Настройки!$C$6,Настройки!$D$7+2,1)))-(YEAR($L$6)*12+MONTH($L$6)))<=11),IF(INDEX($L9:$W9,((YEAR(DATE(Настройки!$C$6,Настройки!$D$7+2,1))*12+MONTH(DATE(Настройки!$C$6,Настройки!$D$7+2,1)))-(YEAR($L$6)*12+MONTH($L$6)))+1)="✓",N($G9),IF(ISNUMBER(INDEX($L9:$W9,((YEAR(DATE(Настройки!$C$6,Настройки!$D$7+2,1))*12+MONTH(DATE(Настройки!$C$6,Настройки!$D$7+2,1)))-(YEAR($L$6)*12+MONTH($L$6)))+1)),INDEX($L9:$W9,((YEAR(DATE(Настройки!$C$6,Настройки!$D$7+2,1))*12+MONTH(DATE(Настройки!$C$6,Настройки!$D$7+2,1)))-(YEAR($L$6)*12+MONTH($L$6)))+1),IF(AND(OR($I9="",$I9<=(DATE(Настройки!$C$6,Настройки!$D$7+2+1,1)-1)),OR($J9="",$J9>=DATE(Настройки!$C$6,Настройки!$D$7+2,1)),MOD((YEAR(DATE(Настройки!$C$6,Настройки!$D$7+2,1))*12+MONTH(DATE(Настройки!$C$6,Настройки!$D$7+2,1)))-(YEAR(IF($I9="",$L$6,$I9))*12+MONTH(IF($I9="",$L$6,$I9))),MAX(1,N($H9)))=0),N($G9),0))),IF(AND(OR($I9="",$I9<=(DATE(Настройки!$C$6,Настройки!$D$7+2+1,1)-1)),OR($J9="",$J9>=DATE(Настройки!$C$6,Настройки!$D$7+2,1)),MOD((YEAR(DATE(Настройки!$C$6,Настройки!$D$7+2,1))*12+MONTH(DATE(Настройки!$C$6,Настройки!$D$7+2,1)))-(YEAR(IF($I9="",$L$6,$I9))*12+MONTH(IF($I9="",$L$6,$I9))),MAX(1,N($H9)))=0),N($G9),0)))
Y70: =IF(OR($C10="",$F10=""),"",DATE(YEAR($N$6),MONTH($N$6),MIN($F10,DAY((DATE(YEAR($N$6),MONTH($N$6)+1,1)-1))))) | Z70: =IF($C10="","",IF($D10="Доход","Доход","Расход")) | AA70: =IF($C10="","",$E10) | AB70: =IF($C10="",0,IF(AND(OR($I10="",$I10<=(DATE(YEAR($N$6),MONTH($N$6)+1,1)-1)),OR($J10="",$J10>=$N$6),MOD((YEAR($N$6)*12+MONTH($N$6))-(YEAR(IF($I10="",$L$6,$I10))*12+MONTH(IF($I10="",$L$6,$I10))),MAX(1,N($H10)))=0),N($G10),0)) | AC70: =IF($C10="",0,IF(N10="✓",N($G10),IF(ISNUMBER(N10),N10,0))) | AD70: =IF($C10="","",$N$6) | AE70: =IF($C10="","",$K10) | AG70: =IF(OR($C10="",$F10=""),"",DATE(YEAR(DATE(Настройки!$C$6,Настройки!$D$7+2,1)),MONTH(DATE(Настройки!$C$6,Настройки!$D$7+2,1)),MIN($F10,DAY((DATE(Настройки!$C$6,Настройки!$D$7+2+1,1)-1))))) | AH70: =IF($C10="","",IF($D10="Доход","Доход","Расход")) | AI70: =IF($C10="","",$E10) | AJ70: =IF($C10="",0,IF(AND(((YEAR(DATE(Настройки!$C$6,Настройки!$D$7+2,1))*12+MONTH(DATE(Настройки!$C$6,Настройки!$D$7+2,1)))-(YEAR($L$6)*12+MONTH($L$6)))>=0,((YEAR(DATE(Настройки!$C$6,Настройки!$D$7+2,1))*12+MONTH(DATE(Настройки!$C$6,Настройки!$D$7+2,1)))-(YEAR($L$6)*12+MONTH($L$6)))<=11),IF(INDEX($L10:$W10,((YEAR(DATE(Настройки!$C$6,Настройки!$D$7+2,1))*12+MONTH(DATE(Настройки!$C$6,Настройки!$D$7+2,1)))-(YEAR($L$6)*12+MONTH($L$6)))+1)="✓",N($G10),IF(ISNUMBER(INDEX($L10:$W10,((YEAR(DATE(Настройки!$C$6,Настройки!$D$7+2,1))*12+MONTH(DATE(Настройки!$C$6,Настройки!$D$7+2,1)))-(YEAR($L$6)*12+MONTH($L$6)))+1)),INDEX($L10:$W10,((YEAR(DATE(Настройки!$C$6,Настройки!$D$7+2,1))*12+MONTH(DATE(Настройки!$C$6,Настройки!$D$7+2,1)))-(YEAR($L$6)*12+MONTH($L$6)))+1),IF(AND(OR($I10="",$I10<=(DATE(Настройки!$C$6,Настройки!$D$7+2+1,1)-1)),OR($J10="",$J10>=DATE(Настройки!$C$6,Настройки!$D$7+2,1)),MOD((YEAR(DATE(Настройки!$C$6,Настройки!$D$7+2,1))*12+MONTH(DATE(Настройки!$C$6,Настройки!$D$7+2,1)))-(YEAR(IF($I10="",$L$6,$I10))*12+MONTH(IF($I10="",$L$6,$I10))),MAX(1,N($H10)))=0),N($G10),0))),IF(AND(OR($I10="",$I10<=(DATE(Настройки!$C$6,Настройки!$D$7+2+1,1)-1)),OR($J10="",$J10>=DATE(Настройки!$C$6,Настройки!$D$7+2,1)),MOD((YEAR(DATE(Настройки!$C$6,Настройки!$D$7+2,1))*12+MONTH(DATE(Настройки!$C$6,Настройки!$D$7+2,1)))-(YEAR(IF($I10="",$L$6,$I10))*12+MONTH(IF($I10="",$L$6,$I10))),MAX(1,N($H10)))=0),N($G10),0)))
Y71: =IF(OR($C11="",$F11=""),"",DATE(YEAR($N$6),MONTH($N$6),MIN($F11,DAY((DATE(YEAR($N$6),MONTH($N$6)+1,1)-1))))) | Z71: =IF($C11="","",IF($D11="Доход","Доход","Расход")) | AA71: =IF($C11="","",$E11) | AB71: =IF($C11="",0,IF(AND(OR($I11="",$I11<=(DATE(YEAR($N$6),MONTH($N$6)+1,1)-1)),OR($J11="",$J11>=$N$6),MOD((YEAR($N$6)*12+MONTH($N$6))-(YEAR(IF($I11="",$L$6,$I11))*12+MONTH(IF($I11="",$L$6,$I11))),MAX(1,N($H11)))=0),N($G11),0)) | AC71: =IF($C11="",0,IF(N11="✓",N($G11),IF(ISNUMBER(N11),N11,0))) | AD71: =IF($C11="","",$N$6) | AE71: =IF($C11="","",$K11) | AG71: =IF(OR($C11="",$F11=""),"",DATE(YEAR(DATE(Настройки!$C$6,Настройки!$D$7+2,1)),MONTH(DATE(Настройки!$C$6,Настройки!$D$7+2,1)),MIN($F11,DAY((DATE(Настройки!$C$6,Настройки!$D$7+2+1,1)-1))))) | AH71: =IF($C11="","",IF($D11="Доход","Доход","Расход")) | AI71: =IF($C11="","",$E11) | AJ71: =IF($C11="",0,IF(AND(((YEAR(DATE(Настройки!$C$6,Настройки!$D$7+2,1))*12+MONTH(DATE(Настройки!$C$6,Настройки!$D$7+2,1)))-(YEAR($L$6)*12+MONTH($L$6)))>=0,((YEAR(DATE(Настройки!$C$6,Настройки!$D$7+2,1))*12+MONTH(DATE(Настройки!$C$6,Настройки!$D$7+2,1)))-(YEAR($L$6)*12+MONTH($L$6)))<=11),IF(INDEX($L11:$W11,((YEAR(DATE(Настройки!$C$6,Настройки!$D$7+2,1))*12+MONTH(DATE(Настройки!$C$6,Настройки!$D$7+2,1)))-(YEAR($L$6)*12+MONTH($L$6)))+1)="✓",N($G11),IF(ISNUMBER(INDEX($L11:$W11,((YEAR(DATE(Настройки!$C$6,Настройки!$D$7+2,1))*12+MONTH(DATE(Настройки!$C$6,Настройки!$D$7+2,1)))-(YEAR($L$6)*12+MONTH($L$6)))+1)),INDEX($L11:$W11,((YEAR(DATE(Настройки!$C$6,Настройки!$D$7+2,1))*12+MONTH(DATE(Настройки!$C$6,Настройки!$D$7+2,1)))-(YEAR($L$6)*12+MONTH($L$6)))+1),IF(AND(OR($I11="",$I11<=(DATE(Настройки!$C$6,Настройки!$D$7+2+1,1)-1)),OR($J11="",$J11>=DATE(Настройки!$C$6,Настройки!$D$7+2,1)),MOD((YEAR(DATE(Настройки!$C$6,Настройки!$D$7+2,1))*12+MONTH(DATE(Настройки!$C$6,Настройки!$D$7+2,1)))-(YEAR(IF($I11="",$L$6,$I11))*12+MONTH(IF($I11="",$L$6,$I11))),MAX(1,N($H11)))=0),N($G11),0))),IF(AND(OR($I11="",$I11<=(DATE(Настройки!$C$6,Настройки!$D$7+2+1,1)-1)),OR($J11="",$J11>=DATE(Настройки!$C$6,Настройки!$D$7+2,1)),MOD((YEAR(DATE(Настройки!$C$6,Настройки!$D$7+2,1))*12+MONTH(DATE(Настройки!$C$6,Настройки!$D$7+2,1)))-(YEAR(IF($I11="",$L$6,$I11))*12+MONTH(IF($I11="",$L$6,$I11))),MAX(1,N($H11)))=0),N($G11),0)))
Y72: =IF(OR($C12="",$F12=""),"",DATE(YEAR($N$6),MONTH($N$6),MIN($F12,DAY((DATE(YEAR($N$6),MONTH($N$6)+1,1)-1))))) | Z72: =IF($C12="","",IF($D12="Доход","Доход","Расход")) | AA72: =IF($C12="","",$E12) | AB72: =IF($C12="",0,IF(AND(OR($I12="",$I12<=(DATE(YEAR($N$6),MONTH($N$6)+1,1)-1)),OR($J12="",$J12>=$N$6),MOD((YEAR($N$6)*12+MONTH($N$6))-(YEAR(IF($I12="",$L$6,$I12))*12+MONTH(IF($I12="",$L$6,$I12))),MAX(1,N($H12)))=0),N($G12),0)) | AC72: =IF($C12="",0,IF(N12="✓",N($G12),IF(ISNUMBER(N12),N12,0))) | AD72: =IF($C12="","",$N$6) | AE72: =IF($C12="","",$K12) | AG72: =IF(OR($C12="",$F12=""),"",DATE(YEAR(DATE(Настройки!$C$6,Настройки!$D$7+2,1)),MONTH(DATE(Настройки!$C$6,Настройки!$D$7+2,1)),MIN($F12,DAY((DATE(Настройки!$C$6,Настройки!$D$7+2+1,1)-1))))) | AH72: =IF($C12="","",IF($D12="Доход","Доход","Расход")) | AI72: =IF($C12="","",$E12) | AJ72: =IF($C12="",0,IF(AND(((YEAR(DATE(Настройки!$C$6,Настройки!$D$7+2,1))*12+MONTH(DATE(Настройки!$C$6,Настройки!$D$7+2,1)))-(YEAR($L$6)*12+MONTH($L$6)))>=0,((YEAR(DATE(Настройки!$C$6,Настройки!$D$7+2,1))*12+MONTH(DATE(Настройки!$C$6,Настройки!$D$7+2,1)))-(YEAR($L$6)*12+MONTH($L$6)))<=11),IF(INDEX($L12:$W12,((YEAR(DATE(Настройки!$C$6,Настройки!$D$7+2,1))*12+MONTH(DATE(Настройки!$C$6,Настройки!$D$7+2,1)))-(YEAR($L$6)*12+MONTH($L$6)))+1)="✓",N($G12),IF(ISNUMBER(INDEX($L12:$W12,((YEAR(DATE(Настройки!$C$6,Настройки!$D$7+2,1))*12+MONTH(DATE(Настройки!$C$6,Настройки!$D$7+2,1)))-(YEAR($L$6)*12+MONTH($L$6)))+1)),INDEX($L12:$W12,((YEAR(DATE(Настройки!$C$6,Настройки!$D$7+2,1))*12+MONTH(DATE(Настройки!$C$6,Настройки!$D$7+2,1)))-(YEAR($L$6)*12+MONTH($L$6)))+1),IF(AND(OR($I12="",$I12<=(DATE(Настройки!$C$6,Настройки!$D$7+2+1,1)-1)),OR($J12="",$J12>=DATE(Настройки!$C$6,Настройки!$D$7+2,1)),MOD((YEAR(DATE(Настройки!$C$6,Настройки!$D$7+2,1))*12+MONTH(DATE(Настройки!$C$6,Настройки!$D$7+2,1)))-(YEAR(IF($I12="",$L$6,$I12))*12+MONTH(IF($I12="",$L$6,$I12))),MAX(1,N($H12)))=0),N($G12),0))),IF(AND(OR($I12="",$I12<=(DATE(Настройки!$C$6,Настройки!$D$7+2+1,1)-1)),OR($J12="",$J12>=DATE(Настройки!$C$6,Настройки!$D$7+2,1)),MOD((YEAR(DATE(Настройки!$C$6,Настройки!$D$7+2,1))*12+MONTH(DATE(Настройки!$C$6,Настройки!$D$7+2,1)))-(YEAR(IF($I12="",$L$6,$I12))*12+MONTH(IF($I12="",$L$6,$I12))),MAX(1,N($H12)))=0),N($G12),0)))
Y73: =IF(OR($C13="",$F13=""),"",DATE(YEAR($N$6),MONTH($N$6),MIN($F13,DAY((DATE(YEAR($N$6),MONTH($N$6)+1,1)-1))))) | Z73: =IF($C13="","",IF($D13="Доход","Доход","Расход")) | AA73: =IF($C13="","",$E13) | AB73: =IF($C13="",0,IF(AND(OR($I13="",$I13<=(DATE(YEAR($N$6),MONTH($N$6)+1,1)-1)),OR($J13="",$J13>=$N$6),MOD((YEAR($N$6)*12+MONTH($N$6))-(YEAR(IF($I13="",$L$6,$I13))*12+MONTH(IF($I13="",$L$6,$I13))),MAX(1,N($H13)))=0),N($G13),0)) | AC73: =IF($C13="",0,IF(N13="✓",N($G13),IF(ISNUMBER(N13),N13,0))) | AD73: =IF($C13="","",$N$6) | AE73: =IF($C13="","",$K13) | AG73: =IF(OR($C13="",$F13=""),"",DATE(YEAR(DATE(Настройки!$C$6,Настройки!$D$7+2,1)),MONTH(DATE(Настройки!$C$6,Настройки!$D$7+2,1)),MIN($F13,DAY((DATE(Настройки!$C$6,Настройки!$D$7+2+1,1)-1))))) | AH73: =IF($C13="","",IF($D13="Доход","Доход","Расход")) | AI73: =IF($C13="","",$E13) | AJ73: =IF($C13="",0,IF(AND(((YEAR(DATE(Настройки!$C$6,Настройки!$D$7+2,1))*12+MONTH(DATE(Настройки!$C$6,Настройки!$D$7+2,1)))-(YEAR($L$6)*12+MONTH($L$6)))>=0,((YEAR(DATE(Настройки!$C$6,Настройки!$D$7+2,1))*12+MONTH(DATE(Настройки!$C$6,Настройки!$D$7+2,1)))-(YEAR($L$6)*12+MONTH($L$6)))<=11),IF(INDEX($L13:$W13,((YEAR(DATE(Настройки!$C$6,Настройки!$D$7+2,1))*12+MONTH(DATE(Настройки!$C$6,Настройки!$D$7+2,1)))-(YEAR($L$6)*12+MONTH($L$6)))+1)="✓",N($G13),IF(ISNUMBER(INDEX($L13:$W13,((YEAR(DATE(Настройки!$C$6,Настройки!$D$7+2,1))*12+MONTH(DATE(Настройки!$C$6,Настройки!$D$7+2,1)))-(YEAR($L$6)*12+MONTH($L$6)))+1)),INDEX($L13:$W13,((YEAR(DATE(Настройки!$C$6,Настройки!$D$7+2,1))*12+MONTH(DATE(Настройки!$C$6,Настройки!$D$7+2,1)))-(YEAR($L$6)*12+MONTH($L$6)))+1),IF(AND(OR($I13="",$I13<=(DATE(Настройки!$C$6,Настройки!$D$7+2+1,1)-1)),OR($J13="",$J13>=DATE(Настройки!$C$6,Настройки!$D$7+2,1)),MOD((YEAR(DATE(Настройки!$C$6,Настройки!$D$7+2,1))*12+MONTH(DATE(Настройки!$C$6,Настройки!$D$7+2,1)))-(YEAR(IF($I13="",$L$6,$I13))*12+MONTH(IF($I13="",$L$6,$I13))),MAX(1,N($H13)))=0),N($G13),0))),IF(AND(OR($I13="",$I13<=(DATE(Настройки!$C$6,Настройки!$D$7+2+1,1)-1)),OR($J13="",$J13>=DATE(Настройки!$C$6,Настройки!$D$7+2,1)),MOD((YEAR(DATE(Настройки!$C$6,Настройки!$D$7+2,1))*12+MONTH(DATE(Настройки!$C$6,Настройки!$D$7+2,1)))-(YEAR(IF($I13="",$L$6,$I13))*12+MONTH(IF($I13="",$L$6,$I13))),MAX(1,N($H13)))=0),N($G13),0)))
Y74: =IF(OR($C14="",$F14=""),"",DATE(YEAR($N$6),MONTH($N$6),MIN($F14,DAY((DATE(YEAR($N$6),MONTH($N$6)+1,1)-1))))) | Z74: =IF($C14="","",IF($D14="Доход","Доход","Расход")) | AA74: =IF($C14="","",$E14) | AB74: =IF($C14="",0,IF(AND(OR($I14="",$I14<=(DATE(YEAR($N$6),MONTH($N$6)+1,1)-1)),OR($J14="",$J14>=$N$6),MOD((YEAR($N$6)*12+MONTH($N$6))-(YEAR(IF($I14="",$L$6,$I14))*12+MONTH(IF($I14="",$L$6,$I14))),MAX(1,N($H14)))=0),N($G14),0)) | AC74: =IF($C14="",0,IF(N14="✓",N($G14),IF(ISNUMBER(N14),N14,0))) | AD74: =IF($C14="","",$N$6) | AE74: =IF($C14="","",$K14) | AG74: =IF(OR($C14="",$F14=""),"",DATE(YEAR(DATE(Настройки!$C$6,Настройки!$D$7+2,1)),MONTH(DATE(Настройки!$C$6,Настройки!$D$7+2,1)),MIN($F14,DAY((DATE(Настройки!$C$6,Настройки!$D$7+2+1,1)-1))))) | AH74: =IF($C14="","",IF($D14="Доход","Доход","Расход")) | AI74: =IF($C14="","",$E14) | AJ74: =IF($C14="",0,IF(AND(((YEAR(DATE(Настройки!$C$6,Настройки!$D$7+2,1))*12+MONTH(DATE(Настройки!$C$6,Настройки!$D$7+2,1)))-(YEAR($L$6)*12+MONTH($L$6)))>=0,((YEAR(DATE(Настройки!$C$6,Настройки!$D$7+2,1))*12+MONTH(DATE(Настройки!$C$6,Настройки!$D$7+2,1)))-(YEAR($L$6)*12+MONTH($L$6)))<=11),IF(INDEX($L14:$W14,((YEAR(DATE(Настройки!$C$6,Настройки!$D$7+2,1))*12+MONTH(DATE(Настройки!$C$6,Настройки!$D$7+2,1)))-(YEAR($L$6)*12+MONTH($L$6)))+1)="✓",N($G14),IF(ISNUMBER(INDEX($L14:$W14,((YEAR(DATE(Настройки!$C$6,Настройки!$D$7+2,1))*12+MONTH(DATE(Настройки!$C$6,Настройки!$D$7+2,1)))-(YEAR($L$6)*12+MONTH($L$6)))+1)),INDEX($L14:$W14,((YEAR(DATE(Настройки!$C$6,Настройки!$D$7+2,1))*12+MONTH(DATE(Настройки!$C$6,Настройки!$D$7+2,1)))-(YEAR($L$6)*12+MONTH($L$6)))+1),IF(AND(OR($I14="",$I14<=(DATE(Настройки!$C$6,Настройки!$D$7+2+1,1)-1)),OR($J14="",$J14>=DATE(Настройки!$C$6,Настройки!$D$7+2,1)),MOD((YEAR(DATE(Настройки!$C$6,Настройки!$D$7+2,1))*12+MONTH(DATE(Настройки!$C$6,Настройки!$D$7+2,1)))-(YEAR(IF($I14="",$L$6,$I14))*12+MONTH(IF($I14="",$L$6,$I14))),MAX(1,N($H14)))=0),N($G14),0))),IF(AND(OR($I14="",$I14<=(DATE(Настройки!$C$6,Настройки!$D$7+2+1,1)-1)),OR($J14="",$J14>=DATE(Настройки!$C$6,Настройки!$D$7+2,1)),MOD((YEAR(DATE(Настройки!$C$6,Настройки!$D$7+2,1))*12+MONTH(DATE(Настройки!$C$6,Настройки!$D$7+2,1)))-(YEAR(IF($I14="",$L$6,$I14))*12+MONTH(IF($I14="",$L$6,$I14))),MAX(1,N($H14)))=0),N($G14),0)))
Y75: =IF(OR($C15="",$F15=""),"",DATE(YEAR($N$6),MONTH($N$6),MIN($F15,DAY((DATE(YEAR($N$6),MONTH($N$6)+1,1)-1))))) | Z75: =IF($C15="","",IF($D15="Доход","Доход","Расход")) | AA75: =IF($C15="","",$E15) | AB75: =IF($C15="",0,IF(AND(OR($I15="",$I15<=(DATE(YEAR($N$6),MONTH($N$6)+1,1)-1)),OR($J15="",$J15>=$N$6),MOD((YEAR($N$6)*12+MONTH($N$6))-(YEAR(IF($I15="",$L$6,$I15))*12+MONTH(IF($I15="",$L$6,$I15))),MAX(1,N($H15)))=0),N($G15),0)) | AC75: =IF($C15="",0,IF(N15="✓",N($G15),IF(ISNUMBER(N15),N15,0))) | AD75: =IF($C15="","",$N$6) | AE75: =IF($C15="","",$K15) | AG75: =IF(OR($C15="",$F15=""),"",DATE(YEAR(DATE(Настройки!$C$6,Настройки!$D$7+2,1)),MONTH(DATE(Настройки!$C$6,Настройки!$D$7+2,1)),MIN($F15,DAY((DATE(Настройки!$C$6,Настройки!$D$7+2+1,1)-1))))) | AH75: =IF($C15="","",IF($D15="Доход","Доход","Расход")) | AI75: =IF($C15="","",$E15) | AJ75: =IF($C15="",0,IF(AND(((YEAR(DATE(Настройки!$C$6,Настройки!$D$7+2,1))*12+MONTH(DATE(Настройки!$C$6,Настройки!$D$7+2,1)))-(YEAR($L$6)*12+MONTH($L$6)))>=0,((YEAR(DATE(Настройки!$C$6,Настройки!$D$7+2,1))*12+MONTH(DATE(Настройки!$C$6,Настройки!$D$7+2,1)))-(YEAR($L$6)*12+MONTH($L$6)))<=11),IF(INDEX($L15:$W15,((YEAR(DATE(Настройки!$C$6,Настройки!$D$7+2,1))*12+MONTH(DATE(Настройки!$C$6,Настройки!$D$7+2,1)))-(YEAR($L$6)*12+MONTH($L$6)))+1)="✓",N($G15),IF(ISNUMBER(INDEX($L15:$W15,((YEAR(DATE(Настройки!$C$6,Настройки!$D$7+2,1))*12+MONTH(DATE(Настройки!$C$6,Настройки!$D$7+2,1)))-(YEAR($L$6)*12+MONTH($L$6)))+1)),INDEX($L15:$W15,((YEAR(DATE(Настройки!$C$6,Настройки!$D$7+2,1))*12+MONTH(DATE(Настройки!$C$6,Настройки!$D$7+2,1)))-(YEAR($L$6)*12+MONTH($L$6)))+1),IF(AND(OR($I15="",$I15<=(DATE(Настройки!$C$6,Настройки!$D$7+2+1,1)-1)),OR($J15="",$J15>=DATE(Настройки!$C$6,Настройки!$D$7+2,1)),MOD((YEAR(DATE(Настройки!$C$6,Настройки!$D$7+2,1))*12+MONTH(DATE(Настройки!$C$6,Настройки!$D$7+2,1)))-(YEAR(IF($I15="",$L$6,$I15))*12+MONTH(IF($I15="",$L$6,$I15))),MAX(1,N($H15)))=0),N($G15),0))),IF(AND(OR($I15="",$I15<=(DATE(Настройки!$C$6,Настройки!$D$7+2+1,1)-1)),OR($J15="",$J15>=DATE(Настройки!$C$6,Настройки!$D$7+2,1)),MOD((YEAR(DATE(Настройки!$C$6,Настройки!$D$7+2,1))*12+MONTH(DATE(Настройки!$C$6,Настройки!$D$7+2,1)))-(YEAR(IF($I15="",$L$6,$I15))*12+MONTH(IF($I15="",$L$6,$I15))),MAX(1,N($H15)))=0),N($G15),0)))
Y76: =IF(OR($C16="",$F16=""),"",DATE(YEAR($N$6),MONTH($N$6),MIN($F16,DAY((DATE(YEAR($N$6),MONTH($N$6)+1,1)-1))))) | Z76: =IF($C16="","",IF($D16="Доход","Доход","Расход")) | AA76: =IF($C16="","",$E16) | AB76: =IF($C16="",0,IF(AND(OR($I16="",$I16<=(DATE(YEAR($N$6),MONTH($N$6)+1,1)-1)),OR($J16="",$J16>=$N$6),MOD((YEAR($N$6)*12+MONTH($N$6))-(YEAR(IF($I16="",$L$6,$I16))*12+MONTH(IF($I16="",$L$6,$I16))),MAX(1,N($H16)))=0),N($G16),0)) | AC76: =IF($C16="",0,IF(N16="✓",N($G16),IF(ISNUMBER(N16),N16,0))) | AD76: =IF($C16="","",$N$6) | AE76: =IF($C16="","",$K16) | AG76: =IF(OR($C16="",$F16=""),"",DATE(YEAR(DATE(Настройки!$C$6,Настройки!$D$7+2,1)),MONTH(DATE(Настройки!$C$6,Настройки!$D$7+2,1)),MIN($F16,DAY((DATE(Настройки!$C$6,Настройки!$D$7+2+1,1)-1))))) | AH76: =IF($C16="","",IF($D16="Доход","Доход","Расход")) | AI76: =IF($C16="","",$E16) | AJ76: =IF($C16="",0,IF(AND(((YEAR(DATE(Настройки!$C$6,Настройки!$D$7+2,1))*12+MONTH(DATE(Настройки!$C$6,Настройки!$D$7+2,1)))-(YEAR($L$6)*12+MONTH($L$6)))>=0,((YEAR(DATE(Настройки!$C$6,Настройки!$D$7+2,1))*12+MONTH(DATE(Настройки!$C$6,Настройки!$D$7+2,1)))-(YEAR($L$6)*12+MONTH($L$6)))<=11),IF(INDEX($L16:$W16,((YEAR(DATE(Настройки!$C$6,Настройки!$D$7+2,1))*12+MONTH(DATE(Настройки!$C$6,Настройки!$D$7+2,1)))-(YEAR($L$6)*12+MONTH($L$6)))+1)="✓",N($G16),IF(ISNUMBER(INDEX($L16:$W16,((YEAR(DATE(Настройки!$C$6,Настройки!$D$7+2,1))*12+MONTH(DATE(Настройки!$C$6,Настройки!$D$7+2,1)))-(YEAR($L$6)*12+MONTH($L$6)))+1)),INDEX($L16:$W16,((YEAR(DATE(Настройки!$C$6,Настройки!$D$7+2,1))*12+MONTH(DATE(Настройки!$C$6,Настройки!$D$7+2,1)))-(YEAR($L$6)*12+MONTH($L$6)))+1),IF(AND(OR($I16="",$I16<=(DATE(Настройки!$C$6,Настройки!$D$7+2+1,1)-1)),OR($J16="",$J16>=DATE(Настройки!$C$6,Настройки!$D$7+2,1)),MOD((YEAR(DATE(Настройки!$C$6,Настройки!$D$7+2,1))*12+MONTH(DATE(Настройки!$C$6,Настройки!$D$7+2,1)))-(YEAR(IF($I16="",$L$6,$I16))*12+MONTH(IF($I16="",$L$6,$I16))),MAX(1,N($H16)))=0),N($G16),0))),IF(AND(OR($I16="",$I16<=(DATE(Настройки!$C$6,Настройки!$D$7+2+1,1)-1)),OR($J16="",$J16>=DATE(Настройки!$C$6,Настройки!$D$7+2,1)),MOD((YEAR(DATE(Настройки!$C$6,Настройки!$D$7+2,1))*12+MONTH(DATE(Настройки!$C$6,Настройки!$D$7+2,1)))-(YEAR(IF($I16="",$L$6,$I16))*12+MONTH(IF($I16="",$L$6,$I16))),MAX(1,N($H16)))=0),N($G16),0)))
Y77: =IF(OR($C17="",$F17=""),"",DATE(YEAR($N$6),MONTH($N$6),MIN($F17,DAY((DATE(YEAR($N$6),MONTH($N$6)+1,1)-1))))) | Z77: =IF($C17="","",IF($D17="Доход","Доход","Расход")) | AA77: =IF($C17="","",$E17) | AB77: =IF($C17="",0,IF(AND(OR($I17="",$I17<=(DATE(YEAR($N$6),MONTH($N$6)+1,1)-1)),OR($J17="",$J17>=$N$6),MOD((YEAR($N$6)*12+MONTH($N$6))-(YEAR(IF($I17="",$L$6,$I17))*12+MONTH(IF($I17="",$L$6,$I17))),MAX(1,N($H17)))=0),N($G17),0)) | AC77: =IF($C17="",0,IF(N17="✓",N($G17),IF(ISNUMBER(N17),N17,0))) | AD77: =IF($C17="","",$N$6) | AE77: =IF($C17="","",$K17) | AG77: =IF(OR($C17="",$F17=""),"",DATE(YEAR(DATE(Настройки!$C$6,Настройки!$D$7+2,1)),MONTH(DATE(Настройки!$C$6,Настройки!$D$7+2,1)),MIN($F17,DAY((DATE(Настройки!$C$6,Настройки!$D$7+2+1,1)-1))))) | AH77: =IF($C17="","",IF($D17="Доход","Доход","Расход")) | AI77: =IF($C17="","",$E17) | AJ77: =IF($C17="",0,IF(AND(((YEAR(DATE(Настройки!$C$6,Настройки!$D$7+2,1))*12+MONTH(DATE(Настройки!$C$6,Настройки!$D$7+2,1)))-(YEAR($L$6)*12+MONTH($L$6)))>=0,((YEAR(DATE(Настройки!$C$6,Настройки!$D$7+2,1))*12+MONTH(DATE(Настройки!$C$6,Настройки!$D$7+2,1)))-(YEAR($L$6)*12+MONTH($L$6)))<=11),IF(INDEX($L17:$W17,((YEAR(DATE(Настройки!$C$6,Настройки!$D$7+2,1))*12+MONTH(DATE(Настройки!$C$6,Настройки!$D$7+2,1)))-(YEAR($L$6)*12+MONTH($L$6)))+1)="✓",N($G17),IF(ISNUMBER(INDEX($L17:$W17,((YEAR(DATE(Настройки!$C$6,Настройки!$D$7+2,1))*12+MONTH(DATE(Настройки!$C$6,Настройки!$D$7+2,1)))-(YEAR($L$6)*12+MONTH($L$6)))+1)),INDEX($L17:$W17,((YEAR(DATE(Настройки!$C$6,Настройки!$D$7+2,1))*12+MONTH(DATE(Настройки!$C$6,Настройки!$D$7+2,1)))-(YEAR($L$6)*12+MONTH($L$6)))+1),IF(AND(OR($I17="",$I17<=(DATE(Настройки!$C$6,Настройки!$D$7+2+1,1)-1)),OR($J17="",$J17>=DATE(Настройки!$C$6,Настройки!$D$7+2,1)),MOD((YEAR(DATE(Настройки!$C$6,Настройки!$D$7+2,1))*12+MONTH(DATE(Настройки!$C$6,Настройки!$D$7+2,1)))-(YEAR(IF($I17="",$L$6,$I17))*12+MONTH(IF($I17="",$L$6,$I17))),MAX(1,N($H17)))=0),N($G17),0))),IF(AND(OR($I17="",$I17<=(DATE(Настройки!$C$6,Настройки!$D$7+2+1,1)-1)),OR($J17="",$J17>=DATE(Настройки!$C$6,Настройки!$D$7+2,1)),MOD((YEAR(DATE(Настройки!$C$6,Настройки!$D$7+2,1))*12+MONTH(DATE(Настройки!$C$6,Настройки!$D$7+2,1)))-(YEAR(IF($I17="",$L$6,$I17))*12+MONTH(IF($I17="",$L$6,$I17))),MAX(1,N($H17)))=0),N($G17),0)))
Y78: =IF(OR($C18="",$F18=""),"",DATE(YEAR($N$6),MONTH($N$6),MIN($F18,DAY((DATE(YEAR($N$6),MONTH($N$6)+1,1)-1))))) | Z78: =IF($C18="","",IF($D18="Доход","Доход","Расход")) | AA78: =IF($C18="","",$E18) | AB78: =IF($C18="",0,IF(AND(OR($I18="",$I18<=(DATE(YEAR($N$6),MONTH($N$6)+1,1)-1)),OR($J18="",$J18>=$N$6),MOD((YEAR($N$6)*12+MONTH($N$6))-(YEAR(IF($I18="",$L$6,$I18))*12+MONTH(IF($I18="",$L$6,$I18))),MAX(1,N($H18)))=0),N($G18),0)) | AC78: =IF($C18="",0,IF(N18="✓",N($G18),IF(ISNUMBER(N18),N18,0))) | AD78: =IF($C18="","",$N$6) | AE78: =IF($C18="","",$K18) | AG78: =IF(OR($C18="",$F18=""),"",DATE(YEAR(DATE(Настройки!$C$6,Настройки!$D$7+2,1)),MONTH(DATE(Настройки!$C$6,Настройки!$D$7+2,1)),MIN($F18,DAY((DATE(Настройки!$C$6,Настройки!$D$7+2+1,1)-1))))) | AH78: =IF($C18="","",IF($D18="Доход","Доход","Расход")) | AI78: =IF($C18="","",$E18) | AJ78: =IF($C18="",0,IF(AND(((YEAR(DATE(Настройки!$C$6,Настройки!$D$7+2,1))*12+MONTH(DATE(Настройки!$C$6,Настройки!$D$7+2,1)))-(YEAR($L$6)*12+MONTH($L$6)))>=0,((YEAR(DATE(Настройки!$C$6,Настройки!$D$7+2,1))*12+MONTH(DATE(Настройки!$C$6,Настройки!$D$7+2,1)))-(YEAR($L$6)*12+MONTH($L$6)))<=11),IF(INDEX($L18:$W18,((YEAR(DATE(Настройки!$C$6,Настройки!$D$7+2,1))*12+MONTH(DATE(Настройки!$C$6,Настройки!$D$7+2,1)))-(YEAR($L$6)*12+MONTH($L$6)))+1)="✓",N($G18),IF(ISNUMBER(INDEX($L18:$W18,((YEAR(DATE(Настройки!$C$6,Настройки!$D$7+2,1))*12+MONTH(DATE(Настройки!$C$6,Настройки!$D$7+2,1)))-(YEAR($L$6)*12+MONTH($L$6)))+1)),INDEX($L18:$W18,((YEAR(DATE(Настройки!$C$6,Настройки!$D$7+2,1))*12+MONTH(DATE(Настройки!$C$6,Настройки!$D$7+2,1)))-(YEAR($L$6)*12+MONTH($L$6)))+1),IF(AND(OR($I18="",$I18<=(DATE(Настройки!$C$6,Настройки!$D$7+2+1,1)-1)),OR($J18="",$J18>=DATE(Настройки!$C$6,Настройки!$D$7+2,1)),MOD((YEAR(DATE(Настройки!$C$6,Настройки!$D$7+2,1))*12+MONTH(DATE(Настройки!$C$6,Настройки!$D$7+2,1)))-(YEAR(IF($I18="",$L$6,$I18))*12+MONTH(IF($I18="",$L$6,$I18))),MAX(1,N($H18)))=0),N($G18),0))),IF(AND(OR($I18="",$I18<=(DATE(Настройки!$C$6,Настройки!$D$7+2+1,1)-1)),OR($J18="",$J18>=DATE(Настройки!$C$6,Настройки!$D$7+2,1)),MOD((YEAR(DATE(Настройки!$C$6,Настройки!$D$7+2,1))*12+MONTH(DATE(Настройки!$C$6,Настройки!$D$7+2,1)))-(YEAR(IF($I18="",$L$6,$I18))*12+MONTH(IF($I18="",$L$6,$I18))),MAX(1,N($H18)))=0),N($G18),0)))
